Workbook

Sheet Summary
A1: Global Search V2 — automated test results
A3: Environment | B3: Staging
A4: Build tested | B4: v26.40.3-36ebbb0
A5: Run date | B5: 2 October 2026 (full run); fixed tests re-run 2–3 October 2026, same build
A6: How it was run | B6: npm test from a fresh copy of the branch: the data was seeded and checked first, then every spec ran. Failures caused by the tests themselves were then fixed and those test files re-run on the same build.
A7: Recorded in TestRail? | B7: No — by instruction, this run is reported only in this file.
A8: Test run these cases belong to | B8: Run 415
A10: Result | B10: Tests | C10: What it means
A11: Passed | B11: =COUNTIF('All results'!$E:$E,A11) -> 218 | C11: The product did what the requirement says.
A12: Failed — possible new problem | B12: =COUNTIF('All results'!$E:$E,A12) -> 7 | C12: The product did not, and no ticket describes it. Not yet checked against the requirement; nothing raised.
A13: Failed — already reported | B13: =COUNTIF('All results'!$E:$E,A13) -> 9 | C13: The product did not, in a way a filed ticket already describes. Nothing new.
A14: Failed — our test's fault | B14: =COUNTIF('All results'!$E:$E,A14) -> 18 | C14: The test was at fault, not the product. Fixed; see the re-run result on each row.
A15: Known fault — still there | B15: =COUNTIF('All results'!$E:$E,A15) -> 21 | C15: A fault already in a ticket is still present. Expected.
A16: Known fault — did not reproduce | B16: =COUNTIF('All results'!$E:$E,A16) -> 1 | C16: A known fault did not happen this time — possibly fixed. Worth checking by hand.
A17: Stood down | B17: =COUNTIF('All results'!$E:$E,A17) -> 64 | C17: Not judged: something the test needs was missing. The reason is on each row.
A18: Total | B18: =SUM(B11:B17) -> 338 | C18: Should equal the number of tests in the suite (338).
A19: Of the test's-fault failures: passed when re-run after the fix | B19: =COUNTIFS('All results'!$E:$E,"Failed — our test's fault",'All results'!$N:$N,"Passed") -> 18 | C19: Each was a fault in the test, not the product, and has been fixed. Should equal the line above it in the table.
A21: Failures by what happened | B21: Tests
A22: A contact's e-mail match shows a different detail of the record instead of the e-mail. | B22: =COUNTIF('All results'!$F:$F,A22) -> 0
A23: None of the 65 rows for the typed text carried a highlight. | B23: =COUNTIF('All results'!$F:$F,A23) -> 0
A24: Parts: the whole part name is highlighted, instead of just the typed part inside it. | B24: =COUNTIF('All results'!$F:$F,A24) -> 0
A25: Purchase orders: a received order is listed above one still on order. | B25: =COUNTIF('All results'!$F:$F,A25) -> 0
A26: The customer row does not show the telephone on hover. | B26: =COUNTIF('All results'!$F:$F,A26) -> 0
A27: The row shows only the characters typed, not the whole value that matched. | B27: =COUNTIF('All results'!$F:$F,A27) -> 0
A28: The search box did not open in time, in the file whose other tests had just failed on the wrong server. | B28: =COUNTIF('All results'!$F:$F,A28) -> 0
A29: The search box did not respond to a click within 60 seconds — test timing, not a product behaviour. | B29: =COUNTIF('All results'!$F:$F,A29) -> 0
A30: The test failed on a row that matched on a detail it does not display, which cannot show where a highlight sits. | B30: =COUNTIF('All results'!$F:$F,A30) -> 0
A31: The test looked for a technician by a first name that exists only on the old QA branch, so it never switched person and measured what an administrator sees. | B31: =COUNTIF('All results'!$F:$F,A31) -> 0
A32: The test looked for the two suppliers it had just created in a list that did not include them, and crashed. | B32: =COUNTIF('All results'!$F:$F,A32) -> 0
A33: The test sent its requests to the production server instead of staging (a server address written into one helper). | B33: =COUNTIF('All results'!$F:$F,A33) -> 0
... A36: Vehicles: two different vehicles (same unit number, different serial number) read identically in the results. | B36: =COUNTIF('All results'!$F:$F,A36) -> 0
A39: Spec file | B39: Passed | C39: Possible new | D39: Already reported | E39: Our test | F39: Known still there | G39: Known gone | H39: Stood down
A40: C146197-C146208-sri-work-orders.spec.ts | B40: =COUNTIFS('All results'!$K:$K,$A40,'All results'!$E:$E,"Passed") -> 6 | C40: =COUNTIFS('All results'!$K:$K,$A40,'All results'!$E:$E,"Failed — possible new problem") -> 0 | D40: =COUNTIFS('All results'!$K:$K,$A40,'All results'!$E:$E,"Failed — already reported") -> 0 | E40: =COUNTIFS('All results'!$K:$K,$A40,'All results'!$E:$E,"Failed — our test's fault") -> 0 | F40: =COUNTIFS('All results'!$K:$K,$A40,'All results'!$E:$E,"Known fault — still there") -> 0 | G40: =COUNTIFS('All results'!$K:$K,$A40,'All results'!$E:$E,"Known fault — did not reproduce") -> 0 | H40: =COUNTIFS('All results'!$K:$K,$A40,'All results'!$E:$E,"Stood down") -> 1
A41: C146202-C146282-sri-retest-full-value.spec.ts | B41: =COUNTIFS('All results'!$K:$K,$A41,'All results'!$E:$E,"Passed") -> 5 | C41: =COUNTIFS('All results'!$K:$K,$A41,'All results'!$E:$E,"Failed — possible new problem") -> 1 | D41: =COUNTIFS('All results'!$K:$K,$A41,'All results'!$E:$E,"Failed — already reported") -> 7 | E41: =COUNTIFS('All results'!$K:$K,$A41,'All results'!$E:$E,"Failed — our test's fault") -> 0 | F41: =COUNTIFS('All results'!$K:$K,$A41,'All results'!$E:$E,"Known fault — still there") -> 15 | G41: =COUNTIFS('All results'!$K:$K,$A41,'All results'!$E:$E,"Known fault — did not reproduce") -> 0 | H41: =COUNTIFS('All results'!$K:$K,$A41,'All results'!$E:$E,"Stood down") -> 0
A42: C146209-C146223-sri-customers.spec.ts | B42: =COUNTIFS('All results'!$K:$K,$A42,'All results'!$E:$E,"Passed") -> 3 | C42: =COUNTIFS('All results'!$K:$K,$A42,'All results'!$E:$E,"Failed — possible new problem") -> 0 | D42: =COUNTIFS('All results'!$K:$K,$A42,'All results'!$E:$E,"Failed — already reported") -> 2 | E42: =COUNTIFS('All results'!$K:$K,$A42,'All results'!$E:$E,"Failed — our test's fault") -> 0 | F42: =COUNTIFS('All results'!$K:$K,$A42,'All results'!$E:$E,"Known fault — still there") -> 0 | G42: =COUNTIFS('All results'!$K:$K,$A42,'All results'!$E:$E,"Known fault — did not reproduce") -> 0 | H42: =COUNTIFS('All results'!$K:$K,$A42,'All results'!$E:$E,"Stood down") -> 1
A43: C146224-C146284-sri-entities.spec.ts | B43: =COUNTIFS('All results'!$K:$K,$A43,'All results'!$E:$E,"Passed") -> 28 | C43: =COUNTIFS('All results'!$K:$K,$A43,'All results'!$E:$E,"Failed — possible new problem") -> 4 | D43: =COUNTIFS('All results'!$K:$K,$A43,'All results'!$E:$E,"Failed — already reported") -> 0 | E43: =COUNTIFS('All results'!$K:$K,$A43,'All results'!$E:$E,"Failed — our test's fault") -> 4 | F43: =COUNTIFS('All results'!$K:$K,$A43,'All results'!$E:$E,"Known fault — still there") -> 0 | G43: =COUNTIFS('All results'!$K:$K,$A43,'All results'!$E:$E,"Known fault — did not reproduce") -> 0 | H43: =COUNTIFS('All results'!$K:$K,$A43,'All results'!$E:$E,"Stood down") -> 6
A44: C146285-C146306-sri-all-tab.spec.ts | B44: =COUNTIFS('All results'!$K:$K,$A44,'All results'!$E:$E,"Passed") -> 19 | C44: =COUNTIFS('All results'!$K:$K,$A44,'All results'!$E:$E,"Failed — possible new problem") -> 0 | D44: =COUNTIFS('All results'!$K:$K,$A44,'All results'!$E:$E,"Failed — already reported") -> 0 | E44: =COUNTIFS('All results'!$K:$K,$A44,'All results'!$E:$E,"Failed — our test's fault") -> 1 | F44: =COUNTIFS('All results'!$K:$K,$A44,'All results'!$E:$E,"Known fault — still there") -> 0 | G44: =COUNTIFS('All results'!$K:$K,$A44,'All results'!$E:$E,"Known fault — did not reproduce") -> 1 | H44: =COUNTIFS('All results'!$K:$K,$A44,'All results'!$E:$E,"Stood down") -> 1
A45: C44804-C55683-panel-keyboard.spec.ts | B45: =COUNTIFS('All results'!$K:$K,$A45,'All results'!$E:$E,"Passed") -> 10 | C45: =COUNTIFS('All results'!$K:$K,$A45,'All results'!$E:$E,"Failed — possible new problem") -> 0 | D45: =COUNTIFS('All results'!$K:$K,$A45,'All results'!$E:$E,"Failed — already reported") -> 0 | E45: =COUNTIFS('All results'!$K:$K,$A45,'All results'!$E:$E,"Failed — our test's fault") -> 1 | F45: =COUNTIFS('All results'!$K:$K,$A45,'All results'!$E:$E,"Known fault — still there") -> 0 | G45: =COUNTIFS('All results'!$K:$K,$A45,'All results'!$E:$E,"Known fault — did not reproduce") -> 0 | H45: =COUNTIFS('All results'!$K:$K,$A45,'All results'!$E:$E,"Stood down") -> 0
A46: access-and-location.spec.ts | B46: =COUNTIFS('All results'!$K:$K,$A46,'All results'!$E:$E,"Passed") -> 1 | C46: =COUNTIFS('All results'!$K:$K,$A46,'All results'!$E:$E,"Failed — possible new problem") -> 0 | D46: =COUNTIFS('All results'!$K:$K,$A46,'All results'!$E:$E,"Failed — already reported") -> 0 | E46: =COUNTIFS('All results'!$K:$K,$A46,'All results'!$E:$E,"Failed — our test's fault") -> 5 | F46: =COUNTIFS('All results'!$K:$K,$A46,'All results'!$E:$E,"Known fault — still there") -> 0 | G46: =COUNTIFS('All results'!$K:$K,$A46,'All results'!$E:$E,"Known fault — did not reproduce") -> 0 | H46: =COUNTIFS('All results'!$K:$K,$A46,'All results'!$E:$E,"Stood down") -> 0
A47: counts-and-ranking.spec.ts | B47: =COUNTIFS('All results'!$K:$K,$A47,'All results'!$E:$E,"Passed") -> 0 | C47: =COUNTIFS('All results'!$K:$K,$A47,'All results'!$E:$E,"Failed — possible new problem") -> 1 | D47: =COUNTIFS('All results'!$K:$K,$A47,'All results'!$E:$E,"Failed — already reported") -> 0 | E47: =COUNTIFS('All results'!$K:$K,$A47,'All results'!$E:$E,"Failed — our test's fault") -> 1 | F47: =COUNTIFS('All results'!$K:$K,$A47,'All results'!$E:$E,"Known fault — still there") -> 2 | G47: =COUNTIFS('All results'!$K:$K,$A47,'All results'!$E:$E,"Known fault — did not reproduce") -> 0 | H47: =COUNTIFS('All results'!$K:$K,$A47,'All results'!$E:$E,"Stood down") -> 1
A48: findability-matching.spec.ts | B48: =COUNTIFS('All results'!$K:$K,$A48,'All results'!$E:$E,"Passed") -> 10 | C48: =COUNTIFS('All results'!$K:$K,$A48,'All results'!$E:$E,"Failed — possible new problem") -> 1 | D48: =COUNTIFS('All results'!$K:$K,$A48,'All results'!$E:$E,"Failed — already reported") -> 0 | E48: =COUNTIFS('All results'!$K:$K,$A48,'All results'!$E:$E,"Failed — our test's fault") -> 0 | F48: =COUNTIFS('All results'!$K:$K,$A48,'All results'!$E:$E,"Known fault — still there") -> 0 | G48: =COUNTIFS('All results'!$K:$K,$A48,'All results'!$E:$E,"Known fault — did not reproduce") -> 0 | H48: =COUNTIFS('All results'!$K:$K,$A48,'All results'!$E:$E,"Stood down") -> 9
A49: findability.spec.ts | B49: =COUNTIFS('All results'!$K:$K,$A49,'All results'!$E:$E,"Passed") -> 13 | C49: =COUNTIFS('All results'!$K:$K,$A49,'All results'!$E:$E,"Failed — possible new problem") -> 0 | D49: =COUNTIFS('All results'!$K:$K,$A49,'All results'!$E:$E,"Failed — already reported") -> 0 | E49: =COUNTIFS('All results'!$K:$K,$A49,'All results'!$E:$E,"Failed — our test's fault") -> 0 | F49: =COUNTIFS('All results'!$K:$K,$A49,'All results'!$E:$E,"Known fault — still there") -> 3 | G49: =COUNTIFS('All results'!$K:$K,$A49,'All results'!$E:$E,"Known fault — did not reproduce") -> 0 | H49: =COUNTIFS('All results'!$K:$K,$A49,'All results'!$E:$E,"Stood down") -> 10
A50: panel.spec.ts | B50: =COUNTIFS('All results'!$K:$K,$A50,'All results'!$E:$E,"Passed") -> 10 | C50: =COUNTIFS('All results'!$K:$K,$A50,'All results'!$E:$E,"Failed — possible new problem") -> 0 | D50: =COUNTIFS('All results'!$K:$K,$A50,'All results'!$E:$E,"Failed — already reported") -> 0 | E50: =COUNTIFS('All results'!$K:$K,$A50,'All results'!$E:$E,"Failed — our test's fault") -> 0 | F50: =COUNTIFS('All results'!$K:$K,$A50,'All results'!$E:$E,"Known fault — still there") -> 1 | G50: =COUNTIFS('All results'!$K:$K,$A50,'All results'!$E:$E,"Known fault — did not reproduce") -> 0 | H50: =COUNTIFS('All results'!$K:$K,$A50,'All results'!$E:$E,"Stood down") -> 0
A51: permissions-two-accounts.spec.ts | B51: =COUNTIFS('All results'!$K:$K,$A51,'All results'!$E:$E,"Passed") -> 13 | C51: =COUNTIFS('All results'!$K:$K,$A51,'All results'!$E:$E,"Failed — possible new problem") -> 0 | D51: =COUNTIFS('All results'!$K:$K,$A51,'All results'!$E:$E,"Failed — already reported") -> 0 | E51: =COUNTIFS('All results'!$K:$K,$A51,'All results'!$E:$E,"Failed — our test's fault") -> 0 | F51: =COUNTIFS('All results'!$K:$K,$A51,'All results'!$E:$E,"Known fault — still there") -> 0 | G51: =COUNTIFS('All results'!$K:$K,$A51,'All results'!$E:$E,"Known fault — did not reproduce") -> 0 | H51: =COUNTIFS('All results'!$K:$K,$A51,'All results'!$E:$E,"Stood down") -> 7
... A59: tabs-groups-navigation.spec.ts | B59: =COUNTIFS('All results'!$K:$K,$A59,'All results'!$E:$E,"Passed") -> 16 | C59: =COUNTIFS('All results'!$K:$K,$A59,'All results'!$E:$E,"Failed — possible new problem") -> 0 | D59: =COUNTIFS('All results'!$K:$K,$A59,'All results'!$E:$E,"Failed — already reported") -> 0 | E59: =COUNTIFS('All results'!$K:$K,$A59,'All results'!$E:$E,"Failed — our test's fault") -> 0 | F59: =COUNTIFS('All results'!$K:$K,$A59,'All results'!$E:$E,"Known fault — still there") -> 0 | G59: =COUNTIFS('All results'!$K:$K,$A59,'All results'!$E:$E,"Known fault — did not reproduce") -> 0 | H59: =COUNTIFS('All results'!$K:$K,$A59,'All results'!$E:$E,"Stood down") -> 0

Sheet All results
A1: Every test in this run, one row each. The Summary counts are formulas over this sheet.
A2: Case | B2: Case in TestRail | C2: Test run | D2: What the test checks | E2: Result | F2: Likely cause | G2: What happened | H2: What needs to be done | I2: Ticket | J2: Ticket status (read live) | K2: Spec file | L2: Line | M2: Seconds | N2: Re-run after fixing the test | O2: Re-run detail
A3: C146216 | B3: Open case | C3: Run 415 | D3: C146216 — SRI-CUST-C3 — A match on a contact's email address shows the FULL value on the | E3: Failed — possible new problem | G3: Error: the note shows neither the whole value "zzautotest.nophone@staging.shopview.local" nor the text typed — it shows a different detail of the record altogether: ["Contact match: ZZAUTOTEST"] expect(received).toHaveLength(expected) Expected length: 0 Received length: 1 Received array: ["Contact match: ZZAUTOTEST"] 170 | expect(wrongValue, 171 | `the note shows neither the whole value "${term}" nor the text typed — it shows a ` + > 172 | `different detail of the record altogether: ${JSON.stringify(wrongValue)}`).toHaveLength(0); | ^ 173 | return; 174 | } 175 | at /tmp/claude-0/-home-user-Man | H3: Check it against the requirement as it reads today (not yet done), then decide whether to raise it. Nothing has been raised. | K3: C146202-C146282-sri-retest-full-value.spec.ts | L3: 83 | M3: 31.6
A4: C146233 | B4: Open case | C4: Run 415 | D4: C146233 — Parts: the whole part number is shown, with the typed part marked inside it | E4: Failed — possible new problem | G4: Error: row 1: the WHOLE value "ZZLONGROW Heavy Duty Air Brake" is highlighted rather than just the typed "ZZLONGROW" within it, so nothing marks which part actually matched expect(received).toBeGreaterThan(expected) Expected: > 0 Received: 0 260 | expect(unmarked.length, 261 | `row ${r.index}: the WHOLE value "${r.title.text}" is highlighted rather than just the ` + > 262 | `typed "${TERM}" within it, so nothing marks which part actually matched`).toBeGreaterThan(0); | ^ 263 | expect(r.title.clipped, 264 | `row ${r.index} is cut short — it paints ${r.title.clientW}px of ${r.title.scrollW}px an | H4: Check it against the requirement as it reads today (not yet done), then decide whether to raise it. Nothing has been raised. | K4: C146224-C146284-sri-entities.spec.ts | L4: 232 | M4: 9.8 | N4: Failed | O4: Error: row 1: the WHOLE value "ZZLONGROW Heavy Duty Air Brake" is highlighted rather than just the typed "ZZLONGROW" within it, so nothing marks which part actually matched expect(received).toBeGreaterThan(expected) Expected: > 0 Received: 0 282 | expect(unmarked.length, 283 | `row ${r.index}: the WHOLE value "${r.title.text}" is highlighted rather than just the ` + > 284 | `typed "${TERM}" within
A5: C146235 | B5: Open case | C5: Run 415 | D5: C146235 — Parts: the highlight marks the match inside the text, not instead of it | E5: Failed — possible new problem | G5: Error: row 1: every piece of "ZZLONGROW Heavy Duty Air Brake" is highlighted, so the mark covers the whole value instead of the typed "ZZLONGROW" inside it expect(received).toBe(expected) // Object.is equality Expected: true Received: false 315 | expect(r.title.segs.some((x) => !x.marked), 316 | `row ${r.index}: every piece of "${r.title.text}" is highlighted, so the mark covers the ` + > 317 | `whole value instead of the typed "${TERM}" inside it`).toBe(true); | ^ 318 | const rebuilt = r.title.segs.map((x) => x.text).join('').replace(/\s+/g, ' ').trim(); 319 | expect(rebuilt, `row ${r.index}: | H5: Check it against the requirement as it reads today (not yet done), then decide whether to raise it. Nothing has been raised. | K5: C146224-C146284-sri-entities.spec.ts | L5: 305 | M5: 9.8 | N5: Failed | O5: Error: row 1: every piece of "ZZLONGROW Heavy Duty Air Brake" is highlighted, so the mark covers the whole value instead of the typed "ZZLONGROW" inside it expect(received).toBe(expected) // Object.is equality Expected: true Received: false 336 | expect(r.title.segs.some((x) => !x.marked), 337 | `row ${r.index}: every piece of "${r.title.text}" is highlighted, so the mark covers the ` + > 338 | `w
A6: C146227 | B6: Open case | C6: Run 415 | D6: C146227 — Assets: two records sharing the typed text can be told apart | E6: Failed — possible new problem | G6: Error: these rows read identically to a person: ["ZZLONGROW-123786 · 2021 Rowcheck Trucks Longhauler | | ZZLONGROW Heavy Haulage And Trailer Repair Services Of Greater Fernvale 123786"] expect(received).toHaveLength(expected) Expected length: 0 Received length: 1 Received array: ["ZZLONGROW-123786 · 2021 Rowcheck Trucks Longhauler | | ZZLONGROW Heavy Haulage And Trailer Repair Services Of Greater Fernvale 123786"] 331 | const seen = rows.map(visibleRow); 332 | const dupes = seen.filter((v, i) => seen.indexOf(v) !== i); > 333 | expect(dupes, `these rows read identically to a person: ${JSON.stri | H6: Check it against the requirement as it reads today (not yet done), then decide whether to raise it. Nothing has been raised. | K6: C146224-C146284-sri-entities.spec.ts | L6: 324 | M6: 9.8 | N6: Failed | O6: Error: these rows read identically to a person: ["ZZLONGROW-123786 · 2021 Rowcheck Trucks Longhauler | | ZZLONGROW Heavy Haulage And Trailer Repair Services Of Greater Fernvale 123786"] expect(received).toHaveLength(expected) Expected length: 0 Received length: 1 Received array: ["ZZLONGROW-123786 · 2021 Rowcheck Trucks Longhauler | | ZZLONGROW Heavy Haulage And Trailer Repair Services Of Greater
A7: C146228 | B7: Open case | C7: Run 415 | D7: C146228 — Assets: records with the same bold line differ somewhere you can see | E7: Failed — possible new problem | G7: Error: rows 1,2 share the bold line "ZZLONGROW-123786 · 2021 Rowcheck Trucks Longhauler" and nothing visible separates them: [" | ZZLONGROW Heavy Haulage And Trailer Repair Services Of Greater Fernvale 123786"," | ZZLONGROW Heavy Haulage And Trailer Repair Services Of Greater Fernvale 123786"] expect(received).toBe(expected) // Object.is equality Expected: 2 Received: 1 348 | expect(new Set(rest).size, 349 | `rows ${group.map((r) => r.index).join(',')} share the bold line "${title}" and nothing visible ` + > 350 | `separates them: ${JSON.stringify(rest)}`).toBe(group.length); | ^ 351 | } 352 | | H7: Check it against the requirement as it reads today (not yet done), then decide whether to raise it. Nothing has been raised. | K7: C146224-C146284-sri-entities.spec.ts | L7: 336 | M7: 10 | N7: Failed | O7: Error: rows 1,2 share the bold line "ZZLONGROW-123786 · 2021 Rowcheck Trucks Longhauler" and nothing visible separates them: [" | ZZLONGROW Heavy Haulage And Trailer Repair Services Of Greater Fernvale 123786"," | ZZLONGROW Heavy Haulage And Trailer Repair Services Of Greater Fernvale 123786"] expect(received).toBe(expected) // Object.is equality Expected: 2 Received: 1 369 | expect(new Set(rest).
A8: C45137 | B8: Open case | C8: Run 415 | D8: C45137 — still-ordered purchase orders rank above received ones | E8: Failed — possible new problem | G8: Error: a received order is above a still-ordered one: ["Partial","Ordered","Ordered","Ordered","Ordered","Partial","Partial","Ordered","Partial","Partial","Partial","Received","Received","Received","Received","Ordered","Received","Received","Received"] expect(received).toBeLessThan(expected) Expected: < 11 Received: 15 70 | const firstReceived = seq.indexOf('Received'); 71 | if (lastOrdered >= 0 && firstReceived >= 0) { > 72 | expect(lastOrdered, `a received order is above a still-ordered one: ${JSON.stringify(seq)}`).toBeLessThan(firstReceived); | ^ 73 | } 74 | // NOT asserted: where "Partial | H8: Check it against the requirement as it reads today (not yet done), then decide whether to raise it. Nothing has been raised. | K8: counts-and-ranking.spec.ts | L8: 57 | M8: 19 | N8: Failed | O8: Error: a received order is above a still-ordered one: ["Partial","Ordered","Ordered","Ordered","Ordered","Partial","Partial","Ordered","Partial","Partial","Partial","Received","Received","Received","Received","Ordered","Received","Received","Received"] expect(received).toBeLessThan(expected) Expected: < 11 Received: 15 70 | const firstReceived = seq.indexOf('Received'); 71 | if (lastOrdered >= 0 &
A9: C44828 | B9: Open case | C9: Run 415 | D9: C44828 — the typed text is highlighted inside each matching row | E9: Failed — possible new problem | G9: Error: 65 of 65 rows carry no highlight at all expect(received).toBe(expected) // Object.is equality Expected: 0 Received: 65 264 | expect(r.length, `"${word}" finds nothing`).toBeGreaterThan(0); 265 | const unmarked = r.filter(x => x.marks.length === 0).length; > 266 | expect(unmarked, `${unmarked} of ${r.length} rows carry no highlight at all`).toBe(0); | ^ 267 | }); 268 | 269 | test('C44848 — a close match is drawn as a close match @C44848', async () => { at /tmp/claude-0/-home-user-Manual-test-Cases/126e0959-4bca-54ed-8b95-71a191ca38d1/scratchpad/clean3/repo/build/global-search/e2e/tests/f | H9: Check it against the requirement as it reads today (not yet done), then decide whether to raise it. Nothing has been raised. | K9: findability-matching.spec.ts | L9: 261 | M9: 8.1
A10: C146205 | B10: Open case | C10: Run 415 | D10: C146205 — SRI-WO-C4 — A match on line item descriptions (parts and labor on the WO) show | E10: Failed — already reported | G10: Error: these rows show only the characters typed instead of the whole value: ["Part number: \n786","Part number: \n786","Part description: \n786","Part description: \n786","Part description: \n786","Part description: \n786","Part description: \n786"] expect(received).toHaveLength(expected) Expected length: 0 Received length: 7 Received array: ["Part number:· 786", "Part number:· 786", "Part description:· 786", "Part description:· 786", "Part description:· 786", "Part description:· 786", "Part description:· 786"] 187 | expect(onlyTyped, 188 | `these rows show only the characters typed instead o | H10: Nothing new to raise: this is the behaviour SV-10634 describes (status Ready to Fix). It should pass once that fix reaches this build. | I10: SV-10634 | J10: Ready to Fix | K10: C146202-C146282-sri-retest-full-value.spec.ts | L10: 83 | M10: 17.7
A11: C146206 | B11: Open case | C11: Run 415 | D11: C146206 — SRI-WO-C5 — A match on part numbers on the work order's lines (`item_part_numb | E11: Failed — already reported | G11: Error: these rows show only the characters typed instead of the whole value: ["Part number: \n786","Part number: \n786","Part description: \n786","Part description: \n786","Part description: \n786","Part description: \n786","Part description: \n786"] expect(received).toHaveLength(expected) Expected length: 0 Received length: 7 Received array: ["Part number:· 786", "Part number:· 786", "Part description:· 786", "Part description:· 786", "Part description:· 786", "Part description:· 786", "Part description:· 786"] 187 | expect(onlyTyped, 188 | `these rows show only the characters typed instead o | H11: Nothing new to raise: this is the behaviour SV-10634 describes (status Ready to Fix). It should pass once that fix reaches this build. | I11: SV-10634 | J11: Ready to Fix | K11: C146202-C146282-sri-retest-full-value.spec.ts | L11: 83 | M11: 19.4
A12: C146238 | B12: Open case | C12: Run 415 | D12: C146238 — SRI-PART-C1 — A match on bin location shows the FULL value on the row | E12: Failed — already reported | G12: Error: these rows show only the characters typed instead of the whole value: ["Bin: \nH3B","Bin: \nH3B","Bin: \nH3B","Bin: \nH3B","Bin: \nH3B","Bin: \nH3B","Bin: \nH3B","Bin: \nH3B","Bin: \nH3B","Bin: \nH3B","Bin: \nH3B","Bin: \nH3B","Bin: \nH3B","Bin: \nH3B","Bin: \nH3B","Bin: \nH3B","Bin: \nH3B","Bin: \nH3B","Bin: \nH3B","Bin: \nH3B"] expect(received).toHaveLength(expected) Expected length: 0 Received length: 20 Received array: ["Bin:· H3B", "Bin:· H3B", "Bin:· H3B", "Bin:· H3B", "Bin:· H3B", "Bin:· H3B", "Bin:· H3B", "Bin:· H3B", "Bin:· H3B", "Bin:· H3B", …] 187 | expect(onlyTyped, 188 | `t | H12: Nothing new to raise: this is the behaviour SV-10634 describes (status Ready to Fix). It should pass once that fix reaches this build. | I12: SV-10634 | J12: Ready to Fix | K12: C146202-C146282-sri-retest-full-value.spec.ts | L12: 83 | M12: 17.6
A13: C146242 | B13: Open case | C13: Run 415 | D13: C146242 — SRI-PART-C5 — A match on tags shows the FULL value on the row | E13: Failed — already reported | G13: Error: these rows show only the characters typed instead of the whole value: ["Tag: \n496","Tag: \n496"] expect(received).toHaveLength(expected) Expected length: 0 Received length: 2 Received array: ["Tag:· 496", "Tag:· 496"] 187 | expect(onlyTyped, 188 | `these rows show only the characters typed instead of the whole value: ${JSON.stringify(onlyTyped)}`) > 189 | .toHaveLength(0); | ^ 190 | }); 191 | } 192 | at /tmp/claude-0/-home-user-Manual-test-Cases/126e0959-4bca-54ed-8b95-71a191ca38d1/scratchpad/clean3/repo/build/global-search/e2e/tests/C146202-C146282-sri-retest-full-value.spec.ts:189:8 | H13: Nothing new to raise: this is the behaviour SV-10634 describes (status Ready to Fix). It should pass once that fix reaches this build. | I13: SV-10634 | J13: Ready to Fix | K13: C146202-C146282-sri-retest-full-value.spec.ts | L13: 83 | M13: 18.4
A14: C146252 | B14: Open case | C14: Run 415 | D14: C146252 — SRI-VEND-C3 — A match on a contact's telephone shows the FULL value on the row | E14: Failed — already reported | G14: Error: these rows show only the characters typed instead of the whole value: ["Address: \n965","Contact match: \n965","Contact match: \n965","Contact match: \n965","Contact match: \n965","Contact match: \n965","Contact match: \n965"] expect(received).toHaveLength(expected) Expected length: 0 Received length: 7 Received array: ["Address:· 965", "Contact match:· 965", "Contact match:· 965", "Contact match:· 965", "Contact match:· 965", "Contact match:· 965", "Contact match:· 965"] 187 | expect(onlyTyped, 188 | `these rows show only the characters typed instead of the whole value: ${JSON.stringif | H14: Nothing new to raise: this is the behaviour SV-10634 describes (status Ready to Fix). It should pass once that fix reaches this build. | I14: SV-10634 | J14: Ready to Fix | K14: C146202-C146282-sri-retest-full-value.spec.ts | L14: 83 | M14: 17.6
A15: C146271 | B15: Open case | C15: Run 415 | D15: C146271 — SRI-PO-C1 — A match on part numbers on the PO shows the FULL value on the row | E15: Failed — already reported | G15: Error: these rows show only the characters typed instead of the whole value: ["Part number: \n0123"] expect(received).toHaveLength(expected) Expected length: 0 Received length: 1 Received array: ["Part number:· 0123"] 187 | expect(onlyTyped, 188 | `these rows show only the characters typed instead of the whole value: ${JSON.stringify(onlyTyped)}`) > 189 | .toHaveLength(0); | ^ 190 | }); 191 | } 192 | at /tmp/claude-0/-home-user-Manual-test-Cases/126e0959-4bca-54ed-8b95-71a191ca38d1/scratchpad/clean3/repo/build/global-search/e2e/tests/C146202-C146282-sri-retest-full-value.spec.ts:189:8 | H15: Nothing new to raise: this is the behaviour SV-10634 describes (status Ready to Fix). It should pass once that fix reaches this build. | I15: SV-10634 | J15: Ready to Fix | K15: C146202-C146282-sri-retest-full-value.spec.ts | L15: 83 | M15: 17.6
A16: C146272 | B16: Open case | C16: Run 415 | D16: C146272 — SRI-PO-C2 — A match on part descriptions on the PO shows the FULL value on the | E16: Failed — already reported | G16: Error: these rows show only the characters typed instead of the whole value: ["Part description: \n786","Part description: \n786","Part number: \n786","Part description: \n786"] expect(received).toHaveLength(expected) Expected length: 0 Received length: 4 Received array: ["Part description:· 786", "Part description:· 786", "Part number:· 786", "Part description:· 786"] 187 | expect(onlyTyped, 188 | `these rows show only the characters typed instead of the whole value: ${JSON.stringify(onlyTyped)}`) > 189 | .toHaveLength(0); | ^ 190 | }); 191 | } 192 | at /tmp/claude-0/-home-user-Manual-test-Ca | H16: Nothing new to raise: this is the behaviour SV-10634 describes (status Ready to Fix). It should pass once that fix reaches this build. | I16: SV-10634 | J16: Ready to Fix | K16: C146202-C146282-sri-retest-full-value.spec.ts | L16: 83 | M16: 19.2
A17: C146209 | B17: Open case | C17: Run 415 | D17: C146209 — each row shows the COMPLETE telephone, with the typed part inside it | E17: Failed — already reported | G17: Error: these rows show only the digits typed instead of the whole telephone: ["Contact match: \n0900","Contact match: \n0900","Contact match: \n0900","Contact match: \n0900","Contact match: \n0900","Contact match: \n0900","Contact match: \n0900","Contact match: \n0900","Contact match: \n0900","Contact match: \n0900","Contact match: \n0900","Contact match: \n0900","Contact match: \n0900","Contact match: \n0900","Contact match: \n0900"] expect(received).toHaveLength(expected) Expected length: 0 Received length: 15 Received array: ["Contact match:· 0900", "Contact match:· 0900", "Contact match:· | H17: Nothing new to raise: this is the behaviour SV-10634 describes (status Ready to Fix). It should pass once that fix reaches this build. | I17: SV-10634 | J17: Ready to Fix | K17: C146209-C146223-sri-customers.spec.ts | L17: 84 | M17: 9.7
A18: C146222 | B18: Open case | C18: Run 415 | D18: C146222 — the customer row shows every field the requirement names | E18: Failed — already reported | G18: Error: the customer row is missing ["telephone on hover"]. Row reads "7 Star Truck Repair 32 open 305 Harris Cape, Priscillabury, Nunavut". Hover added [] (pointer reached the row: true). expect(received).toHaveLength(expected) Expected length: 0 Received length: 1 Received array: ["telephone on hover"] 209 | expect(missing, `the customer row is missing ${JSON.stringify(missing)}. Row reads "${r.text}". ` + 210 | `Hover added ${JSON.stringify(hov.gained)} (pointer reached the row: ${hoverReached}).`) > 211 | .toHaveLength(0); | ^ 212 | }); 213 | 214 | test('C146223 — a soft match is drawn as a | H18: Nothing new to raise: this is the behaviour SV-10635 describes (status Ready to Fix). It should pass once that fix reaches this build. | I18: SV-10635 | J18: Ready to Fix | K18: C146209-C146223-sri-customers.spec.ts | L18: 162 | M18: 11.4
A19: C146245 | B19: Open case | C19: Run 415 | D19: C146245 — Vendors: the whole telephone is shown, with the typed part marked inside it | E19: Failed — our test's fault | G19: Error: CONTROL FAILED: no highlight found anywhere on row 8, so anything said below about an unhighlighted line is about this reader expect(received).toBeGreaterThan(expected) Expected: > 0 Received: 0 247 | expect(r.marks.length, 248 | `CONTROL FAILED: no highlight found anywhere on row ${r.index}, so anything said below about ` + > 249 | `an unhighlighted line is about this reader`).toBeGreaterThan(0); | ^ 250 | // …then the requirement itself: highlighted in the primary AND secondary text. 251 | expect(unmarkedLines(r, TERM), 252 | `row ${r.index}: the typed text is shown on these lines wit | H19: The test has been fixed. Re-run after the fix: Passed. | K19: C146224-C146284-sri-entities.spec.ts | L19: 232 | M19: 9.9 | N19: Passed
A20: C146266 | B20: Open case | C20: Run 415 | D20: C146266 — Purchase Orders: the whole PO number is shown, with the typed part marked inside it | E20: Failed — our test's fault | G20: Error: CONTROL FAILED: no highlight found anywhere on row 11, so anything said below about an unhighlighted line is about this reader expect(received).toBeGreaterThan(expected) Expected: > 0 Received: 0 247 | expect(r.marks.length, 248 | `CONTROL FAILED: no highlight found anywhere on row ${r.index}, so anything said below about ` + > 249 | `an unhighlighted line is about this reader`).toBeGreaterThan(0); | ^ 250 | // …then the requirement itself: highlighted in the primary AND secondary text. 251 | expect(unmarkedLines(r, TERM), 252 | `row ${r.index}: the typed text is shown on these lines wi | H20: The test has been fixed. Re-run after the fix: Passed. | K20: C146224-C146284-sri-entities.spec.ts | L20: 232 | M20: 9.8 | N20: Passed
A21: C146247 | B21: Open case | C21: Run 415 | D21: C146247 — Vendors: the highlight marks the match inside the text, not instead of it | E21: Failed — our test's fault | G21: Error: CONTROL FAILED: no highlight anywhere on row 8 expect(received).toBeGreaterThan(expected) Expected: > 0 Received: 0 310 | expect(rows.length).toBeGreaterThan(0); 311 | for (const r of rows) { > 312 | expect(r.marks.length, `CONTROL FAILED: no highlight anywhere on row ${r.index}`).toBeGreaterThan(0); | ^ 313 | expect(unmarkedLines(r, TERM), 314 | `row ${r.index}: the typed text appears on these lines unhighlighted`).toEqual([]); 315 | expect(r.title.segs.some((x) => !x.marked), at /tmp/claude-0/-home-user-Manual-test-Cases/126e0959-4bca-54ed-8b95-71a191ca38d1/scratchpad/clean3/repo/buil | H21: The test has been fixed. Re-run after the fix: Passed. | K21: C146224-C146284-sri-entities.spec.ts | L21: 305 | M21: 9.9 | N21: Passed
A22: C146268 | B22: Open case | C22: Run 415 | D22: C146268 — Purchase Orders: the highlight marks the match inside the text, not instead of it | E22: Failed — our test's fault | G22: Error: CONTROL FAILED: no highlight anywhere on row 11 expect(received).toBeGreaterThan(expected) Expected: > 0 Received: 0 310 | expect(rows.length).toBeGreaterThan(0); 311 | for (const r of rows) { > 312 | expect(r.marks.length, `CONTROL FAILED: no highlight anywhere on row ${r.index}`).toBeGreaterThan(0); | ^ 313 | expect(unmarkedLines(r, TERM), 314 | `row ${r.index}: the typed text appears on these lines unhighlighted`).toEqual([]); 315 | expect(r.title.segs.some((x) => !x.marked), at /tmp/claude-0/-home-user-Manual-test-Cases/126e0959-4bca-54ed-8b95-71a191ca38d1/scratchpad/clean3/repo/bui | H22: The test has been fixed. Re-run after the fix: Passed. | K22: C146224-C146284-sri-entities.spec.ts | L22: 305 | M22: 9.9 | N22: Passed
A23: C146306 | B23: Open case | C23: Run 415 | D23: C146306 — someone without access sees no rows AND no count | E23: Failed — our test's fault | G23: Error: Staging needs a live session cookie. Sign in to app.staging.shopview.com in a browser, then set GS_SSO and GS_PHPSESSID (and GS_CF if Cloudflare is in front) — or point GS_STAGING_ENVF at a file holding SV_SSO_SESSION=, PHPSESSID= and CF_CLEARANCE=. Staging uses Google sign-in, so there is no username and password to script. See e2e/.env.example. at ../fixtures/boot.ts:421 419 | const valueOf = (name: string) => SOURCES.find(([n]) => n === name)?.[1] ?? ''; 420 | if (!valueOf('sv_sso_session') || !valueOf('PHPSESSID')) { > 421 | throw new Error( | ^ 422 | 'Staging needs a live session c | H23: The test has been fixed. Re-run after the fix: Passed. | K23: C146285-C146306-sri-all-tab.spec.ts | L23: 368 | M23: 6.9 | N23: Passed
A24: C44809 | B24: Open case | C24: Run 415 | D24: C44809 — Down and Up move the highlight across result rows only | E24: Failed — our test's fault | G24: TimeoutError: locator.click: Timeout 60000ms exceeded. Call log: - waiting for locator('.search-modal input') - locator resolved to <input value="" type="text" tabindex="0" role="combobox" autocorrect="off" autocomplete="off" spellcheck="false" aria-label="Search" aria-expanded="true" autocapitalize="off" data-autofocus="true" enterkeyhint="search" aria-autocomplete="list" data-test-id="search_modal_input" aria-controls="search_modal_listbox" class="q-field__native q-placeholder" id="f_1fbe4b4b-e83a-485d-80e8-c9e8618fdbe0" placeholder="Search work orders, customers, parts and more" aria-active | H24: The test has been fixed. Re-run after the fix: Passed. | K24: C44804-C55683-panel-keyboard.spec.ts | L24: 76 | M24: 63.5 | N24: Passed
A25: C45144 | B25: Open case | C25: Run 415 | D25: C45144 — parts appear only with Catalog & Inventory access | E25: Failed — our test's fault | G25: Error: parts hidden with access granted expect(received).toBeGreaterThan(expected) Expected: > 0 Received: 0 110 | expect((await search(s.page, FIXTURE)).counts['Parts'] ?? 0, 'parts shown without access').toBeFalsy(); 111 | await asTechnicianWith([...new Set([...all, parts])]); > 112 | expect((await search(s.page, FIXTURE)).counts['Parts'] ?? 0, 'parts hidden with access granted').toBeGreaterThan(0); | ^ 113 | }); 114 | 115 | test('C45146 — removing customer access removes customers AND vehicles @C45146', async () => { at /tmp/claude-0/-home-user-Manual-test-Cases/126e0959-4bca-54ed-8b95-71a1 | H25: The test has been fixed. Re-run after the fix: Passed. | K25: access-and-location.spec.ts | L25: 103 | M25: 27.8 | N25: Passed
A26: C45146 | B26: Open case | C26: Run 415 | D26: C45146 — removing customer access removes customers AND vehicles | E26: Failed — our test's fault | G26: Error: customers still shown expect(received).toBeFalsy() Received: 20 121 | await asTechnicianWith(all.filter((id: string) => id !== cust)); 122 | const p = await search(s.page, FIXTURE); > 123 | expect(p.counts['Customers'] ?? 0, 'customers still shown').toBeFalsy(); | ^ 124 | expect(p.counts['Assets'] ?? 0, 'vehicles still shown — they depend on customer access too').toBeFalsy(); 125 | }); 126 | at /tmp/claude-0/-home-user-Manual-test-Cases/126e0959-4bca-54ed-8b95-71a191ca38d1/scratchpad/clean3/repo/build/global-search/e2e/tests/access-and-location.spec.ts:123:63 | H26: The test has been fixed. Re-run after the fix: Passed. | K26: access-and-location.spec.ts | L26: 115 | M26: 12.6 | N26: Passed
A27: C45147 | B27: Open case | C27: Run 415 | D27: C45147 — a time-clock-only person gets nothing at all | E27: Failed — our test's fault | G27: Error: All returned results expect(received).toBeFalsy() Received: 124 131 | await asTechnicianWith(idsOf(['timesheetsView'])); 132 | const p = await search(s.page, FIXTURE); > 133 | for (const [tab, v] of Object.entries(p.counts)) expect(v ?? 0, `${tab} returned results`).toBeFalsy(); | ^ 134 | }); 135 | 136 | /** at /tmp/claude-0/-home-user-Manual-test-Cases/126e0959-4bca-54ed-8b95-71a191ca38d1/scratchpad/clean3/repo/build/global-search/e2e/tests/access-and-location.spec.ts:133:94 | H27: The test has been fixed. Re-run after the fix: Passed. | K27: access-and-location.spec.ts | L27: 127 | M27: 12.9 | N27: Passed
A28: C45143 | B28: Open case | C28: Run 415 | D28: C45143 — a part-sales role sees part sales but not parts or suppliers | E28: Failed — our test's fault | G28: Error: parts shown to a part-sales-only role expect(received).toBeFalsy() Received: 15 158 | const p = await search(s.page, FIXTURE); 159 | expect(p.counts['Part sales'] ?? 0, 'part sales hidden from a part-sales role').toBeGreaterThan(0); > 160 | expect(p.counts['Parts'] ?? 0, 'parts shown to a part-sales-only role').toBeFalsy(); | ^ 161 | expect(p.counts['Vendors'] ?? 0, 'suppliers shown to a part-sales-only role').toBeFalsy(); 162 | }); 163 | at /tmp/claude-0/-home-user-Manual-test-Cases/126e0959-4bca-54ed-8b95-71a191ca38d1/scratchpad/clean3/repo/build/global-search/e2e/tests/access-and-loc | H28: The test has been fixed. Re-run after the fix: Passed. | K28: access-and-location.spec.ts | L28: 143 | M28: 12.5 | N28: Passed
A29: C45151 | B29: Open case | C29: Run 415 | D29: C45151 · C45152 · C55684 — search is limited to the shop you are in, and follows you | E29: Failed — our test's fault | G29: Error: a job could not be created at each shop expect(received).toBeTruthy() Received: undefined 190 | if (label === 'heavy') heavyJob = num; else lethJob = num; 191 | } > 192 | expect(heavyJob && lethJob, 'a job could not be created at each shop').toBeTruthy(); | ^ 193 | await s.page.waitForTimeout(30_000); 194 | 195 | const readAt = async (wp: string) => { at /tmp/claude-0/-home-user-Manual-test-Cases/126e0959-4bca-54ed-8b95-71a191ca38d1/scratchpad/clean3/repo/build/global-search/e2e/tests/access-and-location.spec.ts:192:76 | H29: The test has been fixed. Re-run after the fix: Passed. | K29: access-and-location.spec.ts | L29: 173 | M29: 4.8 | N29: Passed
A30: C55716 | B30: Open case | C30: Run 415 | D30: C55716 — the record changed most recently is listed first [expected to fail: SV-10340] | E30: Failed — our test's fault | G30: TypeError: Cannot read properties of undefined (reading 'id') 144 | const mine = ((list.body as any)?.data?.collection ?? []).filter((v: any) => String(v.name).includes(tag)); 145 | const target = mine[1] ?? mine[0]; > 146 | const w = await api(s.page, 'POST', '/api/parts-catalogue/change-vendor', { ...target, vendor_id: target.id, id: target.id, name: lowered }); | ^ 147 | expect(w.status, `the rename was refused: ${w.text}`).toBeLessThan(400); 148 | 149 | // The edit appearing in the results IS the proof the entry rebuilt. Without it, a stale order at /tmp/claude-0/-home-user-Manual-test-Cas | H30: The test has been fixed. Re-run after the fix: Passed. | I30: SV-10340 | J30: OBSOLETE | K30: counts-and-ranking.spec.ts | L30: 105 | M30: 19.8 | N30: Passed
A31: C55724 | B31: Open case | C31: Run 415 | D31: C55724b — a name starting with the query ranks above one that only contains it (seeded) | E31: Failed — our test's fault | G31: Error: page.evaluate: TypeError: Failed to fetch (api.shopview.com) at https://app.staging.shopview.com/js/sentry.B6EvyTlO.js:17:8323 at eval (eval at evaluate (:290:30), <anonymous>:2:21) at UtilityScript.evaluate (<anonymous>:292:16) at UtilityScript.<anonymous> (<anonymous>:1:44) at https://app.staging.shopview.com/js/sentry.B6EvyTlO.js:17:8323 at eval (eval at evaluate (:290:30), <anonymous>:2:21) at UtilityScript.evaluate (<anonymous>:292:16) at UtilityScript.<anonymous> (<anonymous>:1:44) at createCustomer (/tmp/claude-0/-home-user-Manual-test-Cases/126e0959-4bca-54ed-8b95-71a191ca38d1/s | H31: The test has been fixed. Re-run after the fix: Passed. | K31: ranking-seeded.spec.ts | L31: 85 | M31: 0.8 | N31: Passed
A32: C55723 | B32: Open case | C32: Run 415 | D32: C55723 — a record matched on its name ranks above one matched on a lesser field | E32: Failed — our test's fault | G32: Error: page.evaluate: TypeError: Failed to fetch (api.shopview.com) at https://app.staging.shopview.com/js/sentry.B6EvyTlO.js:17:8323 at eval (eval at evaluate (:290:30), <anonymous>:2:21) at UtilityScript.evaluate (<anonymous>:292:16) at UtilityScript.<anonymous> (<anonymous>:1:44) at https://app.staging.shopview.com/js/sentry.B6EvyTlO.js:17:8323 at eval (eval at evaluate (:290:30), <anonymous>:2:21) at UtilityScript.evaluate (<anonymous>:292:16) at UtilityScript.<anonymous> (<anonymous>:1:44) at createCustomer (/tmp/claude-0/-home-user-Manual-test-Cases/126e0959-4bca-54ed-8b95-71a191ca38d1/s | H32: The test has been fixed. Re-run after the fix: Passed. | K32: ranking-seeded.spec.ts | L32: 98 | M32: 0.6 | N32: Passed
A33: C45139 | B33: Open case | C33: Run 415 | D33: C45139 — a match in a lesser field still finds the company | E33: Failed — our test's fault | G33: Error: page.evaluate: TypeError: Failed to fetch (api.shopview.com) at https://app.staging.shopview.com/js/sentry.B6EvyTlO.js:17:8323 at eval (eval at evaluate (:290:30), <anonymous>:2:21) at UtilityScript.evaluate (<anonymous>:292:16) at UtilityScript.<anonymous> (<anonymous>:1:44) at https://app.staging.shopview.com/js/sentry.B6EvyTlO.js:17:8323 at eval (eval at evaluate (:290:30), <anonymous>:2:21) at UtilityScript.evaluate (<anonymous>:292:16) at UtilityScript.<anonymous> (<anonymous>:1:44) at createCustomer (/tmp/claude-0/-home-user-Manual-test-Cases/126e0959-4bca-54ed-8b95-71a191ca38d1/s | H33: The test has been fixed. Re-run after the fix: Passed. | K33: ranking-seeded.spec.ts | L33: 115 | M33: 0.6 | N33: Passed
A34: C53586 | B34: Open case | C34: Run 415 | D34: C53586 — a newly created customer is findable within 30 seconds | E34: Failed — our test's fault | G34: Error: page.evaluate: TypeError: Failed to fetch (api.shopview.com) at https://app.staging.shopview.com/js/sentry.B6EvyTlO.js:17:8323 at eval (eval at evaluate (:290:30), <anonymous>:2:21) at UtilityScript.evaluate (<anonymous>:292:16) at UtilityScript.<anonymous> (<anonymous>:1:44) at https://app.staging.shopview.com/js/sentry.B6EvyTlO.js:17:8323 at eval (eval at evaluate (:290:30), <anonymous>:2:21) at UtilityScript.evaluate (<anonymous>:292:16) at UtilityScript.<anonymous> (<anonymous>:1:44) at createCustomer (/tmp/claude-0/-home-user-Manual-test-Cases/126e0959-4bca-54ed-8b95-71a191ca38d1/s | H34: The test has been fixed. Re-run after the fix: Passed. | K34: ranking-seeded.spec.ts | L34: 126 | M34: 0.6 | N34: Passed
A35: C53587 | B35: Open case | C35: Run 415 | D35: C53587 — a newly created record of another kind is findable within 30 seconds | E35: Failed — our test's fault | G35: Error: page.evaluate: TypeError: Failed to fetch (api.shopview.com) at https://app.staging.shopview.com/js/sentry.B6EvyTlO.js:17:8323 at eval (eval at evaluate (:290:30), <anonymous>:2:21) at UtilityScript.evaluate (<anonymous>:292:16) at UtilityScript.<anonymous> (<anonymous>:1:44) at https://app.staging.shopview.com/js/sentry.B6EvyTlO.js:17:8323 at eval (eval at evaluate (:290:30), <anonymous>:2:21) at UtilityScript.evaluate (<anonymous>:292:16) at UtilityScript.<anonymous> (<anonymous>:1:44) at createCustomer (/tmp/claude-0/-home-user-Manual-test-Cases/126e0959-4bca-54ed-8b95-71a191ca38d1/s | H35: The test has been fixed. Re-run after the fix: Passed. | K35: ranking-seeded.spec.ts | L35: 137 | M35: 0.7 | N35: Passed
A36: C55712 | B36: Open case | C36: Run 415 | D36: C55712 — Parts: what is relevant to where you are is still found from there | E36: Failed — our test's fault | G36: Error: expect(locator).toBeVisible() failed Locator: locator('.search-modal') Expected: visible Timeout: 20000ms Error: element(s) not found Call log: - Expect "toBeVisible" with timeout 20000ms - waiting for locator('.search-modal') at ../fixtures/search.ts:28 26 | const already = await page.locator(SEL.modal).count(); 27 | if (!already) { await page.keyboard.press('Control+k'); await page.waitForTimeout(1_400); } > 28 | await expect(page.locator(SEL.modal)).toBeVisible(); | ^ 29 | } 30 | 31 | export async function closePanel(page: Page) { at openPanel (/tmp/claude-0/-home-user-Manual-test-Ca | H36: The test has been fixed. Re-run after the fix: Passed. | K36: ranking-seeded.spec.ts | L36: 184 | M36: 21.9 | N36: Passed
A37: C146202 | B37: Open case | C37: Run 415 | D37: C146202 — SRI-WO-C1 — A match on VIN / serial number shows the FULL value on the row | E37: Known fault — still there | G37: Failed in the known way. The fault recorded under None is still there. | H37: Nothing new. Already known; waiting on the fix. | K37: C146202-C146282-sri-retest-full-value.spec.ts | L37: 83 | M37: 30.4
A38: C146214 | B38: Open case | C38: Run 415 | D38: C146214 — SRI-CUST-C1 — A match on the customer's own telephone shows the FULL value on | E38: Known fault — still there | G38: Failed in the known way. The fault recorded under None is still there. | H38: Nothing new. Already known; waiting on the fix. | K38: C146202-C146282-sri-retest-full-value.spec.ts | L38: 83 | M38: 29.5
A39: C146215 | B39: Open case | C39: Run 415 | D39: C146215 — SRI-CUST-C2 — A match on a contact's telephone shows the FULL value on the row | E39: Known fault — still there | G39: Failed in the known way. The fault recorded under None is still there. | H39: Nothing new. Already known; waiting on the fix. | K39: C146202-C146282-sri-retest-full-value.spec.ts | L39: 83 | M39: 28.3
A40: C146217 | B40: Open case | C40: Run 415 | D40: C146217 — SRI-CUST-C4 — A match on a contact's name shows the FULL value on the row | E40: Known fault — still there | G40: Failed in the known way. The fault recorded under None is still there. | H40: Nothing new. Already known; waiting on the fix. | K40: C146202-C146282-sri-retest-full-value.spec.ts | L40: 83 | M40: 29.1
A41: C146218 | B41: Open case | C41: Run 415 | D41: C146218 — SRI-CUST-C5 — A match on address line 2 shows the FULL value on the row | E41: Known fault — still there | G41: Failed in the known way. The fault recorded under None is still there. | H41: Nothing new. Already known; waiting on the fix. | K41: C146202-C146282-sri-retest-full-value.spec.ts | L41: 83 | M41: 27.5
A42: C146229 | B42: Open case | C42: Run 415 | D42: C146229 — SRI-ASSET-C1 — A match on VIN / serial number shows the FULL value on the row | E42: Known fault — still there | G42: Failed in the known way. The fault recorded under None is still there. | H42: Nothing new. Already known; waiting on the fix. | K42: C146202-C146282-sri-retest-full-value.spec.ts | L42: 83 | M42: 28.6
A43: C146230 | B43: Open case | C43: Run 415 | D43: C146230 — SRI-ASSET-C2 — A match on licence plate shows the FULL value on the row | E43: Known fault — still there | G43: Failed in the known way. The fault recorded under None is still there. | H43: Nothing new. Already known; waiting on the fix. | K43: C146202-C146282-sri-retest-full-value.spec.ts | L43: 83 | M43: 27.2
A44: C146239 | B44: Open case | C44: Run 415 | D44: C146239 — SRI-PART-C2 — A match on manufacturer shows the FULL value on the row | E44: Known fault — still there | G44: Failed in the known way. The fault recorded under None is still there. | H44: Nothing new. Already known; waiting on the fix. | K44: C146202-C146282-sri-retest-full-value.spec.ts | L44: 83 | M44: 28.8
A45: C146240 | B45: Open case | C45: Run 415 | D45: C146240 — SRI-PART-C3 — A match on vendor name shows the FULL value on the row | E45: Known fault — still there | G45: Failed in the known way. The fault recorded under None is still there. | H45: Nothing new. Already known; waiting on the fix. | K45: C146202-C146282-sri-retest-full-value.spec.ts | L45: 83 | M45: 30.8
A46: C146251 | B46: Open case | C46: Run 415 | D46: C146251 — SRI-VEND-C2 — A match on address line 2 shows the FULL value on the row | E46: Known fault — still there | G46: Failed in the known way. The fault recorded under None is still there. | H46: Nothing new. Already known; waiting on the fix. | K46: C146202-C146282-sri-retest-full-value.spec.ts | L46: 83 | M46: 28.3
A47: C146262 | B47: Open case | C47: Run 415 | D47: C146262 — SRI-PS-C1 — A match on the asset on the sale shows the FULL value on the row | E47: Known fault — still there | G47: Failed in the known way. The fault recorded under None is still there. | H47: Nothing new. Already known; waiting on the fix. | K47: C146202-C146282-sri-retest-full-value.spec.ts | L47: 83 | M47: 29.3
A48: C146263 | B48: Open case | C48: Run 415 | D48: C146263 — SRI-PS-C2 — A match on VIN / serial number shows the FULL value on the row | E48: Known fault — still there | G48: Failed in the known way. The fault recorded under None is still there. | H48: Nothing new. Already known; waiting on the fix. | K48: C146202-C146282-sri-retest-full-value.spec.ts | L48: 83 | M48: 28.7
... A51: C146282 | B51: Open case | C51: Run 415 | D51: C146282 — SRI-VINV-C1 — A match on the PO number the invoice belongs to shows the FULL v | E51: Known fault — still there | G51: Failed in the known way. The fault recorded under None is still there. | H51: Nothing new. Already known; waiting on the fix. | K51: C146202-C146282-sri-retest-full-value.spec.ts | L51: 83 | M51: 27.2
A52: C53476 | B52: Open case | C52: Run 415 | D52: C53476 — no count reads higher than 20 [expected to fail: SV-10320] | E52: Known fault — still there | G52: Failed in the known way. The fault recorded under SV-10320 is still there. | H52: Nothing new. Already known; waiting on the fix. | I52: SV-10320 | J52: OBSOLETE | K52: counts-and-ranking.spec.ts | L52: 27 | M52: 6
A53: C55716 | B53: Open case | C53: Run 415 | D53: C55716 (customers) — the customer changed most recently is listed first [expected to fail: SV-10340] | E53: Known fault — still there | G53: Failed in the known way. The fault recorded under SV-10340 is still there. | H53: Nothing new. Already known; waiting on the fix. | I53: SV-10340 | J53: OBSOLETE | K53: counts-and-ranking.spec.ts | L53: 161 | M53: 29.1
A54: C53601 | B54: Open case | C54: Run 415 | D54: C53601 — a catalogue-only part is findable [expected to fail: SV-10001] | E54: Known fault — still there | G54: Failed in the known way. The fault recorded under SV-10001 is still there. | H54: Nothing new. Already known; waiting on the fix. | I54: SV-10001 | J54: OBSOLETE | K54: findability.spec.ts | L54: 137 | M54: 9.3
A55: C53605 | B55: Open case | C55: Run 415 | D55: C53605 — year and make typed together find the vehicle [expected to fail: SV-10055] | E55: Known fault — still there | G55: Failed in the known way. The fault recorded under SV-10055 is still there. | H55: Nothing new. Already known; waiting on the fix. | I55: SV-10055 | J55: Done | K55: findability.spec.ts | L55: 150 | M55: 9.9
A56: C55660 | B56: Open case | C56: Run 415 | D56: C55660 — a fragment from the middle of a word finds the record [expected to fail: SV-10060] | E56: Known fault — still there | G56: Failed in the known way. The fault recorded under SV-10060 is still there. | H56: Nothing new. Already known; waiting on the fix. | I56: SV-10060 | J56: OBSOLETE | K56: findability.spec.ts | L56: 163 | M56: 9.1
A57: C55685 | B57: Open case | C57: Run 415 | D57: C55685 — a correct spelling returns only related records [expected to fail: SV-10025] | E57: Known fault — still there | G57: Failed in the known way. The fault recorded under SV-10025 is still there. | H57: Nothing new. Already known; waiting on the fix. | I57: SV-10025 | J57: OBSOLETE | K57: panel.spec.ts | L57: 159 | M57: 9.4
A58: C146286 | B58: Open case | C58: Run 415 | D58: C146286 — no count anywhere reads higher than 20 [expected to fail: SV-10320] | E58: Known fault — did not reproduce | G58: The known fault recorded under SV-10320 did NOT happen this time — the behaviour may have been fixed. | H58: The ticket reads OBSOLETE. Confirm by hand that the behaviour is fixed; if it is, this test should stop expecting the fault. | I58: SV-10320 | J58: OBSOLETE | K58: C146285-C146306-sri-all-tab.spec.ts | L58: 83 | M58: 6.9
A59: C146208 | B59: Open case | C59: Run 415 | D59: C146208 — a soft match is drawn as a soft match | E59: Stood down | G59: the close-match rows carry no highlight at all on this build — the open fault SV-10740. The reader cannot be proved to work on them, so nothing here would be a sound statement about how a soft match is drawn. This starts running again when that fault is fixed. | H59: Supply what the reason names (a record or a login), then run this case again. Nothing was judged. | K59: C146197-C146208-sri-work-orders.spec.ts | L59: 267 | M59: 8.8
A60: C146223 | B60: Open case | C60: Run 415 | D60: C146223 — a soft match is drawn as a soft match | E60: Stood down | G60: close-match rows carry no highlight at all on this build — the open fault SV-10740 — so the reader cannot be proved to see one. This starts running again when that fault is fixed. | H60: Supply what the reason names (a record or a login), then run this case again. Nothing was judged. | K60: C146209-C146223-sri-customers.spec.ts | L60: 214 | M60: 16
A61: C146232 | B61: Open case | C61: Run 415 | D61: C146232 — Assets: a soft match is drawn as a soft match | E61: Stood down | G61: cannot be judged here: 1 of 1 near-miss rows carry no highlight at all (row 2: "≈ close match: PERTAB-C3 · 2019 ZZOBSIDIAM Trucks Hauler Per"). Either the product marks nothing on them or this reader cannot see the marks — and until that is settled, anything said about HOW they are drawn would be about the reader. Run this one by hand. | H61: Supply what the reason names (a record or a login), then run this case again. Nothing was judged. | K61: C146224-C146284-sri-entities.spec.ts | L61: 403 | M61: 9.8
A62: C146244 | B62: Open case | C62: Run 415 | D62: C146244 — Parts: a soft match is drawn as a soft match | E62: Stood down | G62: cannot be judged here: 1 of 1 near-miss rows carry no highlight at all (row 2: "≈ close match: ZZKRYPTOM Wheel Seal 8 Available PERTAB-7003"). Either the product marks nothing on them or this reader cannot see the marks — and until that is settled, anything said about HOW they are drawn would be about the reader. Run this one by hand. | H62: Supply what the reason names (a record or a login), then run this case again. Nothing was judged. | K62: C146224-C146284-sri-entities.spec.ts | L62: 403 | M62: 9.7
A63: C146256 | B63: Open case | C63: Run 415 | D63: C146256 — Vendors: a soft match is drawn as a soft match | E63: Stood down | G63: cannot be judged here: 1 of 1 near-miss rows carry no highlight at all (row 2: "≈ close match: ZZMAGENTO Traders (264) 400-0700 · 11 Per Tab"). Either the product marks nothing on them or this reader cannot see the marks — and until that is settled, anything said about HOW they are drawn would be about the reader. Run this one by hand. | H63: Supply what the reason names (a record or a login), then run this case again. Nothing was judged. | K63: C146224-C146284-sri-entities.spec.ts | L63: 403 | M63: 9.8
A64: C146265 | B64: Open case | C64: Run 415 | D64: C146265 — Part Sales: a soft match is drawn as a soft match | E64: Stood down | G64: cannot be judged here: 2 of 2 near-miss rows carry no highlight at all (row 2: "≈ close match: P2-2305 ZZSOFTHIP Logistics Estimate Admin Sh"). Either the product marks nothing on them or this reader cannot see the marks — and until that is settled, anything said about HOW they are drawn would be about the reader. Run this one by hand. | H64: Supply what the reason names (a record or a login), then run this case again. Nothing was judged. | K64: C146224-C146284-sri-entities.spec.ts | L64: 403 | M64: 9.8
A65: C146276 | B65: Open case | C65: Run 415 | D65: C146276 — Purchase Orders: a soft match is drawn as a soft match | E65: Stood down | G65: cannot be judged here: 2 of 2 near-miss rows carry no highlight at all (row 2: "≈ close match: I2-1536 ZZSOFTHIP Traders Fulfilled $37.00 · "). Either the product marks nothing on them or this reader cannot see the marks — and until that is settled, anything said about HOW they are drawn would be about the reader. Run this one by hand. | H65: Supply what the reason names (a record or a login), then run this case again. Nothing was judged. | K65: C146224-C146284-sri-entities.spec.ts | L65: 403 | M65: 9.8
A66: C146284 | B66: Open case | C66: Run 415 | D66: C146284 — Vendor Invoices: a soft match is drawn as a soft match | E66: Stood down | G66: cannot be judged here: 2 of 2 near-miss rows carry no highlight at all (row 2: "≈ close match: ZZSH-O_TYPO ZZSOFTHIP Traders Unpaid $37.00 ·"). Either the product marks nothing on them or this reader cannot see the marks — and until that is settled, anything said about HOW they are drawn would be about the reader. Run this one by hand. | H66: Supply what the reason names (a record or a login), then run this case again. Nothing was judged. | K66: C146224-C146284-sri-entities.spec.ts | L66: 403 | M66: 9.8
A67: C146291 | B67: Open case | C67: Run 415 | D67: C146291 — typing a full record number puts that record at the very top | E67: Stood down | G67: the pinned top result was withdrawn by the QA lead on 2026-09-29 — this is not a defect and the check is not asserted | H67: Supply what the reason names (a record or a login), then run this case again. Nothing was judged. | K67: C146285-C146306-sri-all-tab.spec.ts | L67: 158 | M67: 0
A68: C45138 | B68: Open case | C68: Run 415 | D68: C45138 — unpaid supplier invoices rank above paid ones | E68: Stood down | G68: needs both a paid and an unpaid invoice in one result set — mark one paid to run this | H68: Supply what the reason names (a record or a login), then run this case again. Nothing was judged. | K68: counts-and-ranking.spec.ts | L68: 79 | M68: 9.2
A69: C44839 | B69: Open case | C69: Run 415 | D69: C44839 — a misspelled word still finds the record (customerName) | E69: Stood down | G69: customerName has no word long enough to damage fairly: "" | H69: Supply what the reason names (a record or a login), then run this case again. Nothing was judged. | K69: findability-matching.spec.ts | L69: 115 | M69: 0
A70: C44840 | B70: Open case | C70: Run 415 | D70: C44840 — a misspelled word still finds the record (customerName) | E70: Stood down | G70: customerName has no word long enough to damage fairly: "" | H70: Supply what the reason names (a record or a login), then run this case again. Nothing was judged. | K70: findability-matching.spec.ts | L70: 115 | M70: 0
... A122: C44830 | B122: Open case | C122: Run 415 | D122: C44830 — groups appear in the order the requirement fixes | E122: Stood down | G122: fewer than two groups came back, so order cannot be judged | H122: Supply what the reason names (a record or a login), then run this case again. Nothing was judged. | K122: structure-and-scoping.spec.ts | L122: 94 | M122: 7
A123: C146197 | B123: Open case | C123: Run 415 | D123: C146197 — the whole WO number is shown, with what you typed marked inside it | E123: Passed | G123: Passed. | K123: C146197-C146208-sri-work-orders.spec.ts | L123: 105 | M123: 0
A124: C146198 | B124: Open case | C124: Run 415 | D124: C146198 — nothing cut off has eaten the match or what tells the rows apart | E124: Passed | G124: Passed. | K124: C146197-C146208-sri-work-orders.spec.ts | L124: 146 | M124: 9.8
A125: C146199 | B125: Open case | C125: Run 415 | D125: C146199 — the highlight marks the match inside the text, not instead of it | E125: Passed | G125: Passed. | K125: C146197-C146208-sri-work-orders.spec.ts | L125: 180 | M125: 0
A126: C146200 | B126: Open case | C126: Run 415 | D126: C146200 — two records sharing the typed text can be told apart from the rows alone | E126: Passed | G126: Passed. | K126: C146197-C146208-sri-work-orders.spec.ts | L126: 193 | M126: 0
A127: C146201 | B127: Open case | C127: Run 415 | D127: C146201 — rows with the same bold line still differ somewhere you can see | E127: Passed | G127: Passed. | K127: C146197-C146208-sri-work-orders.spec.ts | L127: 203 | M127: 0
A128: C146207 | B128: Open case | C128: Run 415 | D128: C146207 — the row shows every field the requirement names | E128: Passed | G128: Passed. | K128: C146197-C146208-sri-work-orders.spec.ts | L128: 221 | M128: 0
A129: C146204 | B129: Open case | C129: Run 415 | D129: C146204 — SRI-WO-C3 — A match on service advisor name shows the FULL value on the row | E129: Passed | G129: Passed. | K129: C146202-C146282-sri-retest-full-value.spec.ts | L129: 83 | M129: 0
A130: C146220 | B130: Open case | C130: Run 415 | D130: C146220 — SRI-CUST-C7 — A match on state / province shows the FULL value on the row | E130: Passed | G130: Passed. | K130: C146202-C146282-sri-retest-full-value.spec.ts | L130: 83 | M130: 18
A131: C146221 | B131: Open case | C131: Run 415 | D131: C146221 — SRI-CUST-C8 — A match on postal code shows the FULL value on the row | E131: Passed | G131: Passed. | K131: C146202-C146282-sri-retest-full-value.spec.ts | L131: 83 | M131: 26.9
A132: C146241 | B132: Open case | C132: Run 415 | D132: C146241 — SRI-PART-C4 — A match on category shows the FULL value on the row | E132: Passed | G132: Passed. | K132: C146202-C146282-sri-retest-full-value.spec.ts | L132: 83 | M132: 28.4
A133: C146250 | B133: Open case | C133: Run 415 | D133: C146250 — SRI-VEND-C1 — A match on email address shows the FULL value on the row | E133: Passed | G133: Passed. | K133: C146202-C146282-sri-retest-full-value.spec.ts | L133: 83 | M133: 30.8
A134: C146210 | B134: Open case | C134: Run 415 | D134: C146210 — nothing cut off has eaten the match or what tells the rows apart | E134: Passed | G134: Passed. | K134: C146209-C146223-sri-customers.spec.ts | L134: 106 | M134: 9.7
... A204: C44838 | B204: Open case | C204: Run 415 | D204: C44838 — status and stock badges appear on the rows that carry them | E204: Passed | G204: Passed. | K204: findability-matching.spec.ts | L204: 279 | M204: 7
C205: Run 415 | D205: seed control — the regression dataset is present | E205: Passed | G205: Passed. | K205: findability.spec.ts | L205: 27 | M205: 9.6
A206: C53578 | B206: Open case | C206: Run 415 | D206: C53578 — typing "Bridgeport" finds it under Work orders | E206: Passed | G206: Passed. | K206: findability.spec.ts | L206: 61 | M206: 19.9
A207: C53580 | B207: Open case | C207: Run 415 | D207: C53580 — typing "ZZT-4471" finds it under Assets | E207: Passed | G207: Passed. | K207: findability.spec.ts | L207: 61 | M207: 18.8
A208: C53581 | B208: Open case | C208: Run 415 | D208: C53581 — typing "Bridgeport" finds it under Assets | E208: Passed | G208: Passed. | K208: findability.spec.ts | L208: 61 | M208: 19.9
A209: C53607 | B209: Open case | C209: Run 415 | D209: C53607 — typing "Kestrel" finds it under Parts | E209: Passed | G209: Passed. | K209: findability.spec.ts | L209: 61 | M209: 19.2
A210: C55663 | B210: Open case | C210: Run 415 | D210: C55663 — typing "(614) 555-0188" finds it under Vendors | E210: Passed | G210: Passed. | K210: findability.spec.ts | L210: 61 | M210: 20
A211: C55665 | B211: Open case | C211: Run 415 | D211: C55665 — typing "Bridgeport" finds it under Part sales | E211: Passed | G211: Passed. | K211: findability.spec.ts | L211: 61 | M211: 19.7
A212: C55666 | B212: Open case | C212: Run 415 | D212: C55666 — typing "ZZT-88-4412" finds it under Parts | E212: Passed | G212: Passed. | K212: findability.spec.ts | L212: 61 | M212: 19.6
A213: C55667 | B213: Open case | C213: Run 415 | D213: C55667 — typing "Bridgeport" finds it under Customers | E213: Passed | G213: Passed. | K213: findability.spec.ts | L213: 61 | M213: 19.7
A214: C55668 | B214: Open case | C214: Run 415 | D214: C55668 — typing "Kestrel" finds it under Vendors | E214: Passed | G214: Passed. | K214: findability.spec.ts | L214: 61 | M214: 19.6
A215: C55671 | B215: Open case | C215: Run 415 | D215: C55671 — capitals never change what is found | E215: Passed | G215: Passed. | K215: findability.spec.ts | L215: 111 | M215: 28.4
A216: C55688 | B216: Open case | C216: Run 415 | D216: C55688 — typing a make returns only that make | E216: Passed | G216: Passed. | K216: findability.spec.ts | L216: 119 | M216: 9.6
A217: C55689 | B217: Open case | C217: Run 415 | D217: C55689 — typing a year returns only that year | E217: Passed | G217: Passed. | K217: findability.spec.ts | L217: 126 | M217: 9.2
... A340: C44811 | B340: Open case | C340: Run 415 | D340: C44811 — Ctrl+Enter opens the highlighted result in a new browser tab | E340: Passed | G340: Passed. | K340: tabs-groups-navigation.spec.ts | L340: 196 | M340: 7.5

Sheet Possible new problems
A1: Failures not described by any ticket. NOT yet checked against the requirement as it reads today, and nothing has been raised.
A2: Case | B2: Case in TestRail | C2: Test run | D2: What the test checks | E2: Result | F2: Likely cause | G2: What happened | H2: What needs to be done | I2: Ticket | J2: Ticket status (read live) | K2: Spec file | L2: Line | M2: Seconds | N2: Re-run after fixing the test | O2: Re-run detail
A3: C146216 | B3: Open case | C3: Run 415 | D3: C146216 — SRI-CUST-C3 — A match on a contact's email address shows the FULL value on the | E3: Failed — possible new problem | G3: Error: the note shows neither the whole value "zzautotest.nophone@staging.shopview.local" nor the text typed — it shows a different detail of the record altogether: ["Contact match: ZZAUTOTEST"] expect(received).toHaveLength(expected) Expected length: 0 Received length: 1 Received array: ["Contact match: ZZAUTOTEST"] 170 | expect(wrongValue, 171 | `the note shows neither the whole value "${term}" nor the text typed — it shows a ` + > 172 | `different detail of the record altogether: ${JSON.stringify(wrongValue)}`).toHaveLength(0); | ^ 173 | return; 174 | } 175 | at /tmp/claude-0/-home-user-Man | H3: Check it against the requirement as it reads today (not yet done), then decide whether to raise it. Nothing has been raised. | K3: C146202-C146282-sri-retest-full-value.spec.ts | L3: 83 | M3: 31.6
A4: C146233 | B4: Open case | C4: Run 415 | D4: C146233 — Parts: the whole part number is shown, with the typed part marked inside it | E4: Failed — possible new problem | G4: Error: row 1: the WHOLE value "ZZLONGROW Heavy Duty Air Brake" is highlighted rather than just the typed "ZZLONGROW" within it, so nothing marks which part actually matched expect(received).toBeGreaterThan(expected) Expected: > 0 Received: 0 260 | expect(unmarked.length, 261 | `row ${r.index}: the WHOLE value "${r.title.text}" is highlighted rather than just the ` + > 262 | `typed "${TERM}" within it, so nothing marks which part actually matched`).toBeGreaterThan(0); | ^ 263 | expect(r.title.clipped, 264 | `row ${r.index} is cut short — it paints ${r.title.clientW}px of ${r.title.scrollW}px an | H4: Check it against the requirement as it reads today (not yet done), then decide whether to raise it. Nothing has been raised. | K4: C146224-C146284-sri-entities.spec.ts | L4: 232 | M4: 9.8 | N4: Failed | O4: Error: row 1: the WHOLE value "ZZLONGROW Heavy Duty Air Brake" is highlighted rather than just the typed "ZZLONGROW" within it, so nothing marks which part actually matched expect(received).toBeGreaterThan(expected) Expected: > 0 Received: 0 282 | expect(unmarked.length, 283 | `row ${r.index}: the WHOLE value "${r.title.text}" is highlighted rather than just the ` + > 284 | `typed "${TERM}" within
A5: C146235 | B5: Open case | C5: Run 415 | D5: C146235 — Parts: the highlight marks the match inside the text, not instead of it | E5: Failed — possible new problem | G5: Error: row 1: every piece of "ZZLONGROW Heavy Duty Air Brake" is highlighted, so the mark covers the whole value instead of the typed "ZZLONGROW" inside it expect(received).toBe(expected) // Object.is equality Expected: true Received: false 315 | expect(r.title.segs.some((x) => !x.marked), 316 | `row ${r.index}: every piece of "${r.title.text}" is highlighted, so the mark covers the ` + > 317 | `whole value instead of the typed "${TERM}" inside it`).toBe(true); | ^ 318 | const rebuilt = r.title.segs.map((x) => x.text).join('').replace(/\s+/g, ' ').trim(); 319 | expect(rebuilt, `row ${r.index}: | H5: Check it against the requirement as it reads today (not yet done), then decide whether to raise it. Nothing has been raised. | K5: C146224-C146284-sri-entities.spec.ts | L5: 305 | M5: 9.8 | N5: Failed | O5: Error: row 1: every piece of "ZZLONGROW Heavy Duty Air Brake" is highlighted, so the mark covers the whole value instead of the typed "ZZLONGROW" inside it expect(received).toBe(expected) // Object.is equality Expected: true Received: false 336 | expect(r.title.segs.some((x) => !x.marked), 337 | `row ${r.index}: every piece of "${r.title.text}" is highlighted, so the mark covers the ` + > 338 | `w
A6: C146227 | B6: Open case | C6: Run 415 | D6: C146227 — Assets: two records sharing the typed text can be told apart | E6: Failed — possible new problem | G6: Error: these rows read identically to a person: ["ZZLONGROW-123786 · 2021 Rowcheck Trucks Longhauler | | ZZLONGROW Heavy Haulage And Trailer Repair Services Of Greater Fernvale 123786"] expect(received).toHaveLength(expected) Expected length: 0 Received length: 1 Received array: ["ZZLONGROW-123786 · 2021 Rowcheck Trucks Longhauler | | ZZLONGROW Heavy Haulage And Trailer Repair Services Of Greater Fernvale 123786"] 331 | const seen = rows.map(visibleRow); 332 | const dupes = seen.filter((v, i) => seen.indexOf(v) !== i); > 333 | expect(dupes, `these rows read identically to a person: ${JSON.stri | H6: Check it against the requirement as it reads today (not yet done), then decide whether to raise it. Nothing has been raised. | K6: C146224-C146284-sri-entities.spec.ts | L6: 324 | M6: 9.8 | N6: Failed | O6: Error: these rows read identically to a person: ["ZZLONGROW-123786 · 2021 Rowcheck Trucks Longhauler | | ZZLONGROW Heavy Haulage And Trailer Repair Services Of Greater Fernvale 123786"] expect(received).toHaveLength(expected) Expected length: 0 Received length: 1 Received array: ["ZZLONGROW-123786 · 2021 Rowcheck Trucks Longhauler | | ZZLONGROW Heavy Haulage And Trailer Repair Services Of Greater
A7: C146228 | B7: Open case | C7: Run 415 | D7: C146228 — Assets: records with the same bold line differ somewhere you can see | E7: Failed — possible new problem | G7: Error: rows 1,2 share the bold line "ZZLONGROW-123786 · 2021 Rowcheck Trucks Longhauler" and nothing visible separates them: [" | ZZLONGROW Heavy Haulage And Trailer Repair Services Of Greater Fernvale 123786"," | ZZLONGROW Heavy Haulage And Trailer Repair Services Of Greater Fernvale 123786"] expect(received).toBe(expected) // Object.is equality Expected: 2 Received: 1 348 | expect(new Set(rest).size, 349 | `rows ${group.map((r) => r.index).join(',')} share the bold line "${title}" and nothing visible ` + > 350 | `separates them: ${JSON.stringify(rest)}`).toBe(group.length); | ^ 351 | } 352 | | H7: Check it against the requirement as it reads today (not yet done), then decide whether to raise it. Nothing has been raised. | K7: C146224-C146284-sri-entities.spec.ts | L7: 336 | M7: 10 | N7: Failed | O7: Error: rows 1,2 share the bold line "ZZLONGROW-123786 · 2021 Rowcheck Trucks Longhauler" and nothing visible separates them: [" | ZZLONGROW Heavy Haulage And Trailer Repair Services Of Greater Fernvale 123786"," | ZZLONGROW Heavy Haulage And Trailer Repair Services Of Greater Fernvale 123786"] expect(received).toBe(expected) // Object.is equality Expected: 2 Received: 1 369 | expect(new Set(rest).
A8: C45137 | B8: Open case | C8: Run 415 | D8: C45137 — still-ordered purchase orders rank above received ones | E8: Failed — possible new problem | G8: Error: a received order is above a still-ordered one: ["Partial","Ordered","Ordered","Ordered","Ordered","Partial","Partial","Ordered","Partial","Partial","Partial","Received","Received","Received","Received","Ordered","Received","Received","Received"] expect(received).toBeLessThan(expected) Expected: < 11 Received: 15 70 | const firstReceived = seq.indexOf('Received'); 71 | if (lastOrdered >= 0 && firstReceived >= 0) { > 72 | expect(lastOrdered, `a received order is above a still-ordered one: ${JSON.stringify(seq)}`).toBeLessThan(firstReceived); | ^ 73 | } 74 | // NOT asserted: where "Partial | H8: Check it against the requirement as it reads today (not yet done), then decide whether to raise it. Nothing has been raised. | K8: counts-and-ranking.spec.ts | L8: 57 | M8: 19 | N8: Failed | O8: Error: a received order is above a still-ordered one: ["Partial","Ordered","Ordered","Ordered","Ordered","Partial","Partial","Ordered","Partial","Partial","Partial","Received","Received","Received","Received","Ordered","Received","Received","Received"] expect(received).toBeLessThan(expected) Expected: < 11 Received: 15 70 | const firstReceived = seq.indexOf('Received'); 71 | if (lastOrdered >= 0 &
A9: C44828 | B9: Open case | C9: Run 415 | D9: C44828 — the typed text is highlighted inside each matching row | E9: Failed — possible new problem | G9: Error: 65 of 65 rows carry no highlight at all expect(received).toBe(expected) // Object.is equality Expected: 0 Received: 65 264 | expect(r.length, `"${word}" finds nothing`).toBeGreaterThan(0); 265 | const unmarked = r.filter(x => x.marks.length === 0).length; > 266 | expect(unmarked, `${unmarked} of ${r.length} rows carry no highlight at all`).toBe(0); | ^ 267 | }); 268 | 269 | test('C44848 — a close match is drawn as a close match @C44848', async () => { at /tmp/claude-0/-home-user-Manual-test-Cases/126e0959-4bca-54ed-8b95-71a191ca38d1/scratchpad/clean3/repo/build/global-search/e2e/tests/f | H9: Check it against the requirement as it reads today (not yet done), then decide whether to raise it. Nothing has been raised. | K9: findability-matching.spec.ts | L9: 261 | M9: 8.1

Sheet Already reported
A1: Failures showing a behaviour a filed ticket already describes. The ticket and its live status are on each row. Nothing new to raise.
A2: Case | B2: Case in TestRail | C2: Test run | D2: What the test checks | E2: Result | F2: Likely cause | G2: What happened | H2: What needs to be done | I2: Ticket | J2: Ticket status (read live) | K2: Spec file | L2: Line | M2: Seconds | N2: Re-run after fixing the test | O2: Re-run detail
A3: C146205 | B3: Open case | C3: Run 415 | D3: C146205 — SRI-WO-C4 — A match on line item descriptions (parts and labor on the WO) show | E3: Failed — already reported | G3: Error: these rows show only the characters typed instead of the whole value: ["Part number: \n786","Part number: \n786","Part description: \n786","Part description: \n786","Part description: \n786","Part description: \n786","Part description: \n786"] expect(received).toHaveLength(expected) Expected length: 0 Received length: 7 Received array: ["Part number:· 786", "Part number:· 786", "Part description:· 786", "Part description:· 786", "Part description:· 786", "Part description:· 786", "Part description:· 786"] 187 | expect(onlyTyped, 188 | `these rows show only the characters typed instead o | H3: Nothing new to raise: this is the behaviour SV-10634 describes (status Ready to Fix). It should pass once that fix reaches this build. | I3: SV-10634 | J3: Ready to Fix | K3: C146202-C146282-sri-retest-full-value.spec.ts | L3: 83 | M3: 17.7
A4: C146206 | B4: Open case | C4: Run 415 | D4: C146206 — SRI-WO-C5 — A match on part numbers on the work order's lines (`item_part_numb | E4: Failed — already reported | G4: Error: these rows show only the characters typed instead of the whole value: ["Part number: \n786","Part number: \n786","Part description: \n786","Part description: \n786","Part description: \n786","Part description: \n786","Part description: \n786"] expect(received).toHaveLength(expected) Expected length: 0 Received length: 7 Received array: ["Part number:· 786", "Part number:· 786", "Part description:· 786", "Part description:· 786", "Part description:· 786", "Part description:· 786", "Part description:· 786"] 187 | expect(onlyTyped, 188 | `these rows show only the characters typed instead o | H4: Nothing new to raise: this is the behaviour SV-10634 describes (status Ready to Fix). It should pass once that fix reaches this build. | I4: SV-10634 | J4: Ready to Fix | K4: C146202-C146282-sri-retest-full-value.spec.ts | L4: 83 | M4: 19.4
A5: C146238 | B5: Open case | C5: Run 415 | D5: C146238 — SRI-PART-C1 — A match on bin location shows the FULL value on the row | E5: Failed — already reported | G5: Error: these rows show only the characters typed instead of the whole value: ["Bin: \nH3B","Bin: \nH3B","Bin: \nH3B","Bin: \nH3B","Bin: \nH3B","Bin: \nH3B","Bin: \nH3B","Bin: \nH3B","Bin: \nH3B","Bin: \nH3B","Bin: \nH3B","Bin: \nH3B","Bin: \nH3B","Bin: \nH3B","Bin: \nH3B","Bin: \nH3B","Bin: \nH3B","Bin: \nH3B","Bin: \nH3B","Bin: \nH3B"] expect(received).toHaveLength(expected) Expected length: 0 Received length: 20 Received array: ["Bin:· H3B", "Bin:· H3B", "Bin:· H3B", "Bin:· H3B", "Bin:· H3B", "Bin:· H3B", "Bin:· H3B", "Bin:· H3B", "Bin:· H3B", "Bin:· H3B", …] 187 | expect(onlyTyped, 188 | `t | H5: Nothing new to raise: this is the behaviour SV-10634 describes (status Ready to Fix). It should pass once that fix reaches this build. | I5: SV-10634 | J5: Ready to Fix | K5: C146202-C146282-sri-retest-full-value.spec.ts | L5: 83 | M5: 17.6
A6: C146242 | B6: Open case | C6: Run 415 | D6: C146242 — SRI-PART-C5 — A match on tags shows the FULL value on the row | E6: Failed — already reported | G6: Error: these rows show only the characters typed instead of the whole value: ["Tag: \n496","Tag: \n496"] expect(received).toHaveLength(expected) Expected length: 0 Received length: 2 Received array: ["Tag:· 496", "Tag:· 496"] 187 | expect(onlyTyped, 188 | `these rows show only the characters typed instead of the whole value: ${JSON.stringify(onlyTyped)}`) > 189 | .toHaveLength(0); | ^ 190 | }); 191 | } 192 | at /tmp/claude-0/-home-user-Manual-test-Cases/126e0959-4bca-54ed-8b95-71a191ca38d1/scratchpad/clean3/repo/build/global-search/e2e/tests/C146202-C146282-sri-retest-full-value.spec.ts:189:8 | H6: Nothing new to raise: this is the behaviour SV-10634 describes (status Ready to Fix). It should pass once that fix reaches this build. | I6: SV-10634 | J6: Ready to Fix | K6: C146202-C146282-sri-retest-full-value.spec.ts | L6: 83 | M6: 18.4
A7: C146252 | B7: Open case | C7: Run 415 | D7: C146252 — SRI-VEND-C3 — A match on a contact's telephone shows the FULL value on the row | E7: Failed — already reported | G7: Error: these rows show only the characters typed instead of the whole value: ["Address: \n965","Contact match: \n965","Contact match: \n965","Contact match: \n965","Contact match: \n965","Contact match: \n965","Contact match: \n965"] expect(received).toHaveLength(expected) Expected length: 0 Received length: 7 Received array: ["Address:· 965", "Contact match:· 965", "Contact match:· 965", "Contact match:· 965", "Contact match:· 965", "Contact match:· 965", "Contact match:· 965"] 187 | expect(onlyTyped, 188 | `these rows show only the characters typed instead of the whole value: ${JSON.stringif | H7: Nothing new to raise: this is the behaviour SV-10634 describes (status Ready to Fix). It should pass once that fix reaches this build. | I7: SV-10634 | J7: Ready to Fix | K7: C146202-C146282-sri-retest-full-value.spec.ts | L7: 83 | M7: 17.6
A8: C146271 | B8: Open case | C8: Run 415 | D8: C146271 — SRI-PO-C1 — A match on part numbers on the PO shows the FULL value on the row | E8: Failed — already reported | G8: Error: these rows show only the characters typed instead of the whole value: ["Part number: \n0123"] expect(received).toHaveLength(expected) Expected length: 0 Received length: 1 Received array: ["Part number:· 0123"] 187 | expect(onlyTyped, 188 | `these rows show only the characters typed instead of the whole value: ${JSON.stringify(onlyTyped)}`) > 189 | .toHaveLength(0); | ^ 190 | }); 191 | } 192 | at /tmp/claude-0/-home-user-Manual-test-Cases/126e0959-4bca-54ed-8b95-71a191ca38d1/scratchpad/clean3/repo/build/global-search/e2e/tests/C146202-C146282-sri-retest-full-value.spec.ts:189:8 | H8: Nothing new to raise: this is the behaviour SV-10634 describes (status Ready to Fix). It should pass once that fix reaches this build. | I8: SV-10634 | J8: Ready to Fix | K8: C146202-C146282-sri-retest-full-value.spec.ts | L8: 83 | M8: 17.6
A9: C146272 | B9: Open case | C9: Run 415 | D9: C146272 — SRI-PO-C2 — A match on part descriptions on the PO shows the FULL value on the | E9: Failed — already reported | G9: Error: these rows show only the characters typed instead of the whole value: ["Part description: \n786","Part description: \n786","Part number: \n786","Part description: \n786"] expect(received).toHaveLength(expected) Expected length: 0 Received length: 4 Received array: ["Part description:· 786", "Part description:· 786", "Part number:· 786", "Part description:· 786"] 187 | expect(onlyTyped, 188 | `these rows show only the characters typed instead of the whole value: ${JSON.stringify(onlyTyped)}`) > 189 | .toHaveLength(0); | ^ 190 | }); 191 | } 192 | at /tmp/claude-0/-home-user-Manual-test-Ca | H9: Nothing new to raise: this is the behaviour SV-10634 describes (status Ready to Fix). It should pass once that fix reaches this build. | I9: SV-10634 | J9: Ready to Fix | K9: C146202-C146282-sri-retest-full-value.spec.ts | L9: 83 | M9: 19.2
A10: C146209 | B10: Open case | C10: Run 415 | D10: C146209 — each row shows the COMPLETE telephone, with the typed part inside it | E10: Failed — already reported | G10: Error: these rows show only the digits typed instead of the whole telephone: ["Contact match: \n0900","Contact match: \n0900","Contact match: \n0900","Contact match: \n0900","Contact match: \n0900","Contact match: \n0900","Contact match: \n0900","Contact match: \n0900","Contact match: \n0900","Contact match: \n0900","Contact match: \n0900","Contact match: \n0900","Contact match: \n0900","Contact match: \n0900","Contact match: \n0900"] expect(received).toHaveLength(expected) Expected length: 0 Received length: 15 Received array: ["Contact match:· 0900", "Contact match:· 0900", "Contact match:· | H10: Nothing new to raise: this is the behaviour SV-10634 describes (status Ready to Fix). It should pass once that fix reaches this build. | I10: SV-10634 | J10: Ready to Fix | K10: C146209-C146223-sri-customers.spec.ts | L10: 84 | M10: 9.7
A11: C146222 | B11: Open case | C11: Run 415 | D11: C146222 — the customer row shows every field the requirement names | E11: Failed — already reported | G11: Error: the customer row is missing ["telephone on hover"]. Row reads "7 Star Truck Repair 32 open 305 Harris Cape, Priscillabury, Nunavut". Hover added [] (pointer reached the row: true). expect(received).toHaveLength(expected) Expected length: 0 Received length: 1 Received array: ["telephone on hover"] 209 | expect(missing, `the customer row is missing ${JSON.stringify(missing)}. Row reads "${r.text}". ` + 210 | `Hover added ${JSON.stringify(hov.gained)} (pointer reached the row: ${hoverReached}).`) > 211 | .toHaveLength(0); | ^ 212 | }); 213 | 214 | test('C146223 — a soft match is drawn as a | H11: Nothing new to raise: this is the behaviour SV-10635 describes (status Ready to Fix). It should pass once that fix reaches this build. | I11: SV-10635 | J11: Ready to Fix | K11: C146209-C146223-sri-customers.spec.ts | L11: 162 | M11: 11.4

Sheet Our test's fault
A1: Failures caused by the test itself, not the product. Each test has been fixed; the last two columns show it re-run on the same build.
A2: Case | B2: Case in TestRail | C2: Test run | D2: What the test checks | E2: Result | F2: Likely cause | G2: What happened | H2: What needs to be done | I2: Ticket | J2: Ticket status (read live) | K2: Spec file | L2: Line | M2: Seconds | N2: Re-run after fixing the test | O2: Re-run detail
A3: C146245 | B3: Open case | C3: Run 415 | D3: C146245 — Vendors: the whole telephone is shown, with the typed part marked inside it | E3: Failed — our test's fault | G3: Error: CONTROL FAILED: no highlight found anywhere on row 8, so anything said below about an unhighlighted line is about this reader expect(received).toBeGreaterThan(expected) Expected: > 0 Received: 0 247 | expect(r.marks.length, 248 | `CONTROL FAILED: no highlight found anywhere on row ${r.index}, so anything said below about ` + > 249 | `an unhighlighted line is about this reader`).toBeGreaterThan(0); | ^ 250 | // …then the requirement itself: highlighted in the primary AND secondary text. 251 | expect(unmarkedLines(r, TERM), 252 | `row ${r.index}: the typed text is shown on these lines wit | H3: The test has been fixed. Re-run after the fix: Passed. | K3: C146224-C146284-sri-entities.spec.ts | L3: 232 | M3: 9.9 | N3: Passed
A4: C146266 | B4: Open case | C4: Run 415 | D4: C146266 — Purchase Orders: the whole PO number is shown, with the typed part marked inside it | E4: Failed — our test's fault | G4: Error: CONTROL FAILED: no highlight found anywhere on row 11, so anything said below about an unhighlighted line is about this reader expect(received).toBeGreaterThan(expected) Expected: > 0 Received: 0 247 | expect(r.marks.length, 248 | `CONTROL FAILED: no highlight found anywhere on row ${r.index}, so anything said below about ` + > 249 | `an unhighlighted line is about this reader`).toBeGreaterThan(0); | ^ 250 | // …then the requirement itself: highlighted in the primary AND secondary text. 251 | expect(unmarkedLines(r, TERM), 252 | `row ${r.index}: the typed text is shown on these lines wi | H4: The test has been fixed. Re-run after the fix: Passed. | K4: C146224-C146284-sri-entities.spec.ts | L4: 232 | M4: 9.8 | N4: Passed
A5: C146247 | B5: Open case | C5: Run 415 | D5: C146247 — Vendors: the highlight marks the match inside the text, not instead of it | E5: Failed — our test's fault | G5: Error: CONTROL FAILED: no highlight anywhere on row 8 expect(received).toBeGreaterThan(expected) Expected: > 0 Received: 0 310 | expect(rows.length).toBeGreaterThan(0); 311 | for (const r of rows) { > 312 | expect(r.marks.length, `CONTROL FAILED: no highlight anywhere on row ${r.index}`).toBeGreaterThan(0); | ^ 313 | expect(unmarkedLines(r, TERM), 314 | `row ${r.index}: the typed text appears on these lines unhighlighted`).toEqual([]); 315 | expect(r.title.segs.some((x) => !x.marked), at /tmp/claude-0/-home-user-Manual-test-Cases/126e0959-4bca-54ed-8b95-71a191ca38d1/scratchpad/clean3/repo/buil | H5: The test has been fixed. Re-run after the fix: Passed. | K5: C146224-C146284-sri-entities.spec.ts | L5: 305 | M5: 9.9 | N5: Passed
A6: C146268 | B6: Open case | C6: Run 415 | D6: C146268 — Purchase Orders: the highlight marks the match inside the text, not instead of it | E6: Failed — our test's fault | G6: Error: CONTROL FAILED: no highlight anywhere on row 11 expect(received).toBeGreaterThan(expected) Expected: > 0 Received: 0 310 | expect(rows.length).toBeGreaterThan(0); 311 | for (const r of rows) { > 312 | expect(r.marks.length, `CONTROL FAILED: no highlight anywhere on row ${r.index}`).toBeGreaterThan(0); | ^ 313 | expect(unmarkedLines(r, TERM), 314 | `row ${r.index}: the typed text appears on these lines unhighlighted`).toEqual([]); 315 | expect(r.title.segs.some((x) => !x.marked), at /tmp/claude-0/-home-user-Manual-test-Cases/126e0959-4bca-54ed-8b95-71a191ca38d1/scratchpad/clean3/repo/bui | H6: The test has been fixed. Re-run after the fix: Passed. | K6: C146224-C146284-sri-entities.spec.ts | L6: 305 | M6: 9.9 | N6: Passed
A7: C146306 | B7: Open case | C7: Run 415 | D7: C146306 — someone without access sees no rows AND no count | E7: Failed — our test's fault | G7: Error: Staging needs a live session cookie. Sign in to app.staging.shopview.com in a browser, then set GS_SSO and GS_PHPSESSID (and GS_CF if Cloudflare is in front) — or point GS_STAGING_ENVF at a file holding SV_SSO_SESSION=, PHPSESSID= and CF_CLEARANCE=. Staging uses Google sign-in, so there is no username and password to script. See e2e/.env.example. at ../fixtures/boot.ts:421 419 | const valueOf = (name: string) => SOURCES.find(([n]) => n === name)?.[1] ?? ''; 420 | if (!valueOf('sv_sso_session') || !valueOf('PHPSESSID')) { > 421 | throw new Error( | ^ 422 | 'Staging needs a live session c | H7: The test has been fixed. Re-run after the fix: Passed. | K7: C146285-C146306-sri-all-tab.spec.ts | L7: 368 | M7: 6.9 | N7: Passed
A8: C44809 | B8: Open case | C8: Run 415 | D8: C44809 — Down and Up move the highlight across result rows only | E8: Failed — our test's fault | G8: TimeoutError: locator.click: Timeout 60000ms exceeded. Call log: - waiting for locator('.search-modal input') - locator resolved to <input value="" type="text" tabindex="0" role="combobox" autocorrect="off" autocomplete="off" spellcheck="false" aria-label="Search" aria-expanded="true" autocapitalize="off" data-autofocus="true" enterkeyhint="search" aria-autocomplete="list" data-test-id="search_modal_input" aria-controls="search_modal_listbox" class="q-field__native q-placeholder" id="f_1fbe4b4b-e83a-485d-80e8-c9e8618fdbe0" placeholder="Search work orders, customers, parts and more" aria-active | H8: The test has been fixed. Re-run after the fix: Passed. | K8: C44804-C55683-panel-keyboard.spec.ts | L8: 76 | M8: 63.5 | N8: Passed
A9: C45144 | B9: Open case | C9: Run 415 | D9: C45144 — parts appear only with Catalog & Inventory access | E9: Failed — our test's fault | G9: Error: parts hidden with access granted expect(received).toBeGreaterThan(expected) Expected: > 0 Received: 0 110 | expect((await search(s.page, FIXTURE)).counts['Parts'] ?? 0, 'parts shown without access').toBeFalsy(); 111 | await asTechnicianWith([...new Set([...all, parts])]); > 112 | expect((await search(s.page, FIXTURE)).counts['Parts'] ?? 0, 'parts hidden with access granted').toBeGreaterThan(0); | ^ 113 | }); 114 | 115 | test('C45146 — removing customer access removes customers AND vehicles @C45146', async () => { at /tmp/claude-0/-home-user-Manual-test-Cases/126e0959-4bca-54ed-8b95-71a1 | H9: The test has been fixed. Re-run after the fix: Passed. | K9: access-and-location.spec.ts | L9: 103 | M9: 27.8 | N9: Passed
A10: C45146 | B10: Open case | C10: Run 415 | D10: C45146 — removing customer access removes customers AND vehicles | E10: Failed — our test's fault | G10: Error: customers still shown expect(received).toBeFalsy() Received: 20 121 | await asTechnicianWith(all.filter((id: string) => id !== cust)); 122 | const p = await search(s.page, FIXTURE); > 123 | expect(p.counts['Customers'] ?? 0, 'customers still shown').toBeFalsy(); | ^ 124 | expect(p.counts['Assets'] ?? 0, 'vehicles still shown — they depend on customer access too').toBeFalsy(); 125 | }); 126 | at /tmp/claude-0/-home-user-Manual-test-Cases/126e0959-4bca-54ed-8b95-71a191ca38d1/scratchpad/clean3/repo/build/global-search/e2e/tests/access-and-location.spec.ts:123:63 | H10: The test has been fixed. Re-run after the fix: Passed. | K10: access-and-location.spec.ts | L10: 115 | M10: 12.6 | N10: Passed
A11: C45147 | B11: Open case | C11: Run 415 | D11: C45147 — a time-clock-only person gets nothing at all | E11: Failed — our test's fault | G11: Error: All returned results expect(received).toBeFalsy() Received: 124 131 | await asTechnicianWith(idsOf(['timesheetsView'])); 132 | const p = await search(s.page, FIXTURE); > 133 | for (const [tab, v] of Object.entries(p.counts)) expect(v ?? 0, `${tab} returned results`).toBeFalsy(); | ^ 134 | }); 135 | 136 | /** at /tmp/claude-0/-home-user-Manual-test-Cases/126e0959-4bca-54ed-8b95-71a191ca38d1/scratchpad/clean3/repo/build/global-search/e2e/tests/access-and-location.spec.ts:133:94 | H11: The test has been fixed. Re-run after the fix: Passed. | K11: access-and-location.spec.ts | L11: 127 | M11: 12.9 | N11: Passed
A12: C45143 | B12: Open case | C12: Run 415 | D12: C45143 — a part-sales role sees part sales but not parts or suppliers | E12: Failed — our test's fault | G12: Error: parts shown to a part-sales-only role expect(received).toBeFalsy() Received: 15 158 | const p = await search(s.page, FIXTURE); 159 | expect(p.counts['Part sales'] ?? 0, 'part sales hidden from a part-sales role').toBeGreaterThan(0); > 160 | expect(p.counts['Parts'] ?? 0, 'parts shown to a part-sales-only role').toBeFalsy(); | ^ 161 | expect(p.counts['Vendors'] ?? 0, 'suppliers shown to a part-sales-only role').toBeFalsy(); 162 | }); 163 | at /tmp/claude-0/-home-user-Manual-test-Cases/126e0959-4bca-54ed-8b95-71a191ca38d1/scratchpad/clean3/repo/build/global-search/e2e/tests/access-and-loc | H12: The test has been fixed. Re-run after the fix: Passed. | K12: access-and-location.spec.ts | L12: 143 | M12: 12.5 | N12: Passed
A13: C45151 | B13: Open case | C13: Run 415 | D13: C45151 · C45152 · C55684 — search is limited to the shop you are in, and follows you | E13: Failed — our test's fault | G13: Error: a job could not be created at each shop expect(received).toBeTruthy() Received: undefined 190 | if (label === 'heavy') heavyJob = num; else lethJob = num; 191 | } > 192 | expect(heavyJob && lethJob, 'a job could not be created at each shop').toBeTruthy(); | ^ 193 | await s.page.waitForTimeout(30_000); 194 | 195 | const readAt = async (wp: string) => { at /tmp/claude-0/-home-user-Manual-test-Cases/126e0959-4bca-54ed-8b95-71a191ca38d1/scratchpad/clean3/repo/build/global-search/e2e/tests/access-and-location.spec.ts:192:76 | H13: The test has been fixed. Re-run after the fix: Passed. | K13: access-and-location.spec.ts | L13: 173 | M13: 4.8 | N13: Passed
A14: C55716 | B14: Open case | C14: Run 415 | D14: C55716 — the record changed most recently is listed first [expected to fail: SV-10340] | E14: Failed — our test's fault | G14: TypeError: Cannot read properties of undefined (reading 'id') 144 | const mine = ((list.body as any)?.data?.collection ?? []).filter((v: any) => String(v.name).includes(tag)); 145 | const target = mine[1] ?? mine[0]; > 146 | const w = await api(s.page, 'POST', '/api/parts-catalogue/change-vendor', { ...target, vendor_id: target.id, id: target.id, name: lowered }); | ^ 147 | expect(w.status, `the rename was refused: ${w.text}`).toBeLessThan(400); 148 | 149 | // The edit appearing in the results IS the proof the entry rebuilt. Without it, a stale order at /tmp/claude-0/-home-user-Manual-test-Cas | H14: The test has been fixed. Re-run after the fix: Passed. | I14: SV-10340 | J14: OBSOLETE | K14: counts-and-ranking.spec.ts | L14: 105 | M14: 19.8 | N14: Passed
A15: C55724 | B15: Open case | C15: Run 415 | D15: C55724b — a name starting with the query ranks above one that only contains it (seeded) | E15: Failed — our test's fault | G15: Error: page.evaluate: TypeError: Failed to fetch (api.shopview.com) at https://app.staging.shopview.com/js/sentry.B6EvyTlO.js:17:8323 at eval (eval at evaluate (:290:30), <anonymous>:2:21) at UtilityScript.evaluate (<anonymous>:292:16) at UtilityScript.<anonymous> (<anonymous>:1:44) at https://app.staging.shopview.com/js/sentry.B6EvyTlO.js:17:8323 at eval (eval at evaluate (:290:30), <anonymous>:2:21) at UtilityScript.evaluate (<anonymous>:292:16) at UtilityScript.<anonymous> (<anonymous>:1:44) at createCustomer (/tmp/claude-0/-home-user-Manual-test-Cases/126e0959-4bca-54ed-8b95-71a191ca38d1/s | H15: The test has been fixed. Re-run after the fix: Passed. | K15: ranking-seeded.spec.ts | L15: 85 | M15: 0.8 | N15: Passed
A16: C55723 | B16: Open case | C16: Run 415 | D16: C55723 — a record matched on its name ranks above one matched on a lesser field | E16: Failed — our test's fault | G16: Error: page.evaluate: TypeError: Failed to fetch (api.shopview.com) at https://app.staging.shopview.com/js/sentry.B6EvyTlO.js:17:8323 at eval (eval at evaluate (:290:30), <anonymous>:2:21) at UtilityScript.evaluate (<anonymous>:292:16) at UtilityScript.<anonymous> (<anonymous>:1:44) at https://app.staging.shopview.com/js/sentry.B6EvyTlO.js:17:8323 at eval (eval at evaluate (:290:30), <anonymous>:2:21) at UtilityScript.evaluate (<anonymous>:292:16) at UtilityScript.<anonymous> (<anonymous>:1:44) at createCustomer (/tmp/claude-0/-home-user-Manual-test-Cases/126e0959-4bca-54ed-8b95-71a191ca38d1/s | H16: The test has been fixed. Re-run after the fix: Passed. | K16: ranking-seeded.spec.ts | L16: 98 | M16: 0.6 | N16: Passed
A17: C45139 | B17: Open case | C17: Run 415 | D17: C45139 — a match in a lesser field still finds the company | E17: Failed — our test's fault | G17: Error: page.evaluate: TypeError: Failed to fetch (api.shopview.com) at https://app.staging.shopview.com/js/sentry.B6EvyTlO.js:17:8323 at eval (eval at evaluate (:290:30), <anonymous>:2:21) at UtilityScript.evaluate (<anonymous>:292:16) at UtilityScript.<anonymous> (<anonymous>:1:44) at https://app.staging.shopview.com/js/sentry.B6EvyTlO.js:17:8323 at eval (eval at evaluate (:290:30), <anonymous>:2:21) at UtilityScript.evaluate (<anonymous>:292:16) at UtilityScript.<anonymous> (<anonymous>:1:44) at createCustomer (/tmp/claude-0/-home-user-Manual-test-Cases/126e0959-4bca-54ed-8b95-71a191ca38d1/s | H17: The test has been fixed. Re-run after the fix: Passed. | K17: ranking-seeded.spec.ts | L17: 115 | M17: 0.6 | N17: Passed
A18: C53586 | B18: Open case | C18: Run 415 | D18: C53586 — a newly created customer is findable within 30 seconds | E18: Failed — our test's fault | G18: Error: page.evaluate: TypeError: Failed to fetch (api.shopview.com) at https://app.staging.shopview.com/js/sentry.B6EvyTlO.js:17:8323 at eval (eval at evaluate (:290:30), <anonymous>:2:21) at UtilityScript.evaluate (<anonymous>:292:16) at UtilityScript.<anonymous> (<anonymous>:1:44) at https://app.staging.shopview.com/js/sentry.B6EvyTlO.js:17:8323 at eval (eval at evaluate (:290:30), <anonymous>:2:21) at UtilityScript.evaluate (<anonymous>:292:16) at UtilityScript.<anonymous> (<anonymous>:1:44) at createCustomer (/tmp/claude-0/-home-user-Manual-test-Cases/126e0959-4bca-54ed-8b95-71a191ca38d1/s | H18: The test has been fixed. Re-run after the fix: Passed. | K18: ranking-seeded.spec.ts | L18: 126 | M18: 0.6 | N18: Passed
A19: C53587 | B19: Open case | C19: Run 415 | D19: C53587 — a newly created record of another kind is findable within 30 seconds | E19: Failed — our test's fault | G19: Error: page.evaluate: TypeError: Failed to fetch (api.shopview.com) at https://app.staging.shopview.com/js/sentry.B6EvyTlO.js:17:8323 at eval (eval at evaluate (:290:30), <anonymous>:2:21) at UtilityScript.evaluate (<anonymous>:292:16) at UtilityScript.<anonymous> (<anonymous>:1:44) at https://app.staging.shopview.com/js/sentry.B6EvyTlO.js:17:8323 at eval (eval at evaluate (:290:30), <anonymous>:2:21) at UtilityScript.evaluate (<anonymous>:292:16) at UtilityScript.<anonymous> (<anonymous>:1:44) at createCustomer (/tmp/claude-0/-home-user-Manual-test-Cases/126e0959-4bca-54ed-8b95-71a191ca38d1/s | H19: The test has been fixed. Re-run after the fix: Passed. | K19: ranking-seeded.spec.ts | L19: 137 | M19: 0.7 | N19: Passed
A20: C55712 | B20: Open case | C20: Run 415 | D20: C55712 — Parts: what is relevant to where you are is still found from there | E20: Failed — our test's fault | G20: Error: expect(locator).toBeVisible() failed Locator: locator('.search-modal') Expected: visible Timeout: 20000ms Error: element(s) not found Call log: - Expect "toBeVisible" with timeout 20000ms - waiting for locator('.search-modal') at ../fixtures/search.ts:28 26 | const already = await page.locator(SEL.modal).count(); 27 | if (!already) { await page.keyboard.press('Control+k'); await page.waitForTimeout(1_400); } > 28 | await expect(page.locator(SEL.modal)).toBeVisible(); | ^ 29 | } 30 | 31 | export async function closePanel(page: Page) { at openPanel (/tmp/claude-0/-home-user-Manual-test-Ca | H20: The test has been fixed. Re-run after the fix: Passed. | K20: ranking-seeded.spec.ts | L20: 184 | M20: 21.9 | N20: Passed

Sheet Known faults - still there
A1: Tests written to reproduce a fault already recorded in a ticket. They failed in exactly the known way — that is the expected result.
A2: Case | B2: Case in TestRail | C2: Test run | D2: What the test checks | E2: Result | F2: Likely cause | G2: What happened | H2: What needs to be done | I2: Ticket | J2: Ticket status (read live) | K2: Spec file | L2: Line | M2: Seconds | N2: Re-run after fixing the test | O2: Re-run detail
A3: C146202 | B3: Open case | C3: Run 415 | D3: C146202 — SRI-WO-C1 — A match on VIN / serial number shows the FULL value on the row | E3: Known fault — still there | G3: Failed in the known way. The fault recorded under None is still there. | H3: Nothing new. Already known; waiting on the fix. | K3: C146202-C146282-sri-retest-full-value.spec.ts | L3: 83 | M3: 30.4
A4: C146214 | B4: Open case | C4: Run 415 | D4: C146214 — SRI-CUST-C1 — A match on the customer's own telephone shows the FULL value on | E4: Known fault — still there | G4: Failed in the known way. The fault recorded under None is still there. | H4: Nothing new. Already known; waiting on the fix. | K4: C146202-C146282-sri-retest-full-value.spec.ts | L4: 83 | M4: 29.5
A5: C146215 | B5: Open case | C5: Run 415 | D5: C146215 — SRI-CUST-C2 — A match on a contact's telephone shows the FULL value on the row | E5: Known fault — still there | G5: Failed in the known way. The fault recorded under None is still there. | H5: Nothing new. Already known; waiting on the fix. | K5: C146202-C146282-sri-retest-full-value.spec.ts | L5: 83 | M5: 28.3
A6: C146217 | B6: Open case | C6: Run 415 | D6: C146217 — SRI-CUST-C4 — A match on a contact's name shows the FULL value on the row | E6: Known fault — still there | G6: Failed in the known way. The fault recorded under None is still there. | H6: Nothing new. Already known; waiting on the fix. | K6: C146202-C146282-sri-retest-full-value.spec.ts | L6: 83 | M6: 29.1
A7: C146218 | B7: Open case | C7: Run 415 | D7: C146218 — SRI-CUST-C5 — A match on address line 2 shows the FULL value on the row | E7: Known fault — still there | G7: Failed in the known way. The fault recorded under None is still there. | H7: Nothing new. Already known; waiting on the fix. | K7: C146202-C146282-sri-retest-full-value.spec.ts | L7: 83 | M7: 27.5
A8: C146229 | B8: Open case | C8: Run 415 | D8: C146229 — SRI-ASSET-C1 — A match on VIN / serial number shows the FULL value on the row | E8: Known fault — still there | G8: Failed in the known way. The fault recorded under None is still there. | H8: Nothing new. Already known; waiting on the fix. | K8: C146202-C146282-sri-retest-full-value.spec.ts | L8: 83 | M8: 28.6
A9: C146230 | B9: Open case | C9: Run 415 | D9: C146230 — SRI-ASSET-C2 — A match on licence plate shows the FULL value on the row | E9: Known fault — still there | G9: Failed in the known way. The fault recorded under None is still there. | H9: Nothing new. Already known; waiting on the fix. | K9: C146202-C146282-sri-retest-full-value.spec.ts | L9: 83 | M9: 27.2
A10: C146239 | B10: Open case | C10: Run 415 | D10: C146239 — SRI-PART-C2 — A match on manufacturer shows the FULL value on the row | E10: Known fault — still there | G10: Failed in the known way. The fault recorded under None is still there. | H10: Nothing new. Already known; waiting on the fix. | K10: C146202-C146282-sri-retest-full-value.spec.ts | L10: 83 | M10: 28.8
A11: C146240 | B11: Open case | C11: Run 415 | D11: C146240 — SRI-PART-C3 — A match on vendor name shows the FULL value on the row | E11: Known fault — still there | G11: Failed in the known way. The fault recorded under None is still there. | H11: Nothing new. Already known; waiting on the fix. | K11: C146202-C146282-sri-retest-full-value.spec.ts | L11: 83 | M11: 30.8
A12: C146251 | B12: Open case | C12: Run 415 | D12: C146251 — SRI-VEND-C2 — A match on address line 2 shows the FULL value on the row | E12: Known fault — still there | G12: Failed in the known way. The fault recorded under None is still there. | H12: Nothing new. Already known; waiting on the fix. | K12: C146202-C146282-sri-retest-full-value.spec.ts | L12: 83 | M12: 28.3
A13: C146262 | B13: Open case | C13: Run 415 | D13: C146262 — SRI-PS-C1 — A match on the asset on the sale shows the FULL value on the row | E13: Known fault — still there | G13: Failed in the known way. The fault recorded under None is still there. | H13: Nothing new. Already known; waiting on the fix. | K13: C146202-C146282-sri-retest-full-value.spec.ts | L13: 83 | M13: 29.3
A14: C146263 | B14: Open case | C14: Run 415 | D14: C146263 — SRI-PS-C2 — A match on VIN / serial number shows the FULL value on the row | E14: Known fault — still there | G14: Failed in the known way. The fault recorded under None is still there. | H14: Nothing new. Already known; waiting on the fix. | K14: C146202-C146282-sri-retest-full-value.spec.ts | L14: 83 | M14: 28.7
... A17: C146282 | B17: Open case | C17: Run 415 | D17: C146282 — SRI-VINV-C1 — A match on the PO number the invoice belongs to shows the FULL v | E17: Known fault — still there | G17: Failed in the known way. The fault recorded under None is still there. | H17: Nothing new. Already known; waiting on the fix. | K17: C146202-C146282-sri-retest-full-value.spec.ts | L17: 83 | M17: 27.2
A18: C53476 | B18: Open case | C18: Run 415 | D18: C53476 — no count reads higher than 20 [expected to fail: SV-10320] | E18: Known fault — still there | G18: Failed in the known way. The fault recorded under SV-10320 is still there. | H18: Nothing new. Already known; waiting on the fix. | I18: SV-10320 | J18: OBSOLETE | K18: counts-and-ranking.spec.ts | L18: 27 | M18: 6
A19: C55716 | B19: Open case | C19: Run 415 | D19: C55716 (customers) — the customer changed most recently is listed first [expected to fail: SV-10340] | E19: Known fault — still there | G19: Failed in the known way. The fault recorded under SV-10340 is still there. | H19: Nothing new. Already known; waiting on the fix. | I19: SV-10340 | J19: OBSOLETE | K19: counts-and-ranking.spec.ts | L19: 161 | M19: 29.1
A20: C53601 | B20: Open case | C20: Run 415 | D20: C53601 — a catalogue-only part is findable [expected to fail: SV-10001] | E20: Known fault — still there | G20: Failed in the known way. The fault recorded under SV-10001 is still there. | H20: Nothing new. Already known; waiting on the fix. | I20: SV-10001 | J20: OBSOLETE | K20: findability.spec.ts | L20: 137 | M20: 9.3
A21: C53605 | B21: Open case | C21: Run 415 | D21: C53605 — year and make typed together find the vehicle [expected to fail: SV-10055] | E21: Known fault — still there | G21: Failed in the known way. The fault recorded under SV-10055 is still there. | H21: Nothing new. Already known; waiting on the fix. | I21: SV-10055 | J21: Done | K21: findability.spec.ts | L21: 150 | M21: 9.9
A22: C55660 | B22: Open case | C22: Run 415 | D22: C55660 — a fragment from the middle of a word finds the record [expected to fail: SV-10060] | E22: Known fault — still there | G22: Failed in the known way. The fault recorded under SV-10060 is still there. | H22: Nothing new. Already known; waiting on the fix. | I22: SV-10060 | J22: OBSOLETE | K22: findability.spec.ts | L22: 163 | M22: 9.1
A23: C55685 | B23: Open case | C23: Run 415 | D23: C55685 — a correct spelling returns only related records [expected to fail: SV-10025] | E23: Known fault — still there | G23: Failed in the known way. The fault recorded under SV-10025 is still there. | H23: Nothing new. Already known; waiting on the fix. | I23: SV-10025 | J23: OBSOLETE | K23: panel.spec.ts | L23: 159 | M23: 9.4

Sheet Known faults - gone
A1: Tests written to reproduce a known fault, where the fault did NOT happen this time. Worth confirming by hand: it may have been fixed.
A2: Case | B2: Case in TestRail | C2: Test run | D2: What the test checks | E2: Result | F2: Likely cause | G2: What happened | H2: What needs to be done | I2: Ticket | J2: Ticket status (read live) | K2: Spec file | L2: Line | M2: Seconds | N2: Re-run after fixing the test | O2: Re-run detail
A3: C146286 | B3: Open case | C3: Run 415 | D3: C146286 — no count anywhere reads higher than 20 [expected to fail: SV-10320] | E3: Known fault — did not reproduce | G3: The known fault recorded under SV-10320 did NOT happen this time — the behaviour may have been fixed. | H3: The ticket reads OBSOLETE. Confirm by hand that the behaviour is fixed; if it is, this test should stop expecting the fault. | I3: SV-10320 | J3: OBSOLETE | K3: C146285-C146306-sri-all-tab.spec.ts | L3: 83 | M3: 6.9

Sheet Stood down
A1: Tests that did not judge the product because something they need was missing. Each says what. These are not passes and not failures.
A2: Case | B2: Case in TestRail | C2: Test run | D2: What the test checks | E2: Result | F2: Likely cause | G2: What happened | H2: What needs to be done | I2: Ticket | J2: Ticket status (read live) | K2: Spec file | L2: Line | M2: Seconds | N2: Re-run after fixing the test | O2: Re-run detail
A3: C146208 | B3: Open case | C3: Run 415 | D3: C146208 — a soft match is drawn as a soft match | E3: Stood down | G3: the close-match rows carry no highlight at all on this build — the open fault SV-10740. The reader cannot be proved to work on them, so nothing here would be a sound statement about how a soft match is drawn. This starts running again when that fault is fixed. | H3: Supply what the reason names (a record or a login), then run this case again. Nothing was judged. | K3: C146197-C146208-sri-work-orders.spec.ts | L3: 267 | M3: 8.8
A4: C146223 | B4: Open case | C4: Run 415 | D4: C146223 — a soft match is drawn as a soft match | E4: Stood down | G4: close-match rows carry no highlight at all on this build — the open fault SV-10740 — so the reader cannot be proved to see one. This starts running again when that fault is fixed. | H4: Supply what the reason names (a record or a login), then run this case again. Nothing was judged. | K4: C146209-C146223-sri-customers.spec.ts | L4: 214 | M4: 16
A5: C146232 | B5: Open case | C5: Run 415 | D5: C146232 — Assets: a soft match is drawn as a soft match | E5: Stood down | G5: cannot be judged here: 1 of 1 near-miss rows carry no highlight at all (row 2: "≈ close match: PERTAB-C3 · 2019 ZZOBSIDIAM Trucks Hauler Per"). Either the product marks nothing on them or this reader cannot see the marks — and until that is settled, anything said about HOW they are drawn would be about the reader. Run this one by hand. | H5: Supply what the reason names (a record or a login), then run this case again. Nothing was judged. | K5: C146224-C146284-sri-entities.spec.ts | L5: 403 | M5: 9.8
A6: C146244 | B6: Open case | C6: Run 415 | D6: C146244 — Parts: a soft match is drawn as a soft match | E6: Stood down | G6: cannot be judged here: 1 of 1 near-miss rows carry no highlight at all (row 2: "≈ close match: ZZKRYPTOM Wheel Seal 8 Available PERTAB-7003"). Either the product marks nothing on them or this reader cannot see the marks — and until that is settled, anything said about HOW they are drawn would be about the reader. Run this one by hand. | H6: Supply what the reason names (a record or a login), then run this case again. Nothing was judged. | K6: C146224-C146284-sri-entities.spec.ts | L6: 403 | M6: 9.7
A7: C146256 | B7: Open case | C7: Run 415 | D7: C146256 — Vendors: a soft match is drawn as a soft match | E7: Stood down | G7: cannot be judged here: 1 of 1 near-miss rows carry no highlight at all (row 2: "≈ close match: ZZMAGENTO Traders (264) 400-0700 · 11 Per Tab"). Either the product marks nothing on them or this reader cannot see the marks — and until that is settled, anything said about HOW they are drawn would be about the reader. Run this one by hand. | H7: Supply what the reason names (a record or a login), then run this case again. Nothing was judged. | K7: C146224-C146284-sri-entities.spec.ts | L7: 403 | M7: 9.8
A8: C146265 | B8: Open case | C8: Run 415 | D8: C146265 — Part Sales: a soft match is drawn as a soft match | E8: Stood down | G8: cannot be judged here: 2 of 2 near-miss rows carry no highlight at all (row 2: "≈ close match: P2-2305 ZZSOFTHIP Logistics Estimate Admin Sh"). Either the product marks nothing on them or this reader cannot see the marks — and until that is settled, anything said about HOW they are drawn would be about the reader. Run this one by hand. | H8: Supply what the reason names (a record or a login), then run this case again. Nothing was judged. | K8: C146224-C146284-sri-entities.spec.ts | L8: 403 | M8: 9.8
A9: C146276 | B9: Open case | C9: Run 415 | D9: C146276 — Purchase Orders: a soft match is drawn as a soft match | E9: Stood down | G9: cannot be judged here: 2 of 2 near-miss rows carry no highlight at all (row 2: "≈ close match: I2-1536 ZZSOFTHIP Traders Fulfilled $37.00 · "). Either the product marks nothing on them or this reader cannot see the marks — and until that is settled, anything said about HOW they are drawn would be about the reader. Run this one by hand. | H9: Supply what the reason names (a record or a login), then run this case again. Nothing was judged. | K9: C146224-C146284-sri-entities.spec.ts | L9: 403 | M9: 9.8
A10: C146284 | B10: Open case | C10: Run 415 | D10: C146284 — Vendor Invoices: a soft match is drawn as a soft match | E10: Stood down | G10: cannot be judged here: 2 of 2 near-miss rows carry no highlight at all (row 2: "≈ close match: ZZSH-O_TYPO ZZSOFTHIP Traders Unpaid $37.00 ·"). Either the product marks nothing on them or this reader cannot see the marks — and until that is settled, anything said about HOW they are drawn would be about the reader. Run this one by hand. | H10: Supply what the reason names (a record or a login), then run this case again. Nothing was judged. | K10: C146224-C146284-sri-entities.spec.ts | L10: 403 | M10: 9.8
A11: C146291 | B11: Open case | C11: Run 415 | D11: C146291 — typing a full record number puts that record at the very top | E11: Stood down | G11: the pinned top result was withdrawn by the QA lead on 2026-09-29 — this is not a defect and the check is not asserted | H11: Supply what the reason names (a record or a login), then run this case again. Nothing was judged. | K11: C146285-C146306-sri-all-tab.spec.ts | L11: 158 | M11: 0
A12: C45138 | B12: Open case | C12: Run 415 | D12: C45138 — unpaid supplier invoices rank above paid ones | E12: Stood down | G12: needs both a paid and an unpaid invoice in one result set — mark one paid to run this | H12: Supply what the reason names (a record or a login), then run this case again. Nothing was judged. | K12: counts-and-ranking.spec.ts | L12: 79 | M12: 9.2
A13: C44839 | B13: Open case | C13: Run 415 | D13: C44839 — a misspelled word still finds the record (customerName) | E13: Stood down | G13: customerName has no word long enough to damage fairly: "" | H13: Supply what the reason names (a record or a login), then run this case again. Nothing was judged. | K13: findability-matching.spec.ts | L13: 115 | M13: 0
A14: C44840 | B14: Open case | C14: Run 415 | D14: C44840 — a misspelled word still finds the record (customerName) | E14: Stood down | G14: customerName has no word long enough to damage fairly: "" | H14: Supply what the reason names (a record or a login), then run this case again. Nothing was judged. | K14: findability-matching.spec.ts | L14: 115 | M14: 0
... A66: C44830 | B66: Open case | C66: Run 415 | D66: C44830 — groups appear in the order the requirement fixes | E66: Stood down | G66: fewer than two groups came back, so order cannot be judged | H66: Supply what the reason names (a record or a login), then run this case again. Nothing was judged. | K66: structure-and-scoping.spec.ts | L66: 94 | M66: 7

Sheet Passed
A1: Tests that passed.
A2: Case | B2: Case in TestRail | C2: Test run | D2: What the test checks | E2: Result | F2: Likely cause | G2: What happened | H2: What needs to be done | I2: Ticket | J2: Ticket status (read live) | K2: Spec file | L2: Line | M2: Seconds | N2: Re-run after fixing the test | O2: Re-run detail
A3: C146197 | B3: Open case | C3: Run 415 | D3: C146197 — the whole WO number is shown, with what you typed marked inside it | E3: Passed | G3: Passed. | K3: C146197-C146208-sri-work-orders.spec.ts | L3: 105 | M3: 0
A4: C146198 | B4: Open case | C4: Run 415 | D4: C146198 — nothing cut off has eaten the match or what tells the rows apart | E4: Passed | G4: Passed. | K4: C146197-C146208-sri-work-orders.spec.ts | L4: 146 | M4: 9.8
A5: C146199 | B5: Open case | C5: Run 415 | D5: C146199 — the highlight marks the match inside the text, not instead of it | E5: Passed | G5: Passed. | K5: C146197-C146208-sri-work-orders.spec.ts | L5: 180 | M5: 0
A6: C146200 | B6: Open case | C6: Run 415 | D6: C146200 — two records sharing the typed text can be told apart from the rows alone | E6: Passed | G6: Passed. | K6: C146197-C146208-sri-work-orders.spec.ts | L6: 193 | M6: 0
A7: C146201 | B7: Open case | C7: Run 415 | D7: C146201 — rows with the same bold line still differ somewhere you can see | E7: Passed | G7: Passed. | K7: C146197-C146208-sri-work-orders.spec.ts | L7: 203 | M7: 0
A8: C146207 | B8: Open case | C8: Run 415 | D8: C146207 — the row shows every field the requirement names | E8: Passed | G8: Passed. | K8: C146197-C146208-sri-work-orders.spec.ts | L8: 221 | M8: 0
A9: C146204 | B9: Open case | C9: Run 415 | D9: C146204 — SRI-WO-C3 — A match on service advisor name shows the FULL value on the row | E9: Passed | G9: Passed. | K9: C146202-C146282-sri-retest-full-value.spec.ts | L9: 83 | M9: 0
A10: C146220 | B10: Open case | C10: Run 415 | D10: C146220 — SRI-CUST-C7 — A match on state / province shows the FULL value on the row | E10: Passed | G10: Passed. | K10: C146202-C146282-sri-retest-full-value.spec.ts | L10: 83 | M10: 18
A11: C146221 | B11: Open case | C11: Run 415 | D11: C146221 — SRI-CUST-C8 — A match on postal code shows the FULL value on the row | E11: Passed | G11: Passed. | K11: C146202-C146282-sri-retest-full-value.spec.ts | L11: 83 | M11: 26.9
A12: C146241 | B12: Open case | C12: Run 415 | D12: C146241 — SRI-PART-C4 — A match on category shows the FULL value on the row | E12: Passed | G12: Passed. | K12: C146202-C146282-sri-retest-full-value.spec.ts | L12: 83 | M12: 28.4
A13: C146250 | B13: Open case | C13: Run 415 | D13: C146250 — SRI-VEND-C1 — A match on email address shows the FULL value on the row | E13: Passed | G13: Passed. | K13: C146202-C146282-sri-retest-full-value.spec.ts | L13: 83 | M13: 30.8
A14: C146210 | B14: Open case | C14: Run 415 | D14: C146210 — nothing cut off has eaten the match or what tells the rows apart | E14: Passed | G14: Passed. | K14: C146209-C146223-sri-customers.spec.ts | L14: 106 | M14: 9.7
... A84: C44838 | B84: Open case | C84: Run 415 | D84: C44838 — status and stock badges appear on the rows that carry them | E84: Passed | G84: Passed. | K84: findability-matching.spec.ts | L84: 279 | M84: 7
C85: Run 415 | D85: seed control — the regression dataset is present | E85: Passed | G85: Passed. | K85: findability.spec.ts | L85: 27 | M85: 9.6
A86: C53578 | B86: Open case | C86: Run 415 | D86: C53578 — typing "Bridgeport" finds it under Work orders | E86: Passed | G86: Passed. | K86: findability.spec.ts | L86: 61 | M86: 19.9
A87: C53580 | B87: Open case | C87: Run 415 | D87: C53580 — typing "ZZT-4471" finds it under Assets | E87: Passed | G87: Passed. | K87: findability.spec.ts | L87: 61 | M87: 18.8
A88: C53581 | B88: Open case | C88: Run 415 | D88: C53581 — typing "Bridgeport" finds it under Assets | E88: Passed | G88: Passed. | K88: findability.spec.ts | L88: 61 | M88: 19.9
A89: C53607 | B89: Open case | C89: Run 415 | D89: C53607 — typing "Kestrel" finds it under Parts | E89: Passed | G89: Passed. | K89: findability.spec.ts | L89: 61 | M89: 19.2
A90: C55663 | B90: Open case | C90: Run 415 | D90: C55663 — typing "(614) 555-0188" finds it under Vendors | E90: Passed | G90: Passed. | K90: findability.spec.ts | L90: 61 | M90: 20
A91: C55665 | B91: Open case | C91: Run 415 | D91: C55665 — typing "Bridgeport" finds it under Part sales | E91: Passed | G91: Passed. | K91: findability.spec.ts | L91: 61 | M91: 19.7
A92: C55666 | B92: Open case | C92: Run 415 | D92: C55666 — typing "ZZT-88-4412" finds it under Parts | E92: Passed | G92: Passed. | K92: findability.spec.ts | L92: 61 | M92: 19.6
A93: C55667 | B93: Open case | C93: Run 415 | D93: C55667 — typing "Bridgeport" finds it under Customers | E93: Passed | G93: Passed. | K93: findability.spec.ts | L93: 61 | M93: 19.7
A94: C55668 | B94: Open case | C94: Run 415 | D94: C55668 — typing "Kestrel" finds it under Vendors | E94: Passed | G94: Passed. | K94: findability.spec.ts | L94: 61 | M94: 19.6
A95: C55671 | B95: Open case | C95: Run 415 | D95: C55671 — capitals never change what is found | E95: Passed | G95: Passed. | K95: findability.spec.ts | L95: 111 | M95: 28.4
A96: C55688 | B96: Open case | C96: Run 415 | D96: C55688 — typing a make returns only that make | E96: Passed | G96: Passed. | K96: findability.spec.ts | L96: 119 | M96: 9.6
A97: C55689 | B97: Open case | C97: Run 415 | D97: C55689 — typing a year returns only that year | E97: Passed | G97: Passed. | K97: findability.spec.ts | L97: 126 | M97: 9.2
... A220: C44811 | B220: Open case | C220: Run 415 | D220: C44811 — Ctrl+Enter opens the highlighted result in a new browser tab | E220: Passed | G220: Passed. | K220: tabs-groups-navigation.spec.ts | L220: 196 | M220: 7.5
