Workbook

Sheet How to run this
A1: Search Results Integrity — manual test pack
A3: Where to run it: https://app.staging.shopview.com · workplace: Staging Heavy Duty - 9919
A4: Sign in with any account that can see all of: Work Orders, Customers, Assets, Parts, Vendors, Part Sales, Purchase Orders and Vendor Invoices.
A5: Open search with the magnifying glass in the header, or press Ctrl+K (Cmd+K on a Mac).
A7: What this pack is for
A8: These tests do NOT check whether search finds the right record. They check whether the row you are looking at TELLS YOU WHAT YOU NEED TO KNOW — so you can pick the right record without opening it, and tell two similar records apart.
A9: It came out of SV-10619 and SV-10551. Both are the same problem: you type 123786 and a row shows you only 786 — which is also what a row for 185786 would show.
A11: Where these live in TestRail
A12: All 110 cases are in TestRail under Global Search > Global Search - Enhancement (Aug 2026) > Search Results Integrity — result row display (SV-10619 / SV-10551), in nine folders, one per tab.
A13: They are all in test run 415, "Global Search V2 — Full Suite": https://shopview.testrail.io/index.php?/runs/view/415
A14: The TestRail column in each sheet links straight to that case. Record your result in TestRail; this sheet is for working through them.
A16: How to read a row
... A28: Write exactly what you typed and exactly what the row showed, and take a screenshot of the whole row. "It was wrong" cannot be fixed by a developer; "I typed 965 and the row showed 9..." can.

Sheet Summary
A1: Search Results Integrity — progress
A3: Environment: https://app.staging.shopview.com · workplace: Staging Heavy Duty - 9919
A5: Tab | B5: Tests | C5: Pass | D5: Fail | E5: Blocked | F5: Not run | G5: Held | H5: Recorded
A6: Work Orders | B6: 12 | C6: =COUNTIF('Work Orders'!$K$2:$K$13,"Pass") | D6: =COUNTIF('Work Orders'!$K$2:$K$13,"Fail") | E6: =COUNTIF('Work Orders'!$K$2:$K$13,"Blocked") | F6: =COUNTIF('Work Orders'!$K$2:$K$13,"Not run") | G6: =COUNTIF('Work Orders'!$K$2:$K$13,"HELD - do not run") | H6: =SUM(C6:G6)
A7: Customers | B7: 16 | C7: =COUNTIF('Customers'!$K$2:$K$17,"Pass") | D7: =COUNTIF('Customers'!$K$2:$K$17,"Fail") | E7: =COUNTIF('Customers'!$K$2:$K$17,"Blocked") | F7: =COUNTIF('Customers'!$K$2:$K$17,"Not run") | G7: =COUNTIF('Customers'!$K$2:$K$17,"HELD - do not run") | H7: =SUM(C7:G7)
A8: Assets | B8: 9 | C8: =COUNTIF('Assets'!$K$2:$K$10,"Pass") | D8: =COUNTIF('Assets'!$K$2:$K$10,"Fail") | E8: =COUNTIF('Assets'!$K$2:$K$10,"Blocked") | F8: =COUNTIF('Assets'!$K$2:$K$10,"Not run") | G8: =COUNTIF('Assets'!$K$2:$K$10,"HELD - do not run") | H8: =SUM(C8:G8)
A9: Parts | B9: 12 | C9: =COUNTIF('Parts'!$K$2:$K$13,"Pass") | D9: =COUNTIF('Parts'!$K$2:$K$13,"Fail") | E9: =COUNTIF('Parts'!$K$2:$K$13,"Blocked") | F9: =COUNTIF('Parts'!$K$2:$K$13,"Not run") | G9: =COUNTIF('Parts'!$K$2:$K$13,"HELD - do not run") | H9: =SUM(C9:G9)
A10: Vendors | B10: 12 | C10: =COUNTIF('Vendors'!$K$2:$K$13,"Pass") | D10: =COUNTIF('Vendors'!$K$2:$K$13,"Fail") | E10: =COUNTIF('Vendors'!$K$2:$K$13,"Blocked") | F10: =COUNTIF('Vendors'!$K$2:$K$13,"Not run") | G10: =COUNTIF('Vendors'!$K$2:$K$13,"HELD - do not run") | H10: =SUM(C10:G10)
A11: Part Sales | B11: 9 | C11: =COUNTIF('Part Sales'!$K$2:$K$10,"Pass") | D11: =COUNTIF('Part Sales'!$K$2:$K$10,"Fail") | E11: =COUNTIF('Part Sales'!$K$2:$K$10,"Blocked") | F11: =COUNTIF('Part Sales'!$K$2:$K$10,"Not run") | G11: =COUNTIF('Part Sales'!$K$2:$K$10,"HELD - do not run") | H11: =SUM(C11:G11)
A12: Purchase Orders | B12: 11 | C12: =COUNTIF('Purchase Orders'!$K$2:$K$12,"Pass") | D12: =COUNTIF('Purchase Orders'!$K$2:$K$12,"Fail") | E12: =COUNTIF('Purchase Orders'!$K$2:$K$12,"Blocked") | F12: =COUNTIF('Purchase Orders'!$K$2:$K$12,"Not run") | G12: =COUNTIF('Purchase Orders'!$K$2:$K$12,"HELD - do not run") | H12: =SUM(C12:G12)
A13: Vendor Invoices | B13: 8 | C13: =COUNTIF('Vendor Invoices'!$K$2:$K$9,"Pass") | D13: =COUNTIF('Vendor Invoices'!$K$2:$K$9,"Fail") | E13: =COUNTIF('Vendor Invoices'!$K$2:$K$9,"Blocked") | F13: =COUNTIF('Vendor Invoices'!$K$2:$K$9,"Not run") | G13: =COUNTIF('Vendor Invoices'!$K$2:$K$9,"HELD - do not run") | H13: =SUM(C13:G13)
A14: All tab and cross-tab | B14: 22 | C14: =COUNTIF('All tab and cross-tab'!$K$2:$K$23,"Pass") | D14: =COUNTIF('All tab and cross-tab'!$K$2:$K$23,"Fail") | E14: =COUNTIF('All tab and cross-tab'!$K$2:$K$23,"Blocked") | F14: =COUNTIF('All tab and cross-tab'!$K$2:$K$23,"Not run") | G14: =COUNTIF('All tab and cross-tab'!$K$2:$K$23,"HELD - do not run") | H14: =SUM(C14:G14)
A15: TOTAL | B15: =SUM(B6:B14) | C15: =SUM(C6:C14) | D15: =SUM(D6:D14) | E15: =SUM(E6:E14) | F15: =SUM(F6:F14) | G15: =SUM(G6:G14) | H15: =SUM(H6:H14)
A17: The "Held" column counts tests the specification cannot yet answer. They are question Q1 on the "Questions for the PO" tab — they are not failures and must not be reported as any result until that question is answered.

Sheet Work Orders
A1: ID | B1: TestRail | C1: What you are checking | D1: Why it matters to a real user | E1: Before you start | F1: TYPE THIS | G1: What to do | H1: What you should see | I1: Where that comes from | J1: The exact wording of the requirement | K1: Result | L1: What you actually saw | M1: Ticket
A2: SRI-WO-A1 | B2: C146197 | C2: The whole matched value is shown, not just what you typed | D2: If the row shows only the characters I typed, I am reading my own query back. It tells me nothing about which record this is. | E2: A work order exists whose WO number contains this fragment somewhere other than the very start. NOTE: 2 rows come back sharing this fragment — perfect for this test | F2: ZZLONGROW | G2: 1. Open search and type the term in the green cell. 2. Open the Work Orders tab. 3. Look at each row WITHOUT opening it. 4. Write down the WO number exactly as the row shows it. | H2: Each row shows the COMPLETE WO number, with the bit you typed highlighted inside it. Seeing only what you typed, or a value cut short with "...", is a FAIL — that is SV-10619 and SV-10551. | I2: PRD v1.5, section 5.3 | J2: Every row has a left-side entity icon, a primary line (bold), a secondary line (subdued), and an optional right-side cluster (status badges, counts, and quick-action buttons on hover). The matched substring of the query is highlighted in the primary and secondary text — searching `Fib` highlights "Fib" in "S1-644 Fibridge Commercial".
A3: SRI-WO-A2 | B3: C146198 | C3: A long value is not cut off through the part that matched | D3: A row that cuts off at "9..." has hidden the one thing I was looking for. | E3: A work order whose text is long enough to overflow the search box (the box is a fixed width), with the matched characters near the END of the value. | F3: ZZLONGROW | G3: 1. Open search and type the term. 2. Open the Work Orders tab. 3. Look for any text ending in "...". 4. If you see one, write down what is hidden and what you typed. | H3: You can still identify the record. If the "..." has eaten the characters you typed, or eaten the part that tells this record from its neighbours, that is a FAIL. | I3: Story SV-9170 | J3: Each result row carries enough context to pick the right record without opening it — its identifier, who it belongs to, its status, and for work orders the unit number and vehicle, which is what tells two of the same customer's work orders apart.
A4: SRI-WO-A3 | B4: C146199 | C4: The highlight marks the match inside the text, not instead of it | D4: A highlight is meant to point at something. If it replaces the text, it points at nothing. | E4: Any work order you can find by typing part of what the row displays. | F4: ZZLONGROW | G4: 1. Open search and type the term. 2. Open the Work Orders tab. 3. Look at how the match is drawn on the row. | H4: The full text is on the row and the matched part is highlighted within it — exactly like the example in the requirement, where typing "Fib" shows the whole of "S1-644 Fibridge Commercial" with "Fib" marked. | I4: PRD v1.5, section 5.3 | J4: Every row has a left-side entity icon, a primary line (bold), a secondary line (subdued), and an optional right-side cluster (status badges, counts, and quick-action buttons on hover). The matched substring of the query is highlighted in the primary and secondary text — searching `Fib` highlights "Fib" in "S1-644 Fibridge Commercial".
A5: SRI-WO-B1 | B5: C146200 | C5: Two records sharing what you typed can be told apart | D5: This is the whole point. Type 123786 and if two rows both draw as "786", you cannot tell 123786 from 185786 without opening both. | E5: Two work orders exist whose WO number are DIFFERENT but share a run of characters. NOTE: 2 rows come back sharing this fragment — perfect for this test | F5: ZZLONGROW | G5: 1. Open search and type the term. 2. Open the Work Orders tab. 3. WITHOUT opening anything, write down which row is which. 4. If you cannot tell them apart, that is the failure — say so. | H5: You can say which row is which from the rows alone. Two rows that read the same is a FAIL — and note that the right number of rows does not rescue it. | I5: Story SV-9170 | J5: Each result row carries enough context to pick the right record without opening it — its identifier, who it belongs to, its status, and for work orders the unit number and vehicle, which is what tells two of the same customer's work orders apart.
A6: SRI-WO-B2 | B6: C146201 | C6: Two records with the same bold line differ somewhere you can see | D6: Real shops have two trucks of the same year/make/model and two vendors with the same name. If the rows are identical the list is useless. | E6: Two work orders whose bold first line is identical but which are different records. These were seeded for this suite. NOTE: 2 rows come back; at least two carry the same bold line | F6: ZZLONGROW | G6: 1. Open search and type the term. 2. Open the Work Orders tab. 3. Compare the two rows line by line. 4. Write down what, if anything, separates them. | H6: Something visible differs — the second line, a badge, a number. Two identical rows is a FAIL; write down both records and what actually differs between them in the data. | I6: Story SV-9170 | J6: Each result row carries enough context to pick the right record without opening it — its identifier, who it belongs to, its status, and for work orders the unit number and vehicle, which is what tells two of the same customer's work orders apart.
A7: SRI-WO-C1 | B7: C146202 | C7: A match on VIN / serial number shows the FULL value on the row | D7: a service advisor reads the VIN off the windscreen or the customer reads it down the phone | E7: A work order carrying a distinctive value in VIN / serial number — a value that appears in NO other field of that record. NOTE: proven to match on vin (exact) | F7: SVEWU82M5ETEJFWFA | G7: 1. Open search and type the term. 2. Open the Work Orders tab. 3. Find the record. Without opening it, read the SECOND line of the row. 4. It should carry a labelled note naming the field that matched. 5. Now check the value in that note against the record itself. | H7: The second line carries a labelled note — such as "Contact match: ...", "Matched: ...", "Unit: ...", "VIN: ..." — naming what matched, with the part you typed highlighted inside it. THE THING TO CHECK IS WHETHER THE VALUE IS COMPLETE. The note must show the WHOLE VIN / serial number value, not just the characters you typed. Open the record and compare. If you typed part of a longer value and the note shows only that part, this is a FAIL — it is SV-10619 and SV-10551, and it means two different records can draw identically. | I7: PRD v1.5, section 5.3 | J7: Every row has a left-side entity icon, a primary line (bold), a secondary line (subdued), and an optional right-side cluster (status badges, counts, and quick-action buttons on hover). The matched substring of the query is highlighted in the primary and secondary text — searching `Fib` highlights "Fib" in "S1-644 Fibridge Commercial".
A8: SRI-WO-C2 | B8: C195898 | C8: A match on lead technician name shows the FULL value on the row | D8: a foreman looks for "the job Danny is on" | E8: A work order carrying a distinctive value in lead technician name — a value that appears in NO other field of that record. NOTE: proven to match on lead_technician_name (word) | F8: Muzamil | G8: 1. Open search and type the term. 2. Open the Work Orders tab. 3. Find the record. Without opening it, read the SECOND line of the row. 4. It should carry a labelled note naming the field that matched. 5. Now check the value in that note against the record itself. | H8: The second line carries a labelled note — such as "Contact match: ...", "Matched: ...", "Unit: ...", "VIN: ..." — naming what matched, with the part you typed highlighted inside it. THE THING TO CHECK IS WHETHER THE VALUE IS COMPLETE. The note must show the WHOLE lead technician name value, not just the characters you typed. Open the record and compare. If you typed part of a longer value and the note shows only that part, this is a FAIL — it is SV-10619 and SV-10551, and it means two different records can draw identically. | I8: PRD v1.5, section 5.3 | J8: Every row has a left-side entity icon, a primary line (bold), a secondary line (subdued), and an optional right-side cluster (status badges, counts, and quick-action buttons on hover). The matched substring of the query is highlighted in the primary and secondary text — searching `Fib` highlights "Fib" in "S1-644 Fibridge Commercial".
A9: SRI-WO-C3 | B9: C146204 | C9: A match on service advisor name shows the FULL value on the row | D9: a manager looks for the jobs one advisor wrote up | E9: A work order carrying a distinctive value in service advisor name — a value that appears in NO other field of that record. NOTE: proven to match on service_advisor_name (word) | F9: Veljkovic | G9: 1. Open search and type the term. 2. Open the Work Orders tab. 3. Find the record. Without opening it, read the SECOND line of the row. 4. It should carry a labelled note naming the field that matched. 5. Now check the value in that note against the record itself. | H9: The second line carries a labelled note — such as "Contact match: ...", "Matched: ...", "Unit: ...", "VIN: ..." — naming what matched, with the part you typed highlighted inside it. THE THING TO CHECK IS WHETHER THE VALUE IS COMPLETE. The note must show the WHOLE service advisor name value, not just the characters you typed. Open the record and compare. If you typed part of a longer value and the note shows only that part, this is a FAIL — it is SV-10619 and SV-10551, and it means two different records can draw identically. | I9: PRD v1.5, section 5.3 | J9: Every row has a left-side entity icon, a primary line (bold), a secondary line (subdued), and an optional right-side cluster (status badges, counts, and quick-action buttons on hover). The matched substring of the query is highlighted in the primary and secondary text — searching `Fib` highlights "Fib" in "S1-644 Fibridge Commercial".
A10: SRI-WO-C4 | B10: C146205 | C10: A match on line item descriptions (parts and labor on the WO) shows the FULL value on the row | D10: a parts person asks "which job did that alternator go on?" | E10: A work order carrying a distinctive value in line item descriptions (parts and labor on the WO) — a value that appears in NO other field of that record. NOTE: 5 rows come back sharing this | F10: 786 | G10: 1. Open search and type the term. 2. Open the Work Orders tab. 3. Find the record. Without opening it, read the SECOND line of the row. 4. It should carry a labelled note naming the field that matched. 5. Now check the value in that note against the record itself. | H10: The second line carries a labelled note — such as "Contact match: ...", "Matched: ...", "Unit: ...", "VIN: ..." — naming what matched, with the part you typed highlighted inside it. THE THING TO CHECK IS WHETHER THE VALUE IS COMPLETE. The note must show the WHOLE line item descriptions (parts and labor on the WO) value, not just the characters you typed. Open the record and compare. If you typed part of a longer value and the note shows only that part, this is a FAIL — it is SV-10619 and SV-10551, and it means two different records can draw identically. | I10: PRD v1.5, section 5.3 | J10: Every row has a left-side entity icon, a primary line (bold), a secondary line (subdued), and an optional right-side cluster (status badges, counts, and quick-action buttons on hover). The matched substring of the query is highlighted in the primary and secondary text — searching `Fib` highlights "Fib" in "S1-644 Fibridge Commercial".
A11: SRI-WO-C5 | B11: C146206 | C11: A match on part numbers on the work order's lines (`item_part_numbers`) shows the FULL value on the row | D11: the same question asked with the number instead of the name | E11: A work order carrying a distinctive value in part numbers on the work order's lines (`item_part_numbers`) — a value that appears in NO other field of that record. NOTE: 2 rows come back sharing this | F11: 786 | G11: 1. Open search and type the term. 2. Open the Work Orders tab. 3. Find the record. Without opening it, read the SECOND line of the row. 4. It should carry a labelled note naming the field that matched. 5. Now check the value in that note against the record itself. | H11: The second line carries a labelled note — such as "Contact match: ...", "Matched: ...", "Unit: ...", "VIN: ..." — naming what matched, with the part you typed highlighted inside it. THE THING TO CHECK IS WHETHER THE VALUE IS COMPLETE. The note must show the WHOLE part numbers on the work order's lines (`item_part_numbers`) value, not just the characters you typed. Open the record and compare. If you typed part of a longer value and the note shows only that part, this is a FAIL — it is SV-10619 and SV-10551, and it means two different records can draw identically. | I11: PRD v1.5, section 5.3 | J11: Every row has a left-side entity icon, a primary line (bold), a secondary line (subdued), and an optional right-side cluster (status badges, counts, and quick-action buttons on hover). The matched substring of the query is highlighted in the primary and secondary text — searching `Fib` highlights "Fib" in "S1-644 Fibridge Commercial".
A12: SRI-WO-D1 | B12: C146207 | C12: The Work Orders row shows everything the specification promised | D12: Each field is there because somebody decided you need it to choose. A missing one is a choice you now have to make by opening records. | E12: Any work order that search returns, which has a value in each field named in the requirement column. | F12: ZZLONGROW | G12: 1. Open search and type something that returns the record. 2. Open the Work Orders tab. 3. Check the row against the requirement column, field by field. 4. Tick off each one. Write down any that is missing. | H12: Every field named in the requirement is on the row. Do not judge whether a missing one matters — just record it. | I12: PRD v1.5, section 4 | J12: Displayed: WO number + customer name (primary), status badge, **unit number + year/make/model**. When the asset has no unit number, the year/make/model stands alone.
A13: SRI-WO-I1 | B13: C146208 | C13: A corrected typo says that it corrected something | D13: If the system quietly fixes my typo without saying so, I will think I found an exact match and act on the wrong record. | E13: A work order whose name or description can be found by spelling it slightly wrong (one or two letters out). Do NOT use a number or a code — those are excluded on purpose. NOTE: checked on this environment: typing this brings back 'S10740-17625', whose name is a near-miss of what you typed, and it should be drawn as a SOFT match. That soft row is the one this test is about — not the exact matches above it. | F13: ZZSOFTHIT | G13: 1. Open search and type the near-miss spelling. 2. Open the Work Orders tab. 3. Look closely at the matched word. | H13: The matched word is highlighted AND carries the "≈" mark or italics that says it is a close match. A corrected typo that looks exactly like an exact match is a FAIL. | I13: PRD v1.5, section 7 | J13: When a match is fuzzy rather than exact, the matched token in the row is still highlighted, and a subtle `≈` or italicized treatment indicates the soft match.

Sheet Customers
A1: ID | B1: TestRail | C1: What you are checking | D1: Why it matters to a real user | E1: Before you start | F1: TYPE THIS | G1: What to do | H1: What you should see | I1: Where that comes from | J1: The exact wording of the requirement | K1: Result | L1: What you actually saw | M1: Ticket
A2: SRI-CUST-A1 | B2: C146209 | C2: The whole matched value is shown, not just what you typed | D2: If the row shows only the characters I typed, I am reading my own query back. It tells me nothing about which record this is. | E2: A customer exists whose telephone contains this fragment somewhere other than the very start. NOTE: 3 rows come back sharing this fragment — perfect for this test | F2: ZZLONGROW | G2: 1. Open search and type the term in the green cell. 2. Open the Customers tab. 3. Look at each row WITHOUT opening it. 4. Write down the telephone exactly as the row shows it. | H2: Each row shows the COMPLETE telephone, with the bit you typed highlighted inside it. Seeing only what you typed, or a value cut short with "...", is a FAIL — that is SV-10619 and SV-10551. | I2: PRD v1.5, section 5.3 | J2: Every row has a left-side entity icon, a primary line (bold), a secondary line (subdued), and an optional right-side cluster (status badges, counts, and quick-action buttons on hover). The matched substring of the query is highlighted in the primary and secondary text — searching `Fib` highlights "Fib" in "S1-644 Fibridge Commercial".
A3: SRI-CUST-A2 | B3: C146210 | C3: A long value is not cut off through the part that matched | D3: A row that cuts off at "9..." has hidden the one thing I was looking for. | E3: A customer whose text is long enough to overflow the search box (the box is a fixed width), with the matched characters near the END of the value. | F3: ZZLONGROW | G3: 1. Open search and type the term. 2. Open the Customers tab. 3. Look for any text ending in "...". 4. If you see one, write down what is hidden and what you typed. | H3: You can still identify the record. If the "..." has eaten the characters you typed, or eaten the part that tells this record from its neighbours, that is a FAIL. | I3: Story SV-9170 | J3: Each result row carries enough context to pick the right record without opening it — its identifier, who it belongs to, its status, and for work orders the unit number and vehicle, which is what tells two of the same customer's work orders apart.
A4: SRI-CUST-A3 | B4: C146211 | C4: The highlight marks the match inside the text, not instead of it | D4: A highlight is meant to point at something. If it replaces the text, it points at nothing. | E4: Any customer you can find by typing part of what the row displays. | F4: ZZLONGROW | G4: 1. Open search and type the term. 2. Open the Customers tab. 3. Look at how the match is drawn on the row. | H4: The full text is on the row and the matched part is highlighted within it — exactly like the example in the requirement, where typing "Fib" shows the whole of "S1-644 Fibridge Commercial" with "Fib" marked. | I4: PRD v1.5, section 5.3 | J4: Every row has a left-side entity icon, a primary line (bold), a secondary line (subdued), and an optional right-side cluster (status badges, counts, and quick-action buttons on hover). The matched substring of the query is highlighted in the primary and secondary text — searching `Fib` highlights "Fib" in "S1-644 Fibridge Commercial".
A5: SRI-CUST-B1 | B5: C146212 | C5: Two records sharing what you typed can be told apart | D5: This is the whole point. Type 123786 and if two rows both draw as "786", you cannot tell 123786 from 185786 without opening both. | E5: Two customers exist whose telephone are DIFFERENT but share a run of characters. NOTE: 3 rows come back sharing this fragment — perfect for this test | F5: ZZLONGROW | G5: 1. Open search and type the term. 2. Open the Customers tab. 3. WITHOUT opening anything, write down which row is which. 4. If you cannot tell them apart, that is the failure — say so. | H5: You can say which row is which from the rows alone. Two rows that read the same is a FAIL — and note that the right number of rows does not rescue it. | I5: Story SV-9170 | J5: Each result row carries enough context to pick the right record without opening it — its identifier, who it belongs to, its status, and for work orders the unit number and vehicle, which is what tells two of the same customer's work orders apart.
A6: SRI-CUST-B2 | B6: C146213 | C6: Two records with the same bold line differ somewhere you can see | D6: Real shops have two trucks of the same year/make/model and two vendors with the same name. If the rows are identical the list is useless. | E6: Two DIFFERENT customers, each holding a contact with the SAME name. Searching that name returns both customer rows, and both carry the identical line "Contact match: ZZSAMEREP". The product will not allow two customers with the same name, so this is the real shape of the risk on this tab. NOTE: 2 rows come back; at least two carry the same bold line | F6: ZZSAMEREP | G6: 1. Open search and type the term. 2. Open the Customers tab. 3. Compare the two rows line by line. 4. Write down what, if anything, separates them. | H6: Something visible differs — the second line, a badge, a number. Two identical rows is a FAIL; write down both records and what actually differs between them in the data. | I6: Story SV-9170 | J6: Each result row carries enough context to pick the right record without opening it — its identifier, who it belongs to, its status, and for work orders the unit number and vehicle, which is what tells two of the same customer's work orders apart.
A7: SRI-CUST-C1 | B7: C146214 | C7: A match on the customer's own telephone shows the FULL value on the row | D7: the single most common way a service advisor finds a caller — and the PRD asks for it on hover, which the build does not do at all | E7: A customer carrying a distinctive value in the customer's own telephone — a value that appears in NO other field of that record. NOTE: proven to match on phone (exact) | F7: 730-246-8895 | G7: 1. Open search and type the term. 2. Open the Customers tab. 3. Find the record. Without opening it, read the SECOND line of the row. 4. It should carry a labelled note naming the field that matched. 5. Now check the value in that note against the record itself. | H7: The second line carries a labelled note — such as "Contact match: ...", "Matched: ...", "Unit: ...", "VIN: ..." — naming what matched, with the part you typed highlighted inside it. THE THING TO CHECK IS WHETHER THE VALUE IS COMPLETE. The note must show the WHOLE the customer's own telephone value, not just the characters you typed. Open the record and compare. If you typed part of a longer value and the note shows only that part, this is a FAIL — it is SV-10619 and SV-10551, and it means two different records can draw identically. | I7: PRD v1.5, section 5.3 | J7: Every row has a left-side entity icon, a primary line (bold), a secondary line (subdued), and an optional right-side cluster (status badges, counts, and quick-action buttons on hover). The matched substring of the query is highlighted in the primary and secondary text — searching `Fib` highlights "Fib" in "S1-644 Fibridge Commercial".
A8: SRI-CUST-C2 | B8: C146215 | C8: A match on a contact's telephone shows the FULL value on the row | D8: the person calling is an employee of the company, not the company | E8: A customer carrying a distinctive value in a contact's telephone — a value that appears in NO other field of that record. NOTE: proven to match on contact_phones (exact) | F8: 898-021-4480 | G8: 1. Open search and type the term. 2. Open the Customers tab. 3. Find the record. Without opening it, read the SECOND line of the row. 4. It should carry a labelled note naming the field that matched. 5. Now check the value in that note against the record itself. | H8: The second line carries a labelled note — such as "Contact match: ...", "Matched: ...", "Unit: ...", "VIN: ..." — naming what matched, with the part you typed highlighted inside it. THE THING TO CHECK IS WHETHER THE VALUE IS COMPLETE. The note must show the WHOLE a contact's telephone value, not just the characters you typed. Open the record and compare. If you typed part of a longer value and the note shows only that part, this is a FAIL — it is SV-10619 and SV-10551, and it means two different records can draw identically. | I8: PRD v1.5, section 5.3 | J8: Every row has a left-side entity icon, a primary line (bold), a secondary line (subdued), and an optional right-side cluster (status badges, counts, and quick-action buttons on hover). The matched substring of the query is highlighted in the primary and secondary text — searching `Fib` highlights "Fib" in "S1-644 Fibridge Commercial".
A9: SRI-CUST-C3 | B9: C146216 | C9: A match on a contact's email address shows the FULL value on the row | D9: the enquiry arrived by email | E9: A customer carrying a distinctive value in a contact's email address — a value that appears in NO other field of that record. NOTE: proven to match on contact_emails (exact) | F9: savannah.tran@staging.shopview.local | G9: 1. Open search and type the term. 2. Open the Customers tab. 3. Find the record. Without opening it, read the SECOND line of the row. 4. It should carry a labelled note naming the field that matched. 5. Now check the value in that note against the record itself. | H9: The second line carries a labelled note — such as "Contact match: ...", "Matched: ...", "Unit: ...", "VIN: ..." — naming what matched, with the part you typed highlighted inside it. THE THING TO CHECK IS WHETHER THE VALUE IS COMPLETE. The note must show the WHOLE a contact's email address value, not just the characters you typed. Open the record and compare. If you typed part of a longer value and the note shows only that part, this is a FAIL — it is SV-10619 and SV-10551, and it means two different records can draw identically. | I9: PRD v1.5, section 5.3 | J9: Every row has a left-side entity icon, a primary line (bold), a secondary line (subdued), and an optional right-side cluster (status badges, counts, and quick-action buttons on hover). The matched substring of the query is highlighted in the primary and secondary text — searching `Fib` highlights "Fib" in "S1-644 Fibridge Commercial".
A10: SRI-CUST-C4 | B10: C146217 | C10: A match on a contact's name shows the FULL value on the row | D10: the caller gives their own name, not the company name | E10: A customer carrying a distinctive value in a contact's name — a value that appears in NO other field of that record. NOTE: proven to match on contact_names (word) | F10: Savannah | G10: 1. Open search and type the term. 2. Open the Customers tab. 3. Find the record. Without opening it, read the SECOND line of the row. 4. It should carry a labelled note naming the field that matched. 5. Now check the value in that note against the record itself. | H10: The second line carries a labelled note — such as "Contact match: ...", "Matched: ...", "Unit: ...", "VIN: ..." — naming what matched, with the part you typed highlighted inside it. THE THING TO CHECK IS WHETHER THE VALUE IS COMPLETE. The note must show the WHOLE a contact's name value, not just the characters you typed. Open the record and compare. If you typed part of a longer value and the note shows only that part, this is a FAIL — it is SV-10619 and SV-10551, and it means two different records can draw identically. | I10: PRD v1.5, section 5.3 | J10: Every row has a left-side entity icon, a primary line (bold), a secondary line (subdued), and an optional right-side cluster (status badges, counts, and quick-action buttons on hover). The matched substring of the query is highlighted in the primary and secondary text — searching `Fib` highlights "Fib" in "S1-644 Fibridge Commercial".
A11: SRI-CUST-C5 | B11: C146218 | C11: A match on address line 2 shows the FULL value on the row | D11: a suite or unit number distinguishes two customers at one street address | E11: A customer carrying a distinctive value in address line 2 — a value that appears in NO other field of that record. NOTE: proven to match on address_line_2 (word) | F11: Apt. 199 | G11: 1. Open search and type the term. 2. Open the Customers tab. 3. Find the record. Without opening it, read the SECOND line of the row. 4. It should carry a labelled note naming the field that matched. 5. Now check the value in that note against the record itself. | H11: The second line carries a labelled note — such as "Contact match: ...", "Matched: ...", "Unit: ...", "VIN: ..." — naming what matched, with the part you typed highlighted inside it. THE THING TO CHECK IS WHETHER THE VALUE IS COMPLETE. The note must show the WHOLE address line 2 value, not just the characters you typed. Open the record and compare. If you typed part of a longer value and the note shows only that part, this is a FAIL — it is SV-10619 and SV-10551, and it means two different records can draw identically. | I11: PRD v1.5, section 5.3 | J11: Every row has a left-side entity icon, a primary line (bold), a secondary line (subdued), and an optional right-side cluster (status badges, counts, and quick-action buttons on hover). The matched substring of the query is highlighted in the primary and secondary text — searching `Fib` highlights "Fib" in "S1-644 Fibridge Commercial".
A12: SRI-CUST-C6 | B12: C195899 | C12: A match on city shows the FULL value on the row | D12: two customers share a name and differ only by town | E12: A customer carrying a distinctive value in city — a value that appears in NO other field of that record. NOTE: proven to match on city (fuzzy) | F12: Raystad | G12: 1. Open search and type the term. 2. Open the Customers tab. 3. Find the record. Without opening it, read the SECOND line of the row. 4. It should carry a labelled note naming the field that matched. 5. Now check the value in that note against the record itself. | H12: The second line carries a labelled note — such as "Contact match: ...", "Matched: ...", "Unit: ...", "VIN: ..." — naming what matched, with the part you typed highlighted inside it. THE THING TO CHECK IS WHETHER THE VALUE IS COMPLETE. The note must show the WHOLE city value, not just the characters you typed. Open the record and compare. If you typed part of a longer value and the note shows only that part, this is a FAIL — it is SV-10619 and SV-10551, and it means two different records can draw identically. | I12: PRD v1.5, section 5.3 | J12: Every row has a left-side entity icon, a primary line (bold), a secondary line (subdued), and an optional right-side cluster (status badges, counts, and quick-action buttons on hover). The matched substring of the query is highlighted in the primary and secondary text — searching `Fib` highlights "Fib" in "S1-644 Fibridge Commercial".
A13: SRI-CUST-C7 | B13: C146220 | C13: A match on state / province shows the FULL value on the row | D13: the same, one level up | E13: A customer carrying a distinctive value in state / province — a value that appears in NO other field of that record. NOTE: proven to match on state (word) | F13: ZZQUEBEXA | G13: 1. Open search and type the term. 2. Open the Customers tab. 3. Find the record. Without opening it, read the SECOND line of the row. 4. It should carry a labelled note naming the field that matched. 5. Now check the value in that note against the record itself. | H13: The second line carries a labelled note — such as "Contact match: ...", "Matched: ...", "Unit: ...", "VIN: ..." — naming what matched, with the part you typed highlighted inside it. THE THING TO CHECK IS WHETHER THE VALUE IS COMPLETE. The note must show the WHOLE state / province value, not just the characters you typed. Open the record and compare. If you typed part of a longer value and the note shows only that part, this is a FAIL — it is SV-10619 and SV-10551, and it means two different records can draw identically. | I13: PRD v1.5, section 5.3 | J13: Every row has a left-side entity icon, a primary line (bold), a secondary line (subdued), and an optional right-side cluster (status badges, counts, and quick-action buttons on hover). The matched substring of the query is highlighted in the primary and secondary text — searching `Fib` highlights "Fib" in "S1-644 Fibridge Commercial".
... A17: SRI-CUST-I1 | B17: C146223 | C17: A corrected typo says that it corrected something | D17: If the system quietly fixes my typo without saying so, I will think I found an exact match and act on the wrong record. | E17: A customer whose name or description can be found by spelling it slightly wrong (one or two letters out). Do NOT use a number or a code — those are excluded on purpose. NOTE: checked on this environment: typing this brings back 'ZZPREFIX Freight Ltd', whose name is a near-miss of what you typed, and it should be drawn as a SOFT match. That soft row is the one this test is about — not the exact matches above it. | F17: ZZPREFIY | G17: 1. Open search and type the near-miss spelling. 2. Open the Customers tab. 3. Look closely at the matched word. | H17: The matched word is highlighted AND carries the "≈" mark or italics that says it is a close match. A corrected typo that looks exactly like an exact match is a FAIL. | I17: PRD v1.5, section 7 | J17: When a match is fuzzy rather than exact, the matched token in the row is still highlighted, and a subtle `≈` or italicized treatment indicates the soft match.

Sheet Assets
A1: ID | B1: TestRail | C1: What you are checking | D1: Why it matters to a real user | E1: Before you start | F1: TYPE THIS | G1: What to do | H1: What you should see | I1: Where that comes from | J1: The exact wording of the requirement | K1: Result | L1: What you actually saw | M1: Ticket
A2: SRI-ASSET-A1 | B2: C146224 | C2: The whole matched value is shown, not just what you typed | D2: If the row shows only the characters I typed, I am reading my own query back. It tells me nothing about which record this is. | E2: A asset exists whose unit number contains this fragment somewhere other than the very start. NOTE: 2 rows come back sharing this fragment — perfect for this test | F2: ZZLONGROW | G2: 1. Open search and type the term in the green cell. 2. Open the Assets tab. 3. Look at each row WITHOUT opening it. 4. Write down the unit number exactly as the row shows it. | H2: Each row shows the COMPLETE unit number, with the bit you typed highlighted inside it. Seeing only what you typed, or a value cut short with "...", is a FAIL — that is SV-10619 and SV-10551. | I2: PRD v1.5, section 5.3 | J2: Every row has a left-side entity icon, a primary line (bold), a secondary line (subdued), and an optional right-side cluster (status badges, counts, and quick-action buttons on hover). The matched substring of the query is highlighted in the primary and secondary text — searching `Fib` highlights "Fib" in "S1-644 Fibridge Commercial".
A3: SRI-ASSET-A2 | B3: C146225 | C3: A long value is not cut off through the part that matched | D3: A row that cuts off at "9..." has hidden the one thing I was looking for. | E3: A asset whose text is long enough to overflow the search box (the box is a fixed width), with the matched characters near the END of the value. | F3: ZZLONGROW | G3: 1. Open search and type the term. 2. Open the Assets tab. 3. Look for any text ending in "...". 4. If you see one, write down what is hidden and what you typed. | H3: You can still identify the record. If the "..." has eaten the characters you typed, or eaten the part that tells this record from its neighbours, that is a FAIL. | I3: Story SV-9170 | J3: Each result row carries enough context to pick the right record without opening it — its identifier, who it belongs to, its status, and for work orders the unit number and vehicle, which is what tells two of the same customer's work orders apart.
A4: SRI-ASSET-A3 | B4: C146226 | C4: The highlight marks the match inside the text, not instead of it | D4: A highlight is meant to point at something. If it replaces the text, it points at nothing. | E4: Any asset you can find by typing part of what the row displays. | F4: ZZLONGROW | G4: 1. Open search and type the term. 2. Open the Assets tab. 3. Look at how the match is drawn on the row. | H4: The full text is on the row and the matched part is highlighted within it — exactly like the example in the requirement, where typing "Fib" shows the whole of "S1-644 Fibridge Commercial" with "Fib" marked. | I4: PRD v1.5, section 5.3 | J4: Every row has a left-side entity icon, a primary line (bold), a secondary line (subdued), and an optional right-side cluster (status badges, counts, and quick-action buttons on hover). The matched substring of the query is highlighted in the primary and secondary text — searching `Fib` highlights "Fib" in "S1-644 Fibridge Commercial".
A5: SRI-ASSET-B1 | B5: C146227 | C5: Two records sharing what you typed can be told apart | D5: This is the whole point. Type 123786 and if two rows both draw as "786", you cannot tell 123786 from 185786 without opening both. | E5: Two assets exist whose unit number are DIFFERENT but share a run of characters. NOTE: 2 rows come back sharing this fragment — perfect for this test | F5: ZZLONGROW | G5: 1. Open search and type the term. 2. Open the Assets tab. 3. WITHOUT opening anything, write down which row is which. 4. If you cannot tell them apart, that is the failure — say so. | H5: You can say which row is which from the rows alone. Two rows that read the same is a FAIL — and note that the right number of rows does not rescue it. | I5: Story SV-9170 | J5: Each result row carries enough context to pick the right record without opening it — its identifier, who it belongs to, its status, and for work orders the unit number and vehicle, which is what tells two of the same customer's work orders apart.
A6: SRI-ASSET-B2 | B6: C146228 | C6: Two records with the same bold line differ somewhere you can see | D6: Real shops have two trucks of the same year/make/model and two vendors with the same name. If the rows are identical the list is useless. | E6: Two assets whose bold first line is identical but which are different records. These were seeded for this suite. NOTE: 2 rows come back; at least two carry the same bold line | F6: ZZLONGROW | G6: 1. Open search and type the term. 2. Open the Assets tab. 3. Compare the two rows line by line. 4. Write down what, if anything, separates them. | H6: Something visible differs — the second line, a badge, a number. Two identical rows is a FAIL; write down both records and what actually differs between them in the data. | I6: Story SV-9170 | J6: Each result row carries enough context to pick the right record without opening it — its identifier, who it belongs to, its status, and for work orders the unit number and vehicle, which is what tells two of the same customer's work orders apart.
A7: SRI-ASSET-C1 | B7: C146229 | C7: A match on VIN / serial number shows the FULL value on the row | D7: the VIN is how a vehicle is identified on every legal document the shop touches, and it is indexed but never shown | E7: A asset carrying a distinctive value in VIN / serial number — a value that appears in NO other field of that record. NOTE: proven to match on vin (exact) | F7: SVEWU82M5ETEJFWFA | G7: 1. Open search and type the term. 2. Open the Assets tab. 3. Find the record. Without opening it, read the SECOND line of the row. 4. It should carry a labelled note naming the field that matched. 5. Now check the value in that note against the record itself. | H7: The second line carries a labelled note — such as "Contact match: ...", "Matched: ...", "Unit: ...", "VIN: ..." — naming what matched, with the part you typed highlighted inside it. THE THING TO CHECK IS WHETHER THE VALUE IS COMPLETE. The note must show the WHOLE VIN / serial number value, not just the characters you typed. Open the record and compare. If you typed part of a longer value and the note shows only that part, this is a FAIL — it is SV-10619 and SV-10551, and it means two different records can draw identically. | I7: PRD v1.5, section 5.3 | J7: Every row has a left-side entity icon, a primary line (bold), a secondary line (subdued), and an optional right-side cluster (status badges, counts, and quick-action buttons on hover). The matched substring of the query is highlighted in the primary and secondary text — searching `Fib` highlights "Fib" in "S1-644 Fibridge Commercial".
A8: SRI-ASSET-C2 | B8: C146230 | C8: A match on licence plate shows the FULL value on the row | D8: measured on the build and NOT listed in PRD §4 — see PO-QUESTIONS Q5 | E8: A asset carrying a distinctive value in licence plate — a value that appears in NO other field of that record. NOTE: proven to match on licence_plate (exact) | F8: KVQ-2870 | G8: 1. Open search and type the term. 2. Open the Assets tab. 3. Find the record. Without opening it, read the SECOND line of the row. 4. It should carry a labelled note naming the field that matched. 5. Now check the value in that note against the record itself. | H8: The second line carries a labelled note — such as "Contact match: ...", "Matched: ...", "Unit: ...", "VIN: ..." — naming what matched, with the part you typed highlighted inside it. THE THING TO CHECK IS WHETHER THE VALUE IS COMPLETE. The note must show the WHOLE licence plate value, not just the characters you typed. Open the record and compare. If you typed part of a longer value and the note shows only that part, this is a FAIL — it is SV-10619 and SV-10551, and it means two different records can draw identically. | I8: PRD v1.5, section 5.3 | J8: Every row has a left-side entity icon, a primary line (bold), a secondary line (subdued), and an optional right-side cluster (status badges, counts, and quick-action buttons on hover). The matched substring of the query is highlighted in the primary and secondary text — searching `Fib` highlights "Fib" in "S1-644 Fibridge Commercial".
A9: SRI-ASSET-D1 | B9: C146231 | C9: The Assets row shows everything the specification promised | D9: Each field is there because somebody decided you need it to choose. A missing one is a choice you now have to make by opening records. | E9: Any asset that search returns, which has a value in each field named in the requirement column. | F9: ZZLONGROW | G9: 1. Open search and type something that returns the record. 2. Open the Assets tab. 3. Check the row against the requirement column, field by field. 4. Tick off each one. Write down any that is missing. | H9: Every field named in the requirement is on the row. Do not judge whether a missing one matters — just record it. | I9: PRD v1.5, section 4 | J9: Displayed: year + make + model (primary), customer name (secondary, smaller).
A10: SRI-ASSET-I1 | B10: C146232 | C10: A corrected typo says that it corrected something | D10: If the system quietly fixes my typo without saying so, I will think I found an exact match and act on the wrong record. | E10: A asset whose name or description can be found by spelling it slightly wrong (one or two letters out). Do NOT use a number or a code — those are excluded on purpose. NOTE: checked on this environment: typing this brings back '2019 ZZOBSIDIAM Trucks Hauler', whose name is a near-miss of what you typed, and it should be drawn as a SOFT match. That soft row is the one this test is about — not the exact matches above it. | F10: ZZOBSIDIAN | G10: 1. Open search and type the near-miss spelling. 2. Open the Assets tab. 3. Look closely at the matched word. | H10: The matched word is highlighted AND carries the "≈" mark or italics that says it is a close match. A corrected typo that looks exactly like an exact match is a FAIL. | I10: PRD v1.5, section 7 | J10: When a match is fuzzy rather than exact, the matched token in the row is still highlighted, and a subtle `≈` or italicized treatment indicates the soft match.

Sheet Parts
A1: ID | B1: TestRail | C1: What you are checking | D1: Why it matters to a real user | E1: Before you start | F1: TYPE THIS | G1: What to do | H1: What you should see | I1: Where that comes from | J1: The exact wording of the requirement | K1: Result | L1: What you actually saw | M1: Ticket
A2: SRI-PART-A1 | B2: C146233 | C2: The whole matched value is shown, not just what you typed | D2: If the row shows only the characters I typed, I am reading my own query back. It tells me nothing about which record this is. | E2: A part exists whose part number contains this fragment somewhere other than the very start. NOTE: 2 rows come back sharing this fragment — perfect for this test | F2: ZZLONGROW | G2: 1. Open search and type the term in the green cell. 2. Open the Parts tab. 3. Look at each row WITHOUT opening it. 4. Write down the part number exactly as the row shows it. | H2: Each row shows the COMPLETE part number, with the bit you typed highlighted inside it. Seeing only what you typed, or a value cut short with "...", is a FAIL — that is SV-10619 and SV-10551. | I2: PRD v1.5, section 5.3 | J2: Every row has a left-side entity icon, a primary line (bold), a secondary line (subdued), and an optional right-side cluster (status badges, counts, and quick-action buttons on hover). The matched substring of the query is highlighted in the primary and secondary text — searching `Fib` highlights "Fib" in "S1-644 Fibridge Commercial".
A3: SRI-PART-A2 | B3: C146234 | C3: A long value is not cut off through the part that matched | D3: A row that cuts off at "9..." has hidden the one thing I was looking for. | E3: A part whose text is long enough to overflow the search box (the box is a fixed width), with the matched characters near the END of the value. | F3: ZZLONGROW | G3: 1. Open search and type the term. 2. Open the Parts tab. 3. Look for any text ending in "...". 4. If you see one, write down what is hidden and what you typed. | H3: You can still identify the record. If the "..." has eaten the characters you typed, or eaten the part that tells this record from its neighbours, that is a FAIL. | I3: Story SV-9170 | J3: Each result row carries enough context to pick the right record without opening it — its identifier, who it belongs to, its status, and for work orders the unit number and vehicle, which is what tells two of the same customer's work orders apart.
A4: SRI-PART-A3 | B4: C146235 | C4: The highlight marks the match inside the text, not instead of it | D4: A highlight is meant to point at something. If it replaces the text, it points at nothing. | E4: Any part you can find by typing part of what the row displays. | F4: ZZLONGROW | G4: 1. Open search and type the term. 2. Open the Parts tab. 3. Look at how the match is drawn on the row. | H4: The full text is on the row and the matched part is highlighted within it — exactly like the example in the requirement, where typing "Fib" shows the whole of "S1-644 Fibridge Commercial" with "Fib" marked. | I4: PRD v1.5, section 5.3 | J4: Every row has a left-side entity icon, a primary line (bold), a secondary line (subdued), and an optional right-side cluster (status badges, counts, and quick-action buttons on hover). The matched substring of the query is highlighted in the primary and secondary text — searching `Fib` highlights "Fib" in "S1-644 Fibridge Commercial".
A5: SRI-PART-B1 | B5: C146236 | C5: Two records sharing what you typed can be told apart | D5: This is the whole point. Type 123786 and if two rows both draw as "786", you cannot tell 123786 from 185786 without opening both. | E5: Two parts exist whose part number are DIFFERENT but share a run of characters. NOTE: 2 rows come back sharing this fragment — perfect for this test | F5: ZZLONGROW | G5: 1. Open search and type the term. 2. Open the Parts tab. 3. WITHOUT opening anything, write down which row is which. 4. If you cannot tell them apart, that is the failure — say so. | H5: You can say which row is which from the rows alone. Two rows that read the same is a FAIL — and note that the right number of rows does not rescue it. | I5: Story SV-9170 | J5: Each result row carries enough context to pick the right record without opening it — its identifier, who it belongs to, its status, and for work orders the unit number and vehicle, which is what tells two of the same customer's work orders apart.
A6: SRI-PART-B2 | B6: C146237 | C6: Two records with the same bold line differ somewhere you can see | D6: Real shops have two trucks of the same year/make/model and two vendors with the same name. If the rows are identical the list is useless. | E6: Two parts whose bold first line is identical but which are different records. These were seeded for this suite. NOTE: 2 rows come back; at least two carry the same bold line | F6: ZZLONGROW Heavy Duty Air Brake | G6: 1. Open search and type the term. 2. Open the Parts tab. 3. Compare the two rows line by line. 4. Write down what, if anything, separates them. | H6: Something visible differs — the second line, a badge, a number. Two identical rows is a FAIL; write down both records and what actually differs between them in the data. | I6: Story SV-9170 | J6: Each result row carries enough context to pick the right record without opening it — its identifier, who it belongs to, its status, and for work orders the unit number and vehicle, which is what tells two of the same customer's work orders apart.
A7: SRI-PART-C1 | B7: C146238 | C7: A match on bin location shows the FULL value on the row | D7: the whole point of the search is often "where is it?" — the PRD names bin location as indexed and the row never shows it | E7: A part carrying a distinctive value in bin location — a value that appears in NO other field of that record. NOTE: proven to match on bin_location (word) | F7: H3B | G7: 1. Open search and type the term. 2. Open the Parts tab. 3. Find the record. Without opening it, read the SECOND line of the row. 4. It should carry a labelled note naming the field that matched. 5. Now check the value in that note against the record itself. | H7: The second line carries a labelled note — such as "Contact match: ...", "Matched: ...", "Unit: ...", "VIN: ..." — naming what matched, with the part you typed highlighted inside it. THE THING TO CHECK IS WHETHER THE VALUE IS COMPLETE. The note must show the WHOLE bin location value, not just the characters you typed. Open the record and compare. If you typed part of a longer value and the note shows only that part, this is a FAIL — it is SV-10619 and SV-10551, and it means two different records can draw identically. | I7: PRD v1.5, section 5.3 | J7: Every row has a left-side entity icon, a primary line (bold), a secondary line (subdued), and an optional right-side cluster (status badges, counts, and quick-action buttons on hover). The matched substring of the query is highlighted in the primary and secondary text — searching `Fib` highlights "Fib" in "S1-644 Fibridge Commercial".
A8: SRI-PART-C2 | B8: C146239 | C8: A match on manufacturer shows the FULL value on the row | D8: a parts person searches by who makes it | E8: A part carrying a distinctive value in manufacturer — a value that appears in NO other field of that record. NOTE: proven to match on manufacturer (word) | F8: Klondike | G8: 1. Open search and type the term. 2. Open the Parts tab. 3. Find the record. Without opening it, read the SECOND line of the row. 4. It should carry a labelled note naming the field that matched. 5. Now check the value in that note against the record itself. | H8: The second line carries a labelled note — such as "Contact match: ...", "Matched: ...", "Unit: ...", "VIN: ..." — naming what matched, with the part you typed highlighted inside it. THE THING TO CHECK IS WHETHER THE VALUE IS COMPLETE. The note must show the WHOLE manufacturer value, not just the characters you typed. Open the record and compare. If you typed part of a longer value and the note shows only that part, this is a FAIL — it is SV-10619 and SV-10551, and it means two different records can draw identically. | I8: PRD v1.5, section 5.3 | J8: Every row has a left-side entity icon, a primary line (bold), a secondary line (subdued), and an optional right-side cluster (status badges, counts, and quick-action buttons on hover). The matched substring of the query is highlighted in the primary and secondary text — searching `Fib` highlights "Fib" in "S1-644 Fibridge Commercial".
A9: SRI-PART-C3 | B9: C146240 | C9: A match on vendor name shows the FULL value on the row | D9: a parts person searches by who sells it | E9: A part carrying a distinctive value in vendor name — a value that appears in NO other field of that record. NOTE: proven to match on vendor_name (word) | F9: Gibson's Mobile Diesel Repair | G9: 1. Open search and type the term. 2. Open the Parts tab. 3. Find the record. Without opening it, read the SECOND line of the row. 4. It should carry a labelled note naming the field that matched. 5. Now check the value in that note against the record itself. | H9: The second line carries a labelled note — such as "Contact match: ...", "Matched: ...", "Unit: ...", "VIN: ..." — naming what matched, with the part you typed highlighted inside it. THE THING TO CHECK IS WHETHER THE VALUE IS COMPLETE. The note must show the WHOLE vendor name value, not just the characters you typed. Open the record and compare. If you typed part of a longer value and the note shows only that part, this is a FAIL — it is SV-10619 and SV-10551, and it means two different records can draw identically. | I9: PRD v1.5, section 5.3 | J9: Every row has a left-side entity icon, a primary line (bold), a secondary line (subdued), and an optional right-side cluster (status badges, counts, and quick-action buttons on hover). The matched substring of the query is highlighted in the primary and secondary text — searching `Fib` highlights "Fib" in "S1-644 Fibridge Commercial".
A10: SRI-PART-C4 | B10: C146241 | C10: A match on category shows the FULL value on the row | D10: a broad hunt for "brakes" | E10: A part carrying a distinctive value in category — a value that appears in NO other field of that record. NOTE: proven to match on category (word) | F10: HD-Lighting & Electrical | G10: 1. Open search and type the term. 2. Open the Parts tab. 3. Find the record. Without opening it, read the SECOND line of the row. 4. It should carry a labelled note naming the field that matched. 5. Now check the value in that note against the record itself. | H10: The second line carries a labelled note — such as "Contact match: ...", "Matched: ...", "Unit: ...", "VIN: ..." — naming what matched, with the part you typed highlighted inside it. THE THING TO CHECK IS WHETHER THE VALUE IS COMPLETE. The note must show the WHOLE category value, not just the characters you typed. Open the record and compare. If you typed part of a longer value and the note shows only that part, this is a FAIL — it is SV-10619 and SV-10551, and it means two different records can draw identically. | I10: PRD v1.5, section 5.3 | J10: Every row has a left-side entity icon, a primary line (bold), a secondary line (subdued), and an optional right-side cluster (status badges, counts, and quick-action buttons on hover). The matched substring of the query is highlighted in the primary and secondary text — searching `Fib` highlights "Fib" in "S1-644 Fibridge Commercial".
A11: SRI-PART-C5 | B11: C146242 | C11: A match on tags shows the FULL value on the row | D11: shop-specific labelling | E11: A part carrying a distinctive value in tags — a value that appears in NO other field of that record. NOTE: 2 rows come back sharing this | F11: 496 | G11: 1. Open search and type the term. 2. Open the Parts tab. 3. Find the record. Without opening it, read the SECOND line of the row. 4. It should carry a labelled note naming the field that matched. 5. Now check the value in that note against the record itself. | H11: The second line carries a labelled note — such as "Contact match: ...", "Matched: ...", "Unit: ...", "VIN: ..." — naming what matched, with the part you typed highlighted inside it. THE THING TO CHECK IS WHETHER THE VALUE IS COMPLETE. The note must show the WHOLE tags value, not just the characters you typed. Open the record and compare. If you typed part of a longer value and the note shows only that part, this is a FAIL — it is SV-10619 and SV-10551, and it means two different records can draw identically. | I11: PRD v1.5, section 5.3 | J11: Every row has a left-side entity icon, a primary line (bold), a secondary line (subdued), and an optional right-side cluster (status badges, counts, and quick-action buttons on hover). The matched substring of the query is highlighted in the primary and secondary text — searching `Fib` highlights "Fib" in "S1-644 Fibridge Commercial".
A12: SRI-PART-D1 | B12: C146243 | C12: The Parts row shows everything the specification promised | D12: Each field is there because somebody decided you need it to choose. A missing one is a choice you now have to make by opening records. | E12: Any part that search returns, which has a value in each field named in the requirement column. | F12: ZZLONGROW | G12: 1. Open search and type something that returns the record. 2. Open the Parts tab. 3. Check the row against the requirement column, field by field. 4. Tick off each one. Write down any that is missing. | H12: Every field named in the requirement is on the row. Do not judge whether a missing one matters — just record it. | I12: PRD v1.5, section 4 | J12: Displayed: description (primary), part number (secondary), total quantity with a stock-status badge (see §5.3).
A13: SRI-PART-I1 | B13: C146244 | C13: A corrected typo says that it corrected something | D13: If the system quietly fixes my typo without saying so, I will think I found an exact match and act on the wrong record. | E13: A part whose name or description can be found by spelling it slightly wrong (one or two letters out). Do NOT use a number or a code — those are excluded on purpose. NOTE: checked on this environment: typing this brings back 'ZZKRYPTOM Wheel Seal', whose name is a near-miss of what you typed, and it should be drawn as a SOFT match. That soft row is the one this test is about — not the exact matches above it. | F13: ZZKRYPTON | G13: 1. Open search and type the near-miss spelling. 2. Open the Parts tab. 3. Look closely at the matched word. | H13: The matched word is highlighted AND carries the "≈" mark or italics that says it is a close match. A corrected typo that looks exactly like an exact match is a FAIL. | I13: PRD v1.5, section 7 | J13: When a match is fuzzy rather than exact, the matched token in the row is still highlighted, and a subtle `≈` or italicized treatment indicates the soft match.

Sheet Vendors
A1: ID | B1: TestRail | C1: What you are checking | D1: Why it matters to a real user | E1: Before you start | F1: TYPE THIS | G1: What to do | H1: What you should see | I1: Where that comes from | J1: The exact wording of the requirement | K1: Result | L1: What you actually saw | M1: Ticket
A2: SRI-VEND-A1 | B2: C146245 | C2: The whole matched value is shown, not just what you typed | D2: If the row shows only the characters I typed, I am reading my own query back. It tells me nothing about which record this is. | E2: A vendor exists whose telephone contains this fragment somewhere other than the very start. NOTE: 4 rows come back sharing this fragment — perfect for this test | F2: ZZLONGROW | G2: 1. Open search and type the term in the green cell. 2. Open the Vendors tab. 3. Look at each row WITHOUT opening it. 4. Write down the telephone exactly as the row shows it. | H2: Each row shows the COMPLETE telephone, with the bit you typed highlighted inside it. Seeing only what you typed, or a value cut short with "...", is a FAIL — that is SV-10619 and SV-10551. | I2: PRD v1.5, section 5.3 | J2: Every row has a left-side entity icon, a primary line (bold), a secondary line (subdued), and an optional right-side cluster (status badges, counts, and quick-action buttons on hover). The matched substring of the query is highlighted in the primary and secondary text — searching `Fib` highlights "Fib" in "S1-644 Fibridge Commercial".
A3: SRI-VEND-A2 | B3: C146246 | C3: A long value is not cut off through the part that matched | D3: A row that cuts off at "9..." has hidden the one thing I was looking for. | E3: A vendor whose text is long enough to overflow the search box (the box is a fixed width), with the matched characters near the END of the value. | F3: ZZLONGROW | G3: 1. Open search and type the term. 2. Open the Vendors tab. 3. Look for any text ending in "...". 4. If you see one, write down what is hidden and what you typed. | H3: You can still identify the record. If the "..." has eaten the characters you typed, or eaten the part that tells this record from its neighbours, that is a FAIL. | I3: Story SV-9170 | J3: Each result row carries enough context to pick the right record without opening it — its identifier, who it belongs to, its status, and for work orders the unit number and vehicle, which is what tells two of the same customer's work orders apart.
A4: SRI-VEND-A3 | B4: C146247 | C4: The highlight marks the match inside the text, not instead of it | D4: A highlight is meant to point at something. If it replaces the text, it points at nothing. | E4: Any vendor you can find by typing part of what the row displays. | F4: ZZLONGROW | G4: 1. Open search and type the term. 2. Open the Vendors tab. 3. Look at how the match is drawn on the row. | H4: The full text is on the row and the matched part is highlighted within it — exactly like the example in the requirement, where typing "Fib" shows the whole of "S1-644 Fibridge Commercial" with "Fib" marked. | I4: PRD v1.5, section 5.3 | J4: Every row has a left-side entity icon, a primary line (bold), a secondary line (subdued), and an optional right-side cluster (status badges, counts, and quick-action buttons on hover). The matched substring of the query is highlighted in the primary and secondary text — searching `Fib` highlights "Fib" in "S1-644 Fibridge Commercial".
A5: SRI-VEND-B1 | B5: C146248 | C5: Two records sharing what you typed can be told apart | D5: This is the whole point. Type 123786 and if two rows both draw as "786", you cannot tell 123786 from 185786 without opening both. | E5: Two vendors exist whose telephone are DIFFERENT but share a run of characters. NOTE: 4 rows come back sharing this fragment — perfect for this test | F5: ZZLONGROW | G5: 1. Open search and type the term. 2. Open the Vendors tab. 3. WITHOUT opening anything, write down which row is which. 4. If you cannot tell them apart, that is the failure — say so. | H5: You can say which row is which from the rows alone. Two rows that read the same is a FAIL — and note that the right number of rows does not rescue it. | I5: Story SV-9170 | J5: Each result row carries enough context to pick the right record without opening it — its identifier, who it belongs to, its status, and for work orders the unit number and vehicle, which is what tells two of the same customer's work orders apart.
A6: SRI-VEND-B2 | B6: C146249 | C6: Two records with the same bold line differ somewhere you can see | D6: Real shops have two trucks of the same year/make/model and two vendors with the same name. If the rows are identical the list is useless. | E6: Two vendors whose bold first line is identical but which are different records. These were seeded for this suite. NOTE: 2 rows come back; at least two carry the same bold line | F6: ZZLONGROW Identical Name Supply | G6: 1. Open search and type the term. 2. Open the Vendors tab. 3. Compare the two rows line by line. 4. Write down what, if anything, separates them. | H6: Something visible differs — the second line, a badge, a number. Two identical rows is a FAIL; write down both records and what actually differs between them in the data. | I6: Story SV-9170 | J6: Each result row carries enough context to pick the right record without opening it — its identifier, who it belongs to, its status, and for work orders the unit number and vehicle, which is what tells two of the same customer's work orders apart.
A7: SRI-VEND-C1 | B7: C146250 | C7: A match on email address shows the FULL value on the row | D7: the vendor contact arrived by email | E7: A vendor carrying a distinctive value in email address — a value that appears in NO other field of that record. NOTE: proven to match on email (exact) | F7: zzhidden.vendor@staging.shopview.local | G7: 1. Open search and type the term. 2. Open the Vendors tab. 3. Find the record. Without opening it, read the SECOND line of the row. 4. It should carry a labelled note naming the field that matched. 5. Now check the value in that note against the record itself. | H7: The second line carries a labelled note — such as "Contact match: ...", "Matched: ...", "Unit: ...", "VIN: ..." — naming what matched, with the part you typed highlighted inside it. THE THING TO CHECK IS WHETHER THE VALUE IS COMPLETE. The note must show the WHOLE email address value, not just the characters you typed. Open the record and compare. If you typed part of a longer value and the note shows only that part, this is a FAIL — it is SV-10619 and SV-10551, and it means two different records can draw identically. | I7: PRD v1.5, section 5.3 | J7: Every row has a left-side entity icon, a primary line (bold), a secondary line (subdued), and an optional right-side cluster (status badges, counts, and quick-action buttons on hover). The matched substring of the query is highlighted in the primary and secondary text — searching `Fib` highlights "Fib" in "S1-644 Fibridge Commercial".
A8: SRI-VEND-C2 | B8: C146251 | C8: A match on address line 2 shows the FULL value on the row | D8: measured on the build; two vendors at one street address differ only here | E8: A vendor carrying a distinctive value in address line 2 — a value that appears in NO other field of that record. NOTE: proven to match on address_line_2 (word) | F8: ZZHIDDENSUITE | G8: 1. Open search and type the term. 2. Open the Vendors tab. 3. Find the record. Without opening it, read the SECOND line of the row. 4. It should carry a labelled note naming the field that matched. 5. Now check the value in that note against the record itself. | H8: The second line carries a labelled note — such as "Contact match: ...", "Matched: ...", "Unit: ...", "VIN: ..." — naming what matched, with the part you typed highlighted inside it. THE THING TO CHECK IS WHETHER THE VALUE IS COMPLETE. The note must show the WHOLE address line 2 value, not just the characters you typed. Open the record and compare. If you typed part of a longer value and the note shows only that part, this is a FAIL — it is SV-10619 and SV-10551, and it means two different records can draw identically. | I8: PRD v1.5, section 5.3 | J8: Every row has a left-side entity icon, a primary line (bold), a secondary line (subdued), and an optional right-side cluster (status badges, counts, and quick-action buttons on hover). The matched substring of the query is highlighted in the primary and secondary text — searching `Fib` highlights "Fib" in "S1-644 Fibridge Commercial".
A9: SRI-VEND-C3 | B9: C146252 | C9: A match on a contact's telephone shows the FULL value on the row | D9: the person to call is a named rep, not the switchboard | E9: A vendor carrying a distinctive value in a contact's telephone — a value that appears in NO other field of that record. NOTE: 7 rows come back sharing this | F9: 965 | G9: 1. Open search and type the term. 2. Open the Vendors tab. 3. Find the record. Without opening it, read the SECOND line of the row. 4. It should carry a labelled note naming the field that matched. 5. Now check the value in that note against the record itself. | H9: The second line carries a labelled note — such as "Contact match: ...", "Matched: ...", "Unit: ...", "VIN: ..." — naming what matched, with the part you typed highlighted inside it. THE THING TO CHECK IS WHETHER THE VALUE IS COMPLETE. The note must show the WHOLE a contact's telephone value, not just the characters you typed. Open the record and compare. If you typed part of a longer value and the note shows only that part, this is a FAIL — it is SV-10619 and SV-10551, and it means two different records can draw identically. | I9: PRD v1.5, section 5.3 | J9: Every row has a left-side entity icon, a primary line (bold), a secondary line (subdued), and an optional right-side cluster (status badges, counts, and quick-action buttons on hover). The matched substring of the query is highlighted in the primary and secondary text — searching `Fib` highlights "Fib" in "S1-644 Fibridge Commercial".
A10: SRI-VEND-C4 | B10: C195900 | C10: A match on a contact's name shows the FULL value on the row | D10: the rep gives their own name | E10: A vendor carrying a distinctive value in a contact's name — a value that appears in NO other field of that record. NOTE: proven to match on contact_names (word) | F10: ZZHIDDENCONTACT | G10: 1. Open search and type the term. 2. Open the Vendors tab. 3. Find the record. Without opening it, read the SECOND line of the row. 4. It should carry a labelled note naming the field that matched. 5. Now check the value in that note against the record itself. | H10: The second line carries a labelled note — such as "Contact match: ...", "Matched: ...", "Unit: ...", "VIN: ..." — naming what matched, with the part you typed highlighted inside it. THE THING TO CHECK IS WHETHER THE VALUE IS COMPLETE. The note must show the WHOLE a contact's name value, not just the characters you typed. Open the record and compare. If you typed part of a longer value and the note shows only that part, this is a FAIL — it is SV-10619 and SV-10551, and it means two different records can draw identically. | I10: PRD v1.5, section 5.3 | J10: Every row has a left-side entity icon, a primary line (bold), a secondary line (subdued), and an optional right-side cluster (status badges, counts, and quick-action buttons on hover). The matched substring of the query is highlighted in the primary and secondary text — searching `Fib` highlights "Fib" in "S1-644 Fibridge Commercial".
A11: SRI-VEND-C5 | B11: C195901 | C11: A match on a contact's email address shows the FULL value on the row | D11: the backorder chase is by email | E11: A vendor carrying a distinctive value in a contact's email address — a value that appears in NO other field of that record. NOTE: proven to match on contact_emails (word) | F11: zzhidden.contact@staging.shopview.local | G11: 1. Open search and type the term. 2. Open the Vendors tab. 3. Find the record. Without opening it, read the SECOND line of the row. 4. It should carry a labelled note naming the field that matched. 5. Now check the value in that note against the record itself. | H11: The second line carries a labelled note — such as "Contact match: ...", "Matched: ...", "Unit: ...", "VIN: ..." — naming what matched, with the part you typed highlighted inside it. THE THING TO CHECK IS WHETHER THE VALUE IS COMPLETE. The note must show the WHOLE a contact's email address value, not just the characters you typed. Open the record and compare. If you typed part of a longer value and the note shows only that part, this is a FAIL — it is SV-10619 and SV-10551, and it means two different records can draw identically. | I11: PRD v1.5, section 5.3 | J11: Every row has a left-side entity icon, a primary line (bold), a secondary line (subdued), and an optional right-side cluster (status badges, counts, and quick-action buttons on hover). The matched substring of the query is highlighted in the primary and secondary text — searching `Fib` highlights "Fib" in "S1-644 Fibridge Commercial".
A12: SRI-VEND-D1 | B12: C146255 | C12: The Vendors row shows everything the specification promised | D12: Each field is there because somebody decided you need it to choose. A missing one is a choice you now have to make by opening records. | E12: Any vendor that search returns, which has a value in each field named in the requirement column. | F12: ZZLONGROW | G12: 1. Open search and type something that returns the record. 2. Open the Vendors tab. 3. Check the row against the requirement column, field by field. 4. Tick off each one. Write down any that is missing. | H12: Every field named in the requirement is on the row. Do not judge whether a missing one matters — just record it. | I12: PRD v1.5, section 4 | J12: Displayed: vendor name (primary), telephone + address line (secondary).
A13: SRI-VEND-I1 | B13: C146256 | C13: A corrected typo says that it corrected something | D13: If the system quietly fixes my typo without saying so, I will think I found an exact match and act on the wrong record. | E13: A vendor whose name or description can be found by spelling it slightly wrong (one or two letters out). Do NOT use a number or a code — those are excluded on purpose. NOTE: checked on this environment: typing this brings back 'ZZMAGENTO Traders', whose name is a near-miss of what you typed, and it should be drawn as a SOFT match. That soft row is the one this test is about — not the exact matches above it. | F13: ZZMAGENTA | G13: 1. Open search and type the near-miss spelling. 2. Open the Vendors tab. 3. Look closely at the matched word. | H13: The matched word is highlighted AND carries the "≈" mark or italics that says it is a close match. A corrected typo that looks exactly like an exact match is a FAIL. | I13: PRD v1.5, section 7 | J13: When a match is fuzzy rather than exact, the matched token in the row is still highlighted, and a subtle `≈` or italicized treatment indicates the soft match.

Sheet Part Sales
A1: ID | B1: TestRail | C1: What you are checking | D1: Why it matters to a real user | E1: Before you start | F1: TYPE THIS | G1: What to do | H1: What you should see | I1: Where that comes from | J1: The exact wording of the requirement | K1: Result | L1: What you actually saw | M1: Ticket
A2: SRI-PS-A1 | B2: C146257 | C2: The whole matched value is shown, not just what you typed | D2: If the row shows only the characters I typed, I am reading my own query back. It tells me nothing about which record this is. | E2: A part sale exists whose P-number contains this fragment somewhere other than the very start. NOTE: 2 rows come back sharing this fragment — perfect for this test | F2: ZZLONGROW | G2: 1. Open search and type the term in the green cell. 2. Open the Part Sales tab. 3. Look at each row WITHOUT opening it. 4. Write down the P-number exactly as the row shows it. | H2: Each row shows the COMPLETE P-number, with the bit you typed highlighted inside it. Seeing only what you typed, or a value cut short with "...", is a FAIL — that is SV-10619 and SV-10551. | I2: PRD v1.5, section 5.3 | J2: Every row has a left-side entity icon, a primary line (bold), a secondary line (subdued), and an optional right-side cluster (status badges, counts, and quick-action buttons on hover). The matched substring of the query is highlighted in the primary and secondary text — searching `Fib` highlights "Fib" in "S1-644 Fibridge Commercial".
A3: SRI-PS-A2 | B3: C146258 | C3: A long value is not cut off through the part that matched | D3: A row that cuts off at "9..." has hidden the one thing I was looking for. | E3: A part sale whose text is long enough to overflow the search box (the box is a fixed width), with the matched characters near the END of the value. | F3: ZZLONGROW | G3: 1. Open search and type the term. 2. Open the Part Sales tab. 3. Look for any text ending in "...". 4. If you see one, write down what is hidden and what you typed. | H3: You can still identify the record. If the "..." has eaten the characters you typed, or eaten the part that tells this record from its neighbours, that is a FAIL. | I3: Story SV-9170 | J3: Each result row carries enough context to pick the right record without opening it — its identifier, who it belongs to, its status, and for work orders the unit number and vehicle, which is what tells two of the same customer's work orders apart.
A4: SRI-PS-A3 | B4: C146259 | C4: The highlight marks the match inside the text, not instead of it | D4: A highlight is meant to point at something. If it replaces the text, it points at nothing. | E4: Any part sale you can find by typing part of what the row displays. | F4: ZZLONGROW | G4: 1. Open search and type the term. 2. Open the Part Sales tab. 3. Look at how the match is drawn on the row. | H4: The full text is on the row and the matched part is highlighted within it — exactly like the example in the requirement, where typing "Fib" shows the whole of "S1-644 Fibridge Commercial" with "Fib" marked. | I4: PRD v1.5, section 5.3 | J4: Every row has a left-side entity icon, a primary line (bold), a secondary line (subdued), and an optional right-side cluster (status badges, counts, and quick-action buttons on hover). The matched substring of the query is highlighted in the primary and secondary text — searching `Fib` highlights "Fib" in "S1-644 Fibridge Commercial".
A5: SRI-PS-B1 | B5: C146260 | C5: Two records sharing what you typed can be told apart | D5: This is the whole point. Type 123786 and if two rows both draw as "786", you cannot tell 123786 from 185786 without opening both. | E5: Two part sales exist whose P-number are DIFFERENT but share a run of characters. NOTE: 2 rows come back sharing this fragment — perfect for this test | F5: ZZLONGROW | G5: 1. Open search and type the term. 2. Open the Part Sales tab. 3. WITHOUT opening anything, write down which row is which. 4. If you cannot tell them apart, that is the failure — say so. | H5: You can say which row is which from the rows alone. Two rows that read the same is a FAIL — and note that the right number of rows does not rescue it. | I5: Story SV-9170 | J5: Each result row carries enough context to pick the right record without opening it — its identifier, who it belongs to, its status, and for work orders the unit number and vehicle, which is what tells two of the same customer's work orders apart.
A6: SRI-PS-B2 | B6: C146261 | C6: Two records with the same bold line differ somewhere you can see | D6: Real shops have two trucks of the same year/make/model and two vendors with the same name. If the rows are identical the list is useless. | E6: Two part sales whose bold first line is identical but which are different records. These were seeded for this suite. NOTE: 2 rows come back; at least two carry the same bold line | F6: ZZLONGROW | G6: 1. Open search and type the term. 2. Open the Part Sales tab. 3. Compare the two rows line by line. 4. Write down what, if anything, separates them. | H6: Something visible differs — the second line, a badge, a number. Two identical rows is a FAIL; write down both records and what actually differs between them in the data. | I6: Story SV-9170 | J6: Each result row carries enough context to pick the right record without opening it — its identifier, who it belongs to, its status, and for work orders the unit number and vehicle, which is what tells two of the same customer's work orders apart.
A7: SRI-PS-C1 | B7: C146262 | C7: A match on the asset on the sale shows the FULL value on the row | D7: a counter sale is remembered by the truck it was for | E7: A part sale carrying a distinctive value in the asset on the sale — a value that appears in NO other field of that record. NOTE: proven to match on asset_description (word) | F7: Quietline | G7: 1. Open search and type the term. 2. Open the Part Sales tab. 3. Find the record. Without opening it, read the SECOND line of the row. 4. It should carry a labelled note naming the field that matched. 5. Now check the value in that note against the record itself. | H7: The second line carries a labelled note — such as "Contact match: ...", "Matched: ...", "Unit: ...", "VIN: ..." — naming what matched, with the part you typed highlighted inside it. THE THING TO CHECK IS WHETHER THE VALUE IS COMPLETE. The note must show the WHOLE the asset on the sale value, not just the characters you typed. Open the record and compare. If you typed part of a longer value and the note shows only that part, this is a FAIL — it is SV-10619 and SV-10551, and it means two different records can draw identically. | I7: PRD v1.5, section 5.3 | J7: Every row has a left-side entity icon, a primary line (bold), a secondary line (subdued), and an optional right-side cluster (status badges, counts, and quick-action buttons on hover). The matched substring of the query is highlighted in the primary and secondary text — searching `Fib` highlights "Fib" in "S1-644 Fibridge Commercial".
A8: SRI-PS-C2 | B8: C146263 | C8: A match on VIN / serial number shows the FULL value on the row | D8: the same, by VIN | E8: A part sale carrying a distinctive value in VIN / serial number — a value that appears in NO other field of that record. NOTE: proven to match on vin (exact) | F8: ZZHIDDENVIN0000001 | G8: 1. Open search and type the term. 2. Open the Part Sales tab. 3. Find the record. Without opening it, read the SECOND line of the row. 4. It should carry a labelled note naming the field that matched. 5. Now check the value in that note against the record itself. | H8: The second line carries a labelled note — such as "Contact match: ...", "Matched: ...", "Unit: ...", "VIN: ..." — naming what matched, with the part you typed highlighted inside it. THE THING TO CHECK IS WHETHER THE VALUE IS COMPLETE. The note must show the WHOLE VIN / serial number value, not just the characters you typed. Open the record and compare. If you typed part of a longer value and the note shows only that part, this is a FAIL — it is SV-10619 and SV-10551, and it means two different records can draw identically. | I8: PRD v1.5, section 5.3 | J8: Every row has a left-side entity icon, a primary line (bold), a secondary line (subdued), and an optional right-side cluster (status badges, counts, and quick-action buttons on hover). The matched substring of the query is highlighted in the primary and secondary text — searching `Fib` highlights "Fib" in "S1-644 Fibridge Commercial".
A9: SRI-PS-D1 | B9: C146264 | C9: The Part Sales row shows everything the specification promised | D9: Each field is there because somebody decided you need it to choose. A missing one is a choice you now have to make by opening records. | E9: Any part sale that search returns, which has a value in each field named in the requirement column. | F9: ZZLONGROW | G9: 1. Open search and type something that returns the record. 2. Open the Part Sales tab. 3. Check the row against the requirement column, field by field. 4. Tick off each one. Write down any that is missing. | H9: Every field named in the requirement is on the row. Do not judge whether a missing one matters — just record it. | I9: PRD v1.5, section 4 | J9: Displayed: P-number + customer (primary), status badge, total price + created date.
A10: SRI-PS-I1 | B10: C146265 | C10: A corrected typo says that it corrected something | D10: If the system quietly fixes my typo without saying so, I will think I found an exact match and act on the wrong record. | E10: A part sale whose name or description can be found by spelling it slightly wrong (one or two letters out). Do NOT use a number or a code — those are excluded on purpose. NOTE: checked on this environment: typing this brings back 'P10740-254', whose name is a near-miss of what you typed, and it should be drawn as a SOFT match. That soft row is the one this test is about — not the exact matches above it. | F10: ZZSOFTHIT | G10: 1. Open search and type the near-miss spelling. 2. Open the Part Sales tab. 3. Look closely at the matched word. | H10: The matched word is highlighted AND carries the "≈" mark or italics that says it is a close match. A corrected typo that looks exactly like an exact match is a FAIL. | I10: PRD v1.5, section 7 | J10: When a match is fuzzy rather than exact, the matched token in the row is still highlighted, and a subtle `≈` or italicized treatment indicates the soft match.

Sheet Purchase Orders
A1: ID | B1: TestRail | C1: What you are checking | D1: Why it matters to a real user | E1: Before you start | F1: TYPE THIS | G1: What to do | H1: What you should see | I1: Where that comes from | J1: The exact wording of the requirement | K1: Result | L1: What you actually saw | M1: Ticket
A2: SRI-PO-A1 | B2: C146266 | C2: The whole matched value is shown, not just what you typed | D2: If the row shows only the characters I typed, I am reading my own query back. It tells me nothing about which record this is. | E2: A purchase order exists whose PO number contains this fragment somewhere other than the very start. NOTE: 6 rows come back sharing this fragment — perfect for this test | F2: Fibridge | G2: 1. Open search and type the term in the green cell. 2. Open the Purchase Orders tab. 3. Look at each row WITHOUT opening it. 4. Write down the PO number exactly as the row shows it. | H2: Each row shows the COMPLETE PO number, with the bit you typed highlighted inside it. Seeing only what you typed, or a value cut short with "...", is a FAIL — that is SV-10619 and SV-10551. | I2: PRD v1.5, section 5.3 | J2: Every row has a left-side entity icon, a primary line (bold), a secondary line (subdued), and an optional right-side cluster (status badges, counts, and quick-action buttons on hover). The matched substring of the query is highlighted in the primary and secondary text — searching `Fib` highlights "Fib" in "S1-644 Fibridge Commercial".
A3: SRI-PO-A2 | B3: C146267 | C3: A long value is not cut off through the part that matched | D3: A row that cuts off at "9..." has hidden the one thing I was looking for. | E3: A purchase order whose text is long enough to overflow the search box (the box is a fixed width), with the matched characters near the END of the value. | F3: Fibridge | G3: 1. Open search and type the term. 2. Open the Purchase Orders tab. 3. Look for any text ending in "...". 4. If you see one, write down what is hidden and what you typed. | H3: You can still identify the record. If the "..." has eaten the characters you typed, or eaten the part that tells this record from its neighbours, that is a FAIL. | I3: Story SV-9170 | J3: Each result row carries enough context to pick the right record without opening it — its identifier, who it belongs to, its status, and for work orders the unit number and vehicle, which is what tells two of the same customer's work orders apart.
A4: SRI-PO-A3 | B4: C146268 | C4: The highlight marks the match inside the text, not instead of it | D4: A highlight is meant to point at something. If it replaces the text, it points at nothing. | E4: Any purchase order you can find by typing part of what the row displays. | F4: Fibridge | G4: 1. Open search and type the term. 2. Open the Purchase Orders tab. 3. Look at how the match is drawn on the row. | H4: The full text is on the row and the matched part is highlighted within it — exactly like the example in the requirement, where typing "Fib" shows the whole of "S1-644 Fibridge Commercial" with "Fib" marked. | I4: PRD v1.5, section 5.3 | J4: Every row has a left-side entity icon, a primary line (bold), a secondary line (subdued), and an optional right-side cluster (status badges, counts, and quick-action buttons on hover). The matched substring of the query is highlighted in the primary and secondary text — searching `Fib` highlights "Fib" in "S1-644 Fibridge Commercial".
A5: SRI-PO-B1 | B5: C146269 | C5: Two records sharing what you typed can be told apart | D5: This is the whole point. Type 123786 and if two rows both draw as "786", you cannot tell 123786 from 185786 without opening both. | E5: Two purchase orders exist whose PO number are DIFFERENT but share a run of characters. NOTE: 6 rows come back sharing this fragment — perfect for this test | F5: Fibridge | G5: 1. Open search and type the term. 2. Open the Purchase Orders tab. 3. WITHOUT opening anything, write down which row is which. 4. If you cannot tell them apart, that is the failure — say so. | H5: You can say which row is which from the rows alone. Two rows that read the same is a FAIL — and note that the right number of rows does not rescue it. | I5: Story SV-9170 | J5: Each result row carries enough context to pick the right record without opening it — its identifier, who it belongs to, its status, and for work orders the unit number and vehicle, which is what tells two of the same customer's work orders apart.
A6: SRI-PO-B2 | B6: C146270 | C6: Two records with the same bold line differ somewhere you can see | D6: Real shops have two trucks of the same year/make/model and two vendors with the same name. If the rows are identical the list is useless. | E6: Two purchase orders whose bold first line is identical but which are different records. These were seeded for this suite. NOTE: 6 rows come back; at least two carry the same bold line | F6: Fibridge | G6: 1. Open search and type the term. 2. Open the Purchase Orders tab. 3. Compare the two rows line by line. 4. Write down what, if anything, separates them. | H6: Something visible differs — the second line, a badge, a number. Two identical rows is a FAIL; write down both records and what actually differs between them in the data. | I6: Story SV-9170 | J6: Each result row carries enough context to pick the right record without opening it — its identifier, who it belongs to, its status, and for work orders the unit number and vehicle, which is what tells two of the same customer's work orders apart.
A7: SRI-PO-C1 | B7: C146271 | C7: A match on part numbers on the PO shows the FULL value on the row | D7: the buyer asks "which order did I put that part on?" | E7: A purchase order carrying a distinctive value in part numbers on the PO — a value that appears in NO other field of that record. NOTE: 3 rows come back sharing this | F7: 0123 | G7: 1. Open search and type the term. 2. Open the Purchase Orders tab. 3. Find the record. Without opening it, read the SECOND line of the row. 4. It should carry a labelled note naming the field that matched. 5. Now check the value in that note against the record itself. | H7: The second line carries a labelled note — such as "Contact match: ...", "Matched: ...", "Unit: ...", "VIN: ..." — naming what matched, with the part you typed highlighted inside it. THE THING TO CHECK IS WHETHER THE VALUE IS COMPLETE. The note must show the WHOLE part numbers on the PO value, not just the characters you typed. Open the record and compare. If you typed part of a longer value and the note shows only that part, this is a FAIL — it is SV-10619 and SV-10551, and it means two different records can draw identically. | I7: PRD v1.5, section 5.3 | J7: Every row has a left-side entity icon, a primary line (bold), a secondary line (subdued), and an optional right-side cluster (status badges, counts, and quick-action buttons on hover). The matched substring of the query is highlighted in the primary and secondary text — searching `Fib` highlights "Fib" in "S1-644 Fibridge Commercial".
A8: SRI-PO-C2 | B8: C146272 | C8: A match on part descriptions on the PO shows the FULL value on the row | D8: the same question by name | E8: A purchase order carrying a distinctive value in part descriptions on the PO — a value that appears in NO other field of that record. NOTE: 3 rows come back sharing this | F8: 786 | G8: 1. Open search and type the term. 2. Open the Purchase Orders tab. 3. Find the record. Without opening it, read the SECOND line of the row. 4. It should carry a labelled note naming the field that matched. 5. Now check the value in that note against the record itself. | H8: The second line carries a labelled note — such as "Contact match: ...", "Matched: ...", "Unit: ...", "VIN: ..." — naming what matched, with the part you typed highlighted inside it. THE THING TO CHECK IS WHETHER THE VALUE IS COMPLETE. The note must show the WHOLE part descriptions on the PO value, not just the characters you typed. Open the record and compare. If you typed part of a longer value and the note shows only that part, this is a FAIL — it is SV-10619 and SV-10551, and it means two different records can draw identically. | I8: PRD v1.5, section 5.3 | J8: Every row has a left-side entity icon, a primary line (bold), a secondary line (subdued), and an optional right-side cluster (status badges, counts, and quick-action buttons on hover). The matched substring of the query is highlighted in the primary and secondary text — searching `Fib` highlights "Fib" in "S1-644 Fibridge Commercial".
A9: SRI-PO-C3 | B9: C146273 | C9: A match on created-by user shows the FULL value on the row | D9: the buyer looks for their own orders | E9: A purchase order carrying a distinctive value in created-by user — a value that appears in NO other field of that record. NOTE: proven to match on ordered_by_name (word) | F9: Admin ShopView | G9: 1. Open search and type the term. 2. Open the Purchase Orders tab. 3. Find the record. Without opening it, read the SECOND line of the row. 4. It should carry a labelled note naming the field that matched. 5. Now check the value in that note against the record itself. | H9: The second line carries a labelled note — such as "Contact match: ...", "Matched: ...", "Unit: ...", "VIN: ..." — naming what matched, with the part you typed highlighted inside it. THE THING TO CHECK IS WHETHER THE VALUE IS COMPLETE. The note must show the WHOLE created-by user value, not just the characters you typed. Open the record and compare. If you typed part of a longer value and the note shows only that part, this is a FAIL — it is SV-10619 and SV-10551, and it means two different records can draw identically. | I9: PRD v1.5, section 5.3 | J9: Every row has a left-side entity icon, a primary line (bold), a secondary line (subdued), and an optional right-side cluster (status badges, counts, and quick-action buttons on hover). The matched substring of the query is highlighted in the primary and secondary text — searching `Fib` highlights "Fib" in "S1-644 Fibridge Commercial".
A10: SRI-PO-C4 | B10: C146274 | C10: A match on spliced number variants (`number_variants`) shows the FULL value on the row | D10: measured on the build and NOT listed in PRD §4 — see PO-QUESTIONS Q7; it is what makes a PO match a number that appears in no displayed text | E10: A purchase order carrying a distinctive value in spliced number variants (`number_variants`) — a value that appears in NO other field of that record. NOTE: proven to match on number_variants (word) | F10: 107401402 | G10: 1. Open search and type the term. 2. Open the Purchase Orders tab. 3. Find the record. Without opening it, read the SECOND line of the row. 4. It should carry a labelled note naming the field that matched. 5. Now check the value in that note against the record itself. | H10: The second line carries a labelled note — such as "Contact match: ...", "Matched: ...", "Unit: ...", "VIN: ..." — naming what matched, with the part you typed highlighted inside it. THE THING TO CHECK IS WHETHER THE VALUE IS COMPLETE. The note must show the WHOLE spliced number variants (`number_variants`) value, not just the characters you typed. Open the record and compare. If you typed part of a longer value and the note shows only that part, this is a FAIL — it is SV-10619 and SV-10551, and it means two different records can draw identically. | I10: PRD v1.5, section 5.3 | J10: Every row has a left-side entity icon, a primary line (bold), a secondary line (subdued), and an optional right-side cluster (status badges, counts, and quick-action buttons on hover). The matched substring of the query is highlighted in the primary and secondary text — searching `Fib` highlights "Fib" in "S1-644 Fibridge Commercial".
A11: SRI-PO-D1 | B11: C146275 | C11: The Purchase Orders row shows everything the specification promised | D11: Each field is there because somebody decided you need it to choose. A missing one is a choice you now have to make by opening records. | E11: Any purchase order that search returns, which has a value in each field named in the requirement column. | F11: Fibridge | G11: 1. Open search and type something that returns the record. 2. Open the Purchase Orders tab. 3. Check the row against the requirement column, field by field. 4. Tick off each one. Write down any that is missing. | H11: Every field named in the requirement is on the row. Do not judge whether a missing one matters — just record it. | I11: PRD v1.5, section 4 | J11: Displayed: PO number + vendor (primary), status badge (Ordered / Received), total + created date.
A12: SRI-PO-I1 | B12: C146276 | C12: A corrected typo says that it corrected something | D12: If the system quietly fixes my typo without saying so, I will think I found an exact match and act on the wrong record. | E12: A purchase order whose name or description can be found by spelling it slightly wrong (one or two letters out). Do NOT use a number or a code — those are excluded on purpose. NOTE: checked on this environment: typing this brings back 'I10740-1400', whose name is a near-miss of what you typed, and it should be drawn as a SOFT match. That soft row is the one this test is about — not the exact matches above it. | F12: ZZSOFTHIT | G12: 1. Open search and type the near-miss spelling. 2. Open the Purchase Orders tab. 3. Look closely at the matched word. | H12: The matched word is highlighted AND carries the "≈" mark or italics that says it is a close match. A corrected typo that looks exactly like an exact match is a FAIL. | I12: PRD v1.5, section 7 | J12: When a match is fuzzy rather than exact, the matched token in the row is still highlighted, and a subtle `≈` or italicized treatment indicates the soft match.

Sheet Vendor Invoices
A1: ID | B1: TestRail | C1: What you are checking | D1: Why it matters to a real user | E1: Before you start | F1: TYPE THIS | G1: What to do | H1: What you should see | I1: Where that comes from | J1: The exact wording of the requirement | K1: Result | L1: What you actually saw | M1: Ticket
A2: SRI-VINV-A1 | B2: C146277 | C2: The whole matched value is shown, not just what you typed | D2: If the row shows only the characters I typed, I am reading my own query back. It tells me nothing about which record this is. | E2: A vendor invoice exists whose invoice number contains this fragment somewhere other than the very start. NOTE: 3 rows come back sharing this fragment — perfect for this test | F2: Fibridge | G2: 1. Open search and type the term in the green cell. 2. Open the Vendor Invoices tab. 3. Look at each row WITHOUT opening it. 4. Write down the invoice number exactly as the row shows it. | H2: Each row shows the COMPLETE invoice number, with the bit you typed highlighted inside it. Seeing only what you typed, or a value cut short with "...", is a FAIL — that is SV-10619 and SV-10551. | I2: PRD v1.5, section 5.3 | J2: Every row has a left-side entity icon, a primary line (bold), a secondary line (subdued), and an optional right-side cluster (status badges, counts, and quick-action buttons on hover). The matched substring of the query is highlighted in the primary and secondary text — searching `Fib` highlights "Fib" in "S1-644 Fibridge Commercial".
A3: SRI-VINV-A2 | B3: C146278 | C3: A long value is not cut off through the part that matched | D3: A row that cuts off at "9..." has hidden the one thing I was looking for. | E3: A vendor invoice whose text is long enough to overflow the search box (the box is a fixed width), with the matched characters near the END of the value. | F3: Fibridge | G3: 1. Open search and type the term. 2. Open the Vendor Invoices tab. 3. Look for any text ending in "...". 4. If you see one, write down what is hidden and what you typed. | H3: You can still identify the record. If the "..." has eaten the characters you typed, or eaten the part that tells this record from its neighbours, that is a FAIL. | I3: Story SV-9170 | J3: Each result row carries enough context to pick the right record without opening it — its identifier, who it belongs to, its status, and for work orders the unit number and vehicle, which is what tells two of the same customer's work orders apart.
A4: SRI-VINV-A3 | B4: C146279 | C4: The highlight marks the match inside the text, not instead of it | D4: A highlight is meant to point at something. If it replaces the text, it points at nothing. | E4: Any vendor invoice you can find by typing part of what the row displays. | F4: Fibridge | G4: 1. Open search and type the term. 2. Open the Vendor Invoices tab. 3. Look at how the match is drawn on the row. | H4: The full text is on the row and the matched part is highlighted within it — exactly like the example in the requirement, where typing "Fib" shows the whole of "S1-644 Fibridge Commercial" with "Fib" marked. | I4: PRD v1.5, section 5.3 | J4: Every row has a left-side entity icon, a primary line (bold), a secondary line (subdued), and an optional right-side cluster (status badges, counts, and quick-action buttons on hover). The matched substring of the query is highlighted in the primary and secondary text — searching `Fib` highlights "Fib" in "S1-644 Fibridge Commercial".
A5: SRI-VINV-B1 | B5: C146280 | C5: Two records sharing what you typed can be told apart | D5: This is the whole point. Type 123786 and if two rows both draw as "786", you cannot tell 123786 from 185786 without opening both. | E5: Two vendor invoices exist whose invoice number are DIFFERENT but share a run of characters. NOTE: 3 rows come back sharing this fragment — perfect for this test | F5: Fibridge | G5: 1. Open search and type the term. 2. Open the Vendor Invoices tab. 3. WITHOUT opening anything, write down which row is which. 4. If you cannot tell them apart, that is the failure — say so. | H5: You can say which row is which from the rows alone. Two rows that read the same is a FAIL — and note that the right number of rows does not rescue it. | I5: Story SV-9170 | J5: Each result row carries enough context to pick the right record without opening it — its identifier, who it belongs to, its status, and for work orders the unit number and vehicle, which is what tells two of the same customer's work orders apart.
A6: SRI-VINV-B2 | B6: C146281 | C6: Two records with the same bold line differ somewhere you can see | D6: Real shops have two trucks of the same year/make/model and two vendors with the same name. If the rows are identical the list is useless. | E6: Two vendor invoices whose bold first line is identical but which are different records. These were seeded for this suite. NOTE: 3 rows come back; at least two carry the same bold line | F6: Fibridge | G6: 1. Open search and type the term. 2. Open the Vendor Invoices tab. 3. Compare the two rows line by line. 4. Write down what, if anything, separates them. | H6: Something visible differs — the second line, a badge, a number. Two identical rows is a FAIL; write down both records and what actually differs between them in the data. | I6: Story SV-9170 | J6: Each result row carries enough context to pick the right record without opening it — its identifier, who it belongs to, its status, and for work orders the unit number and vehicle, which is what tells two of the same customer's work orders apart.
A7: SRI-VINV-C1 | B7: C146282 | C7: A match on the PO number the invoice belongs to shows the FULL value on the row | D7: accounts payable reconciles an invoice against the order it came from, and the PO number is indexed but never shown | E7: A vendor invoice carrying a distinctive value in the PO number the invoice belongs to — a value that appears in NO other field of that record. NOTE: proven to match on order_number (exact) | F7: I10740-965 | G7: 1. Open search and type the term. 2. Open the Vendor Invoices tab. 3. Find the record. Without opening it, read the SECOND line of the row. 4. It should carry a labelled note naming the field that matched. 5. Now check the value in that note against the record itself. | H7: The second line carries a labelled note — such as "Contact match: ...", "Matched: ...", "Unit: ...", "VIN: ..." — naming what matched, with the part you typed highlighted inside it. THE THING TO CHECK IS WHETHER THE VALUE IS COMPLETE. The note must show the WHOLE the PO number the invoice belongs to value, not just the characters you typed. Open the record and compare. If you typed part of a longer value and the note shows only that part, this is a FAIL — it is SV-10619 and SV-10551, and it means two different records can draw identically. | I7: PRD v1.5, section 5.3 | J7: Every row has a left-side entity icon, a primary line (bold), a secondary line (subdued), and an optional right-side cluster (status badges, counts, and quick-action buttons on hover). The matched substring of the query is highlighted in the primary and secondary text — searching `Fib` highlights "Fib" in "S1-644 Fibridge Commercial".
A8: SRI-VINV-D1 | B8: C146283 | C8: The Vendor Invoices row shows everything the specification promised | D8: Each field is there because somebody decided you need it to choose. A missing one is a choice you now have to make by opening records. | E8: Any vendor invoice that search returns, which has a value in each field named in the requirement column. | F8: Fibridge | G8: 1. Open search and type something that returns the record. 2. Open the Vendor Invoices tab. 3. Check the row against the requirement column, field by field. 4. Tick off each one. Write down any that is missing. | H8: Every field named in the requirement is on the row. Do not judge whether a missing one matters — just record it. | I8: PRD v1.5, section 4 | J8: Displayed: invoice number + vendor (primary), status badge (Paid / Unpaid), total + invoice date.
A9: SRI-VINV-I1 | B9: C146284 | C9: A corrected typo says that it corrected something | D9: If the system quietly fixes my typo without saying so, I will think I found an exact match and act on the wrong record. | E9: A vendor invoice whose name or description can be found by spelling it slightly wrong (one or two letters out). Do NOT use a number or a code — those are excluded on purpose. NOTE: checked on this environment: typing this brings back 'ZZTINV-RISOFT-9001', whose name is a near-miss of what you typed, and it should be drawn as a SOFT match. That soft row is the one this test is about — not the exact matches above it. | F9: ZZSOFTHIT | G9: 1. Open search and type the near-miss spelling. 2. Open the Vendor Invoices tab. 3. Look closely at the matched word. | H9: The matched word is highlighted AND carries the "≈" mark or italics that says it is a close match. A corrected typo that looks exactly like an exact match is a FAIL. | I9: PRD v1.5, section 7 | J9: When a match is fuzzy rather than exact, the matched token in the row is still highlighted, and a subtle `≈` or italicized treatment indicates the soft match.

Sheet All tab and cross-tab
A1: ID | B1: TestRail | C1: What you are checking | D1: Why it matters to a real user | E1: Before you start | F1: TYPE THIS | G1: What to do | H1: What you should see | I1: Where that comes from | J1: The exact wording of the requirement | K1: Result | L1: What you actually saw | M1: Ticket
A2: SRI-ALL-E1 | B2: C146285 | C2: A tab's count equals the number of rows inside it | D2: If the tab says 8 and shows 5, I stop looking and miss the record. | E2: A search that returns more than 5 but fewer than 20 of one kind. | F2: 965 | G2: 1. Type the term. 2. Read the number on each tab. 3. Open a tab and count the rows. 4. Compare the two. | H2: The number on the tab and the number of rows inside it agree, up to a maximum of 20. | I2: PRD v1.5, section 5.2 | J2: The scoped tab shows **up to 20 rows**, scrolled within the modal — there is no pagination and no further loading, and no `Show all` link inside the tab.
A3: SRI-ALL-E2 | B3: C146286 | C3: No count anywhere reads higher than 20 | D3: A count I cannot reach is a promise the product does not keep. | E3: A search matching more than 20 of one kind. ZZBROAD matches 22 parts. | F3: ZZBROAD | G3: 1. Type the term. 2. Read the Parts tab count. 3. Read the group heading count on the All tab. 4. Read the "Show all N" link. | H3: All three read 20 — never the true total. | I3: PRD v1.5, section 5.2 | J3: **Counts are capped at 20.** No count in the modal reads higher than `20` — not a tab, not a group header, not the `Show all N` link. A query matching 34 work orders shows `Work Orders (20)` and `Show all 20`. Twenty is both what search returns per entity type and what it reports.
A4: SRI-ALL-E3 | B4: C146287 | C4: A group on the All tab shows 5 and offers the rest | D4: Five is a sample. I need to know a sample is what I am looking at. | E4: A search returning more than 5 of one kind. | F4: ZZBROAD | G4: 1. Type the term. 2. Stay on the All tab. 3. Count the rows under the Parts heading. 4. Look to the right of that heading. | H4: Exactly 5 rows, and a "Show all N" link beside the heading. | I4: PRD v1.5, section 5.2 | J4: Each group shows up to **5** results (raised from today's 3). When a group has more, a `Show all N` link appears to the right of the group header.
A5: SRI-ALL-E4 | B5: C146288 | C5: "Show all" opens that tab and keeps you in the search box | D5: Losing the search box loses my query and my place. | E5: A search returning more than 5 of one kind. | F5: ZZBROAD | G5: 1. Type the term. 2. Click "Show all N" beside a group heading. 3. Check where you have landed and whether your text is still in the box. | H5: You land on that entity's tab, still inside the search box, with your text intact. Being sent to a separate page is a FAIL. | I5: PRD v1.5, section 5.2 | J5: Clicking it switches the modal to that entity's scope tab. The user never leaves the modal: there is no separate search results page and no handoff of the query to the entity's list page.
A6: SRI-ALL-E5 | B6: C146289 | C6: All nine tabs are there, named and counted | D6: A missing tab is a kind of record I will never think to look for. | E6: Anything that returns at least one result. | F6: 965 | G6: 1. Type the term. 2. Read the tab strip left to right, scrolling it sideways. 3. Check each tab carries a count. | H6: All nine, in this order: All, Work Orders, Customers, Assets, Parts, Vendors, Part Sales, Purchase Orders, Vendor Invoices. | I6: PRD v1.5, section 5.2 | J6: A horizontal tab strip immediately under the input: `All · Work Orders · Customers · Assets · Parts · Vendors · Part Sales · Purchase Orders · Vendor Invoices`. Each tab carries its result count, e.g. `All (12)`, `Work Orders (8)`.
A7: SRI-ALL-E6 | B7: C146290 | C7: Groups on the All tab are always in the same order | D7: A stable order is what lets me scan without reading. | E7: A search returning results in four or more kinds. | F7: 965 | G7: 1. Type the term. 2. Stay on the All tab. 3. Read the group headings top to bottom. | H7: Work Orders, then Customers, Assets, Parts, Vendors, Part Sales, Purchase Orders, Vendor Invoices. Kinds with no results are simply skipped. | I7: PRD v1.5, section 6.2 | J7: Group display order in "All" is: Work Orders → Customers → Assets → Parts → Vendors → Part Sales → Purchase Orders → Vendor Invoices.
A8: SRI-ALL-E7 | B8: C146291 | C8: Typing a full record number puts that record at the very top | D8: If I typed a work order number I want that work order, not a list. | E8: A record whose number you can type in full. Take one from any list page. | F8: S10740-17584 | G8: 1. Type the number in full. 2. Look ABOVE the first group heading. | H8: That one record sits alone at the top, above all the groups, with its icon. | I8: PRD v1.5, section 6.2 | J8: When the top result across all groups has a score > 0.95 (effectively an ID match), it is pinned as a separate single row at the very top, above the groups, labeled by its entity icon — the "if you typed `S2-15276`, jump straight to that WO" experience.
A9: SRI-ALL-F1 | B9: C146292 | C9: A number is found with and without its dashes | D9: I type what is printed on the paper in front of me, dashes and all. | E9: Any work order number, e.g. from the Work Orders list. | F9: S10740-17584 | G9: 1. Type the number exactly as printed, dashes and all. 2. Note what comes back. 3. Type it again with every dash and space removed. 4. Compare the two lists. | H9: Both find the same record. | I9: PRD v1.5, section 7 | J9: Lowercase; strip diacritics; collapse whitespace; for identifier fields (WO number, part number, VIN, phone) also strip non-alphanumerics so `S2-15276` and `s215276` match, and `(264) 328-6723` and `2643286723` match. For names, keep spaces but treat hyphens and apostrophes as optional.
A10: SRI-ALL-F2 | B10: C146293 | C10: A phone number is found however it is punctuated | D10: The number on my screen has brackets. The number in my head does not. | E10: A customer with a punctuated phone number. | F10: 730-246-8895 | G10: 1. Type the number with its dashes. 2. Type the same digits with nothing between them. 3. Compare the two lists. 4. Now type only the last four digits and see what comes back. | H10: The first two find the same customer. The last-four search is a different test — write down whether you can tell the results apart (that is test B1 on the Customers tab). | I10: PRD v1.5, section 7 | J10: Lowercase; strip diacritics; collapse whitespace; for identifier fields (WO number, part number, VIN, phone) also strip non-alphanumerics so `S2-15276` and `s215276` match, and `(264) 328-6723` and `2643286723` match. For names, keep spaces but treat hyphens and apostrophes as optional.
A11: SRI-ALL-F3 | B11: C146294 | C11: An accented name is found typed either way | D11: Nobody types the accent. | E11: A customer whose name has an accent. The seeded ZZACC records have one. | F11: ZZACC | G11: 1. Type the name with its accents. 2. Type it without. 3. Compare. | H11: Both spellings return the same single customer. | I11: PRD v1.5, section 7 | J11: Lowercase; strip diacritics; collapse whitespace; for identifier fields (WO number, part number, VIN, phone) also strip non-alphanumerics so `S2-15276` and `s215276` match, and `(264) 328-6723` and `2643286723` match. For names, keep spaces but treat hyphens and apostrophes as optional.
A12: SRI-ALL-F4 | B12: C146295 | C12: An apostrophe or hyphen in a name is optional | D12: "O'Brien" and "OBrien" are the same person to everyone but a computer. | E12: The seeded ZZPUNC records — one has an apostrophe, one a hyphen. | F12: ZZPUNC | G12: 1. Type each name with its punctuation. 2. Type each name without it. 3. Compare. | H12: Both spellings find the record. | I12: PRD v1.5, section 7 | J12: Lowercase; strip diacritics; collapse whitespace; for identifier fields (WO number, part number, VIN, phone) also strip non-alphanumerics so `S2-15276` and `s215276` match, and `(264) 328-6723` and `2643286723` match. For names, keep spaces but treat hyphens and apostrophes as optional.
A13: SRI-ALL-F5 | B13: C146296 | C13: A typo in a NUMBER is not silently corrected | D13: A wrong VIN is a wrong truck. I would rather see nothing than the wrong vehicle presented as a match. This is the most dangerous result search can give. | E13: A real VIN, proven on this environment. | F13: 1FUJGLDR9CLBP8834 | G13: 1. Type the VIN exactly — confirm the vehicle comes back. 2. Now change ONE character and search again. 3. Read the result list carefully. | H13: The near-miss VIN does NOT return the vehicle. If it does, that is a FAIL — record it immediately, this one matters more than the rest. | I13: PRD v1.5, section 7 | J13: Exact identifier fields — VIN, WO number, P-number, part number, PO number, invoice number — bypass fuzzy logic and require exact match after normalization. A typo in a VIN is almost always a wrong VIN, not a typo, and fuzzy matching here would surface confusing results.
... A17: SRI-ALL-G3 | B17: C146300 | C17: A very common word still gives a usable list | D17: Parts are called "Kit", "Filter", "Seal". If a common word gives 20 near-identical rows the tab is dead weight. | E17: A word that appears in many part descriptions. | F17: Filter | G17: 1. Type the word. 2. Open the Parts tab. 3. Pick one specific part you know exists and try to find it in the list. | H17: The part you wanted is inside the 20, and the rows differ enough to choose from. If you cannot reach it, say which part and what you typed. | I17: PRD v1.5, section 6.1 | J17: Because search returns at most 20 records per entity type (§5.2), ranking quality is what decides whether the record the user wanted is reachable at all.
A18: SRI-ALL-G4 | B18: C195902 | C18: One or two characters behaves sensibly | D18: Everybody types one character on the way to typing six. | E18: Nothing. | F18: 9 | G18: 1. Type a single character and wait. 2. Add a second character and wait. 3. Write down what happened at each step. | H18: THIS ROW IS HELD — the specification sets a typing delay but no minimum length, so we cannot say what one character should do. Do not pass or fail it. It must not error, must not hang, and must not leave the previous keystroke's results on screen. | I18: PRD v1.5, section 8 (the spec is silent — see question Q10) | J18: …debounce input at 150ms… | K18: HELD - do not run
A19: SRI-ALL-G5 | B19: C146302 | C19: A kind of record that does not exist yet does not break search | D19: A new shop has no part sales. Search must still work. | E19: A workplace where at least one kind has no records at all. | F19: 965 | G19: 1. Search something that returns results in other kinds. 2. Read the tab strip. 3. Read the group list. | H19: Search works normally and the empty kind simply does not appear. | I19: PRD v1.5, section 9 | J19: Search must work for a single-tenant dataset where any entity type is empty (e.g. a shop with no part sales yet).
A20: SRI-ALL-H1 | B20: C146303 | C20: No results shows your query back, and nothing else | D20: Seeing my own typo is how I realise it was a typo. | E20: Nothing. | F20: Zqwxpol | G20: 1. Type the term. 2. Read the message. | H20: It reads: No results for 'Zqwxpol' — and nothing else. No suggestions, no buttons, no tips. | I20: PRD v1.5, section 5.2 | J20: "No results for '<query>'" — plus " in <Tab>" when a scope tab other than All is active. Nothing else.
A21: SRI-ALL-H2 | B21: C146304 | C21: No results inside a tab names the tab | D21: "No results" when there ARE results on another tab would send me away for nothing. | E21: A search returning results in one kind only. | F21: ZZVORTAC | G21: 1. Type the term. 2. Open a tab that has no results for it. 3. Read the message. | H21: The message names the tab you are on, so you know the search is narrowed and not empty everywhere. | I21: PRD v1.5, section 5.2 | J21: "No results for '<query>'" — plus " in <Tab>" when a scope tab other than All is active. Nothing else.
A22: SRI-ALL-H3 | B22: C146305 | C22: A record you can open from its own list is never "not found" | D22: The worst possible outcome — the record exists, I can open it from its list page, and search says it does not exist. | E22: Pick any record from its own list page and note one of its values. | F22: ZZLONGROW | G22: 1. Search that value. 2. If nothing comes back, confirm the record still opens from its list page. 3. Then search a DIFFERENT value from the SAME record as a control. 4. Record both outcomes together — the control is what makes this trustworthy. | H22: The value finds its record. The control in step 3 is NOT optional: without it you cannot tell "this field is not searchable" from "the search is down". | I22: PRD v1.5, section 4 | J22: The indexed fields are what a typed query is matched against…
A23: SRI-ALL-K1 | B23: C146306 | C23: Someone without access sees no rows AND no count | D23: A technician seeing finance rows is a data leak, not a search bug. | E23: A role without Parts access, and one without Purchase Order / Vendor Invoice access. The seven seeded "ZZAUTOTEST No ..." roles cover this. | F23: 965 | G23: 1. Sign in as a user with full access, search, and note the rows and the counts. 2. Sign in as the restricted role and run the IDENTICAL search. 3. Compare rows AND counts. | H23: The restricted user sees none of those rows, no tab for them, and no count. Check the COUNT as well — a count still showing the full total leaks how much exists. | I23: PRD v1.5, section 9 | J23: All result fields must respect existing tenant-isolation and role-based-access checks — a technician without Parts access does not see Parts results, and the same applies to Purchase Orders and Vendor Invoices, which are finance-adjacent and more likely to be restricted.

Sheet Questions for the PO
A1: # | B1: The question | C1: What is happening now | D1: Why it matters | E1: What the specification says today | F1: What we need decided | G1: TRY IT YOURSELF — type this | H1: What you will see | I1: Tests waiting on it
A2: THESE ARE NOT TESTS. They cannot be run in the application — they are decisions we need before 32 of the tests can say pass or fail. The test rows they block are named in the last column. EVERY ROW CARRIES SOMETHING YOU CAN TYPE INTO THE SEARCH YOURSELF (green cell) AND WHAT IT ACTUALLY RETURNED WHEN WE CHECKED IT ON STAGING ON 2026-09-29.
A3: Q1 | B3: 🟢 ANSWERED ON THE BUILD 2026-09-29 — WITHDRAWN. The row DOES say why it came back. | C3: We asked what a row should do when it matches on a field it does not display. The QA lead tested it and the answer was already in the product: the row appends a labelled note to its second line — "Contact match: 609-461-6502", "Matched: KVQ-2870", "Number: I-1522", "Unit: ...", "VIN: ...". | D3: Nothing is blocked by this any more. The 32 test cases that were held on it are now ordinary assertions and have been rewritten; they check that the note shows the FULL value. | E3: Section 5.3 does not describe this labelled note, so the specification is behind the build. That is a documentation gap, not a behaviour decision. | F3: Only this: should section 5.3 be updated to describe the labelled match note, so the spec and the product agree? No product change is being proposed. | G3: 609-461-6502 | H3: The customer comes back and the second line reads "Contact match: 609-461-6502" with the number highlighted. The row says why it is here. This is what we got wrong. | I3: None — all 32 released
A4: Q2 | B4: 🟢 ANSWERED — WITHDRAWN. A customer found by phone DOES show the phone. | C4: We reported that a customer matched on a telephone number showed no telephone. That was wrong: the row shows "Contact match: <the number>" on its second line. | D4: The claim came from reading the API payload and the row variants rather than opening the screen. It is withdrawn. | E4: Section 4 says "telephone on hover" for Customers, which is a different thing again and is not what the build does. | F4: Nothing. Folded into Q1 as a documentation point. | G4: 609-461-6502 | H4: Same search. The phone number IS on the row, as a Contact match note. Our earlier claim that it was missing is withdrawn. | I4: None
A5: Q3 | B5: 🔴 THE ONE REAL DEFECT — show the whole value, highlight the part that matched. | C5: When you type part of a longer value, the row shows only the part you typed. Type 965 and a row reads "Contact match: 965" — the phone number it came from, 857-496-5067, is never shown. But type 3286 against (264) 328-6723 and the row shows the whole number. Same field, same kind of match, two behaviours. | D5: THIS IS THE BUG BEHIND SV-10619 AND SV-10551. Two records whose numbers both contain 965 draw identically, so the user cannot tell them apart — 123786 and 185786 both showing as 786. The QA lead: "we need to show the full word/number and highlight the matching part." | E5: Section 5.3: "The matched substring of the query is highlighted in the primary and secondary text" — highlighting a substring requires the whole text to be there. | F5: Confirm the fix: the API should send the WHOLE field value, and the screen should highlight the typed part inside it. The front end already does exactly that wherever it has the full text — the change is in MatchDescriptorFactory::fragmentOf() on the API side. NEEDS A DEVELOPER. | G5: 965 | H5: Look at the Contact match notes. Some read "Contact match: 965" — only the three characters typed. The phone number they came from is never shown. Now search 3286 and you get "Contact match: (264) 328-6723", the whole number. THIS is the bug: two records whose numbers both contain 965 draw identically. | I5: Every "A" and "C" case — 56
A6: Q4 | B6: 🟢 ANSWERED — the Assets row shows the unit number, and that is wanted. | C6: The build shows the unit number leading the Assets row; section 4 does not list it. | D6: The QA lead confirmed this is fine and useful. | E6: Section 4 does not list the unit number for Assets. | F6: Add the unit number to section 4 for Assets so the spec matches the build. Documentation only. | G6: ZZLONGROW | H6: On the Assets tab the unit number leads the row. Useful — the spec just does not mention it. | I6: None
A7: Q5 | B7: 🟢 ANSWERED — licence plate appears on the second line. | C7: Typing a licence plate returns the vehicle and the row reads "Matched: KVQ-2870". | D7: Confirmed by the QA lead on staging. | E7: Licence plate is not in section 4 searchable list. | F7: Add licence plate to section 4 as a searchable field. Documentation only. | G7: KVQ-2870 | H7: The vehicle comes back and the second line reads "Matched: KVQ-2870". | I7: None
A8: Q6 | B8: 🟢 ANSWERED — postal code appears on the second line. | C8: Typing a postal code returns the customer and the row reads "Matched: H8A3X9". | D8: Confirmed by the QA lead on staging. | E8: Postal code is not in section 4 searchable list. | F8: Add postal code to section 4 as a searchable field. Documentation only. | G8: H8A3X9 | H8: The customer comes back and the second line reads "Matched: H8A3X9". | I8: None
A9: Q7 | B9: 🟢 ANSWERED — the number you typed appears on the second line. | C9: A purchase order displaying I2-1522 is found by typing I-1522, and the row reads "Number: I-1522" so you can see why it came back. | D9: Confirmed by the QA lead on staging. | E9: Number variants are not in section 4. | F9: Add the alternate number form to section 4 as searchable. Documentation only. | G9: I-1522 | H9: The purchase order comes back reading I2-1522, and the second line reads "Number: I-1522" so you can see why. | I9: None
A10: Q8 | B10: 🟢 ANSWERED — the received date is the right date. | C10: Section 4 says "invoice date"; the row shows the received date. | D10: The QA lead confirmed the received date is correct for this row. | E10: Section 4 says invoice date. | F10: Correct section 4 to say received date. Documentation only. | G10: Fibridge | H10: On Vendor Invoices the date shown is the received date, which is the one you want. | I10: None
A11: Q9 | B11: 🟢 ANSWERED — the unit number shows when the vehicle has one. | C11: A work order row shows the unit number first on the second line when the vehicle carries one, and the year/make/model alone when it does not. | D11: Confirmed by the QA lead on staging. | E11: Section 4 covers the fallback and the build matches it. | F11: Nothing. | G11: ZZNOUNIT | H11: A work order comes back and the unit number leads the second line when the vehicle has one. | I11: None
A12: Q10 | B12: 🟢 ANSWERED — a one-character search behaves sensibly. | C12: Typing a single character searches and behaves as expected. | D12: Confirmed by the QA lead on staging. | E12: The specification sets a typing delay but no minimum length. | F12: Optional: record in section 8 that there is no minimum query length, so the behaviour is documented rather than incidental. Documentation only. | G12: 9 | H12: Type a single 9. The search runs and behaves normally. | I12: None

Sheet Ticket to create
A1: Ticket to be created for the one real defect
A2: Everything below is ready to paste. Nothing needs to be worked out again. Raise it as written — the shape follows our standing rules for a defect ticket.
A4: Summary (the ticket title) | B4: Global Search: a result row shows only the characters typed, not the full value that matched
A5: Issue type | B5: Story Defect (NOT "Story Defect - Archive")
A6: Parent | B6: SV-9170 — FE — Entity result rows: shared base row, nine variants, badges and match highlighting. The parent must be the OWNING STORY; an Epic parent is rejected with HTTP 400.
A7: Priority | B7: Medium. High is barred by our standing rules — do not raise it.
A8: Links | B8: Also link SV-9170 as "relates to". Link SV-10619 and SV-10551 as "relates to" — this ticket is the root cause of both.
A9: Product Area | B9: Leave empty. This issue type does not carry the field.
A10: Environment | B10: Reproduced on staging, app.staging.shopview.com, workplace "Staging Heavy Duty - 9919", build v26.39.1-97cad2c, on 2026-09-29.
A11: What happens | B11: When a search matches part of a longer value, the result row displays ONLY the characters that were typed instead of the whole value they came from. Type 965 and a customer row reads "Contact match: 965". The telephone number it actually matched — 857-496-5067 — is never shown. Type 3286 and a customer row reads "Contact match: (264) 328-6723" — the WHOLE number. Same field, same kind of match, two different behaviours.
A12: Steps to reproduce | B12: 1. Open global search on staging (Ctrl+K). 2. Type 965. 3. Open the Customers tab and read the second line of each row. 4. Some rows read "Contact match: 965" — only what you typed. 5. Now type 3286 and read the second lines again. 6. Rows now read "Contact match: (264) 328-6723" — the full number. The difference: in step 2 the typed string appears literally inside the stored value; in step 5 it does not, because of the brackets and dash.
A13: Expected | B13: The row shows the COMPLETE value that matched, with the part that was typed highlighted inside it — e.g. "Contact match: 857-496-5067" with 965 marked. Quoted from Global Search - Product Requirements v1.5 (2026-09-08), section 5.3: "The matched substring of the query is highlighted in the primary and secondary text — searching `Fib` highlights "Fib" in "S1-644 Fibridge Commercial"." The example in the specification is decisive: the query was three characters and what the row shows is the whole of "S1-644 Fibridge Commercial".
A14: Actual | B14: The row shows only the typed characters, so two different records can draw identically and cannot be told apart.
A15: Why it matters | B15: This is the whole purpose of a result row. Story SV-9170: "Each result row carries enough context to pick the right record without opening it ... which is what tells two of the same customer's work orders apart." Concretely: search 123786 and 185786 both draw as "786". The user cannot tell which record is which without opening both, and cannot even tell that they are different records.
... A20: Already-raised tickets this explains | B20: SV-10619 — "Some search results show "...." for the match instead of the full match." SV-10551 — "Not providing the complete Unit number it is matching with." Both are symptoms of this one cause. Consider closing them against this ticket rather than fixing them separately.
